Workbook
Name Slicer_carrier_name: #N/A
Name Slicer_cost_per_mile: #N/A
Name Slicer_customer_name: #N/A
Name Slicer_deadhead_miles: #N/A
Name Slicer_driver_pay_total: #N/A
Name Slicer_empty_miles: #N/A
Name Slicer_truck_types: #N/A
Name Slicer_variable_cost_per_mile: #N/A
Name Slicer_Years__scheduled_delivery_datetime: #N/A

Sheet dim_fleet_260
A1: truck_id | B1: driver_id | C1: carrier_id | D1: carrier_name | E1: truck_type | F1: truck_model_year | G1: home_terminal_state | H1: home_terminal_city | I1: insurance_policy_id | J1: insurance_coverage_limit_usd | K1: insurance_deductible_usd | L1: insurance_premium_monthly_usd | M1: insurance_claims_12m | N1: safety_score | O1: maintenance_interval_days | P1: last_maintenance_date | Q1: next_maintenance_due | R1: maintenance_overdue_flag | S1: epr_compliant_flag | T1: epr_audit_score | U1: hazmat_certified_flag
A2: 770487 | B2: 9683481 | C2: 8270 | D2: Desert Road Haulers | E2: Tanker | F2: 2024 | G2: WA | H2: Grand Rapids | I2: 26784725 | J2: 1000000 | K2: 2500 | L2: 1909.09 | M2: 0 | N2: 80 | O2: 45 | P2: 45769 | Q2: 45814 | R2: 0 | S2: 0 | T2: 73.7 | U2: 0
A3: 216739 | B3: 8574680 | C3: 1860 | D3: Pacific Linehaul | E3: Intermodal | F3: 2021 | G3: TX | H3: El Paso | I3: 24081983 | J3: 2000000 | K3: 5000 | L3: 1656.09 | M3: 0 | N3: 76.1 | O3: 45 | P3: 45768 | Q3: 45813 | R3: 0 | S3: 1 | T3: 97.1 | U3: 0
A4: 126225 | B4: 3030113 | C4: 6390 | D4: Midwest Express Trucking | E4: Dry Van | F4: 2011 | G4: WA | H4: Everett | I4: 25137284 | J4: 3000000 | K4: 1000 | L4: 1538.42 | M4: 0 | N4: 83.5 | O4: 30 | P4: 45742 | Q4: 45772 | R4: 0 | S4: 1 | T4: 83 | U4: 0
A5: 877572 | B5: 5159166 | C5: 6191 | D5: Great Lakes Carriers | E5: Reefer | F5: 2025 | G5: TN | H5: Knoxville | I5: 29756883 | J5: 1000000 | K5: 1000 | L5: 1866.24 | M5: 0 | N5: 86 | O5: 45 | P5: 45658 | Q5: 45703 | R5: 0 | S5: 0 | T5: 78.2 | U5: 0
A6: 388389 | B6: 4769795 | C6: 6734 | D6: Pacific Linehaul | E6: Dry Van | F6: 2021 | G6: MI | H6: Flint | I6: 26191135 | J6: 2000000 | K6: 1000 | L6: 1638.04 | M6: 1 | N6: 68.2 | O6: 45 | P6: 45924 | Q6: 45969 | R6: 0 | S6: 1 | T6: 86.6 | U6: 0
A7: 356787 | B7: 2074176 | C7: 7265 | D7: Great Lakes Carriers | E7: Dry Van | F7: 2016 | G7: NC | H7: Durham | I7: 27939993 | J7: 1000000 | K7: 5000 | L7: 1871.91 | M7: 2 | N7: 86.7 | O7: 30 | P7: 46010 | Q7: 46040 | R7: 0 | S7: 1 | T7: 87.6 | U7: 0
A8: 334053 | B8: 6672134 | C8: 1466 | D8: Keystone Freight | E8: Dry Van | F8: 2012 | G8: NJ | H8: Trenton | I8: 29285735 | J8: 1000000 | K8: 2500 | L8: 1442.49 | M8: 1 | N8: 77.1 | O8: 60 | P8: 45739 | Q8: 45799 | R8: 0 | S8: 1 | T8: 88.6 | U8: 0
A9: 246316 | B9: 1352896 | C9: 5426 | D9: Lone Star Transport | E9: Dry Van | F9: 2023 | G9: WA | H9: Tacoma | I9: 28907391 | J9: 3000000 | K9: 2500 | L9: 1566.51 | M9: 1 | N9: 78.2 | O9: 45 | P9: 45900 | Q9: 45945 | R9: 0 | S9: 1 | T9: 89.8 | U9: 0
A10: 872246 | B10: 4860684 | C10: 6578 | D10: Keystone Freight | E10: Reefer | F10: 2021 | G10: AZ | H10: Flagstaff | I10: 25767292 | J10: 2000000 | K10: 5000 | L10: 2355.31 | M10: 2 | N10: 80.4 | O10: 60 | P10: 45928 | Q10: 45988 | R10: 0 | S10: 1 | T10: 87.2 | U10: 0
A11: 207473 | B11: 4694634 | C11: 9322 | D11: Blue Ridge Logistics | E11: Dry Van | F11: 2019 | G11: NJ | H11: Trenton | I11: 27138769 | J11: 2000000 | K11: 5000 | L11: 1479.49 | M11: 1 | N11: 80.1 | O11: 60 | P11: 45967 | Q11: 46027 | R11: 0 | S11: 1 | T11: 89.5 | U11: 0
A12: 809570 | B12: 1120642 | C12: 2685 | D12: Pacific Linehaul | E12: Tanker | F12: 2024 | G12: MI | H12: Grand Rapids | I12: 29233986 | J12: 3000000 | K12: 2500 | L12: 2235.23 | M12: 0 | N12: 90.6 | O12: 30 | P12: 45812 | Q12: 45842 | R12: 0 | S12: 0 | T12: 84 | U12: 0
A13: 876646 | B13: 2191066 | C13: 1769 | D13: Blue Ridge Logistics | E13: Tanker | F13: 2023 | G13: MO | H13: St. Louis | I13: 25549757 | J13: 3000000 | K13: 5000 | L13: 2037.21 | M13: 0 | N13: 84.6 | O13: 60 | P13: 45768 | Q13: 45828 | R13: 0 | S13: 0 | T13: 79.9 | U13: 0
... A261: 559381 | B261: 4526280 | C261: 9754 | D261: Keystone Freight | E261: Reefer | F261: 2024 | G261: AZ | H261: Tucson | I261: 23918527 | J261: 1000000 | K261: 1000 | L261: 2089.22 | M261: 1 | N261: 83.4 | O261: 45 | P261: 45696 | Q261: 45741 | R261: 0 | S261: 1 | T261: 84.5 | U261: 0

Sheet fact_orders_1000
A1: order_id | B1: truck_id | C1: driver_id | D1: carrier_id | E1: carrier_name | F1: customer_id | G1: customer_name | H1: shipping_dat | I1: ship_date_clean | J1: pickup_datetime | K1: scheduled_delivery_datetime | L1: actual_delivery_datetime | M1: delivery_date | N1: origin_state | O1: origin_city | P1: destination_state | Q1: destination_city | R1: region | S1: lane_id | T1: lanes_usa | U1: distance_miles | V1: empty_miles | W1: deadhead_miles | X1: loaded_miles | Y1: total_miles | Z1: truck_types | AA1: delivery_times | AB1: pickup_time_bucket | AC1: day_of_the_week | AD1: Delay Reason | AE1: delay_minutes | AF1: detention_minutes | AG1: weather_severity_index | AH1: traffic_index | AI1: mechanical_flag | AJ1: utilization_rate | AK1: load_factor | AL1: shipment_value_usd | AM1: shipment_value_bucket | AN1: total_shipments | AO1: on_time_deliveries | AP1: late_deliveries | AQ1: on_time_count | AR1: Late_count | AS1: on_time_flag | AT1: late_flag | AU1: cost_per_mile | AV1: variable_cost_per_mile | AW1: fuel_cost_total | AX1: maintenance_cost_total | AY1: driver_pay_total | AZ1: insurance_risk_score | BA1: maintenance_risk_score
A2: 545478870 | B2: 220116 | C2: 6933742 | D2: 5218 | E2: Sunbelt Haulage | F2: 52666 | G2: Coca-Cola Bottling | H2: 45818 | I2: 45818 | J2: 45818.76 | K2: 45818.949 | L2: 45818.93 | M2: 45818 | N2: OH | O2: Toledo | P2: OH | Q2: Cleveland | R2: Midwest | S2: 797593 | T2: 101-300 | U2: 224 | V2: 9.3 | W2: 20.3 | X2: 218.4 | Y2: 248 | Z2: Dry Van | AA2: 4.07 | AB2: 18:00-23:59 | AC2: Tuesday | AE2: -27 | AF2: 0 | AG2: 0 | AH2: 30.2 | AI2: 0 | AJ2: 0.805 | AK2: 0.576 | AL2: 3050.4 | AM2: Low | AN2: 1 | AO2: 1 | AP2: 0 | AQ2: 1 | AR2: 0 | AS2: 1 | AT2: 0 | AU2: 2.03 | AV2: 1.51 | AW2: 215.13 | AX2: 50.82 | AY2: 146.57 | AZ2: 31.9 | BA2: 44.5
A3: 803217037 | B3: 974628 | C3: 3641282 | D3: 6892 | E3: Sunbelt Haulage | F3: 58655 | G3: Target DC | H3: 45766 | I3: 45766 | J3: 45766.479 | K3: 45766.666 | L3: 45766.645 | M3: 45766 | N3: TN | O3: Chattanooga | P3: TN | Q3: Memphis | R3: South | S3: 733303 | T3: 101-300 | U3: 201 | V3: 28.7 | W3: 2.7 | X3: 199.4 | Y3: 230.8 | Z3: Dry Van | AA3: 3.97 | AB3: 10:00-13:59 | AC3: Saturday | AE3: -31 | AF3: 0 | AG3: 0 | AH3: 27.9 | AI3: 0 | AJ3: 0.87 | AK3: 0.774 | AL3: 2754.27 | AM3: Low | AN3: 1 | AO3: 1 | AP3: 0 | AQ3: 1 | AR3: 0 | AS3: 1 | AT3: 0 | AU3: 2.28 | AV3: 1.73 | AW3: 201.01 | AX3: 43.43 | AY3: 160.22 | AZ3: 1.4 | BA3: 13.1
A4: 206323670 | B4: 198246 | C4: 9626108 | D4: 5555 | E4: Sunbelt Haulage | F4: 55968 | G4: Costco Distribution | H4: 45824 | I4: 45824 | J4: 45824.09 | K4: 45824.213 | L4: 45824.204 | M4: 45824 | N4: CA | O4: Fresno | P4: TN | Q4: Chattanooga | R4: South | S4: 747187 | T4: 101-300 | U4: 166 | V4: 36.8 | W4: 9.4 | X4: 162.2 | Y4: 208.4 | Z4: Intermodal | AA4: 2.72 | AB4: 00:00-05:59 | AC4: Monday | AE4: -13 | AF4: 0 | AG4: 0 | AH4: 31.9 | AI4: 0 | AJ4: 0.664 | AK4: 0.544 | AL4: 3026.58 | AM4: Low | AN4: 1 | AO4: 1 | AP4: 0 | AQ4: 1 | AR4: 0 | AS4: 1 | AT4: 0 | AU4: 1.87 | AV4: 1.21 | AW4: 183.12 | AX4: 29.36 | AY4: 135.98 | AZ4: 11.5 | BA4: 5.4
A5: 995171130 | B5: 584714 | C5: 5004485 | D5: 7938 | E5: Blue Ridge Logistics | F5: 57641 | G5: Target DC | H5: 45683 | I5: 45683 | J5: 45683.663 | K5: 45683.726 | L5: 45683.714 | M5: 45683 | N5: OH | O5: Cincinnati | P5: AZ | Q5: Flagstaff | R5: West | S5: 759297 | T5: 0-100 | U5: 46 | V5: 24.5 | W5: 50.7 | X5: 49 | Y5: 124.2 | Z5: Dry Van | AA5: 1.22 | AB5: 14:00-17:59 | AC5: Sunday | AE5: -17 | AF5: 0 | AG5: 0 | AH5: 49.2 | AI5: 0 | AJ5: 0.654 | AK5: 0.699 | AL5: 1358.53 | AM5: Low | AN5: 1 | AO5: 1 | AP5: 0 | AQ5: 1 | AR5: 0 | AS5: 1 | AT5: 0 | AU5: 2.11 | AV5: 1.67 | AW5: 78.37 | AX5: 25.85 | AY5: 64.72 | AZ5: 0.2 | BA5: 49.4
A6: 625432379 | B6: 835911 | C6: 7774229 | D6: 3454 | E6: Cascade Cargo | F6: 52181 | G6: Costco Distribution | H6: 45949 | I6: 45949 | J6: 45949.326 | K6: 45949.535 | L6: 45949.519 | M6: 45949 | N6: FL | O6: Orlando | P6: FL | Q6: Jacksonville | R6: South | S6: 758654 | T6: 101-300 | U6: 187 | V6: 47.9 | W6: 3.4 | X6: 191.8 | Y6: 243.1 | Z6: Reefer | AA6: 4.63 | AB6: 06:00-09:59 | AC6: Sunday | AE6: -22 | AF6: 37 | AG6: 0 | AH6: 49.4 | AI6: 0 | AJ6: 0.678 | AK6: 0.319 | AL6: 4480.11 | AM6: Low | AN6: 1 | AO6: 1 | AP6: 0 | AQ6: 1 | AR6: 0 | AS6: 1 | AT6: 0 | AU6: 2.43 | AV6: 1.42 | AW6: 223.18 | AX6: 47.37 | AY6: 128.76 | AZ6: 11.7 | BA6: 55.9
A7: 761051532 | B7: 972064 | C7: 2818692 | D7: 8158 | E7: Blue Ridge Logistics | F7: 59834 | G7: UPS Supply Chain | H7: 45746 | I7: 45746 | J7: 45746.587 | K7: 45746.928 | L7: 45746.905 | M7: 45746 | N7: CA | O7: Fresno | P7: OH | Q7: Columbus | R7: Midwest | S7: 752047 | T7: 101-300 | U7: 284 | V7: 10.4 | W7: 29.8 | X7: 279.8 | Y7: 320 | Z7: Reefer | AA7: 7.63 | AB7: 14:00-17:59 | AC7: Sunday | AE7: -34 | AF7: 0 | AG7: 0 | AH7: 87 | AI7: 0 | AJ7: 0.777 | AK7: 0.484 | AL7: 5631.22 | AM7: Low | AN7: 1 | AO7: 1 | AP7: 0 | AQ7: 1 | AR7: 0 | AS7: 1 | AT7: 0 | AU7: 2.32 | AV7: 1.59 | AW7: 246.65 | AX7: 48.5 | AY7: 216.14 | AZ7: 10 | BA7: 36.6
A8: 538211092 | B8: 145561 | C8: 2564689 | D8: 1161 | E8: Great Lakes Carriers | F8: 53888 | G8: Tyson Foods | H8: 45922 | I8: 45922 | J8: 45922.41 | K8: 45922.665 | L8: 45922.648 | M8: 45922 | N8: AZ | O8: Flagstaff | P8: GA | Q8: Macon | R8: South | S8: 700025 | T8: 101-300 | U8: 312 | V8: 19.8 | W8: 0.7 | X8: 306.8 | Y8: 327.3 | Z8: Dry Van | AA8: 5.72 | AB8: 06:00-09:59 | AC8: Monday | AE8: -24 | AF8: 0 | AG8: 0 | AH8: 9 | AI8: 0 | AJ8: 0.523 | AK8: 0.791 | AL8: 5672.69 | AM8: Low | AN8: 1 | AO8: 1 | AP8: 0 | AQ8: 1 | AR8: 0 | AS8: 1 | AT8: 0 | AU8: 2.43 | AV8: 1.55 | AW8: 288.62 | AX8: 65.74 | AY8: 190.54 | AZ8: 5.6 | BA8: 0
A9: 400368694 | B9: 891952 | C9: 3135534 | D9: 2218 | E9: Pacific Linehaul | F9: 50840 | G9: IKEA Distribution | H9: 45682 | I9: 45682 | J9: 45682.51 | K9: 45682.841 | L9: 45682.832 | M9: 45682 | N9: AZ | O9: Tucson | P9: CO | Q9: Denver | R9: West | S9: 795199 | T9: 301-500 | U9: 390 | V9: 27 | W9: 24 | X9: 395.1 | Y9: 446.1 | Z9: Flatbed | AA9: 7.73 | AB9: 10:00-13:59 | AC9: Saturday | AE9: -12 | AF9: 0 | AG9: 0 | AH9: 35.9 | AI9: 0 | AJ9: 0.515 | AK9: 0.54 | AL9: 9867.64 | AM9: Medium | AN9: 1 | AO9: 1 | AP9: 0 | AQ9: 1 | AR9: 0 | AS9: 1 | AT9: 0 | AU9: 2.35 | AV9: 1.75 | AW9: 397.71 | AX9: 59.15 | AY9: 240.79 | AZ9: 4.1 | BA9: 57.6
A10: 135128844 | B10: 322086 | C10: 7751158 | D10: 4987 | E10: Cascade Cargo | F10: 55899 | G10: Amazon Fulfillment | H10: 46006 | I10: 46006 | J10: 46006.747 | K10: 46006.933 | L10: 46007.198 | M10: 46007 | N10: NJ | O10: Jersey City | P10: CO | Q10: Pueblo | R10: West | S10: 704543 | T10: 101-300 | U10: 189 | V10: 19.2 | W10: 26.6 | X10: 183.1 | Y10: 228.9 | Z10: Intermodal | AA10: 10.83 | AB10: 14:00-17:59 | AC10: Monday | AD10: mechanical | AE10: 381 | AF10: 0 | AG10: 0 | AH10: 38.5 | AI10: 1 | AJ10: 0.725 | AK10: 0.595 | AL10: 2362.61 | AM10: Low | AN10: 1 | AO10: 0 | AP10: 1 | AQ10: 0 | AR10: 1 | AS10: 0 | AT10: 1 | AU10: 1.89 | AV10: 1.43 | AW10: 177.25 | AX10: 552.41 | AY10: 133.09 | AZ10: 23.2 | BA10: 66.3
A11: 841183219 | B11: 145561 | C11: 2564689 | D11: 1161 | E11: Great Lakes Carriers | F11: 54118 | G11: IKEA Distribution | H11: 45728 | I11: 45728 | J11: 45728.882 | K11: 45728.944 | L11: 45728.949 | M11: 45728 | N11: TN | O11: Chattanooga | P11: NY | Q11: Buffalo | R11: Northeast | S11: 737287 | T11: 0-100 | U11: 96 | V11: 17.7 | W11: 21.8 | X11: 94.3 | Y11: 133.8 | Z11: Dry Van | AA11: 1.62 | AB11: 18:00-23:59 | AC11: Wednesday | AE11: 7 | AF11: 0 | AG11: 0 | AH11: 68.8 | AI11: 0 | AJ11: 0.8 | AK11: 0.575 | AL11: 849.69 | AM11: Low | AN11: 1 | AO11: 1 | AP11: 0 | AQ11: 1 | AR11: 0 | AS11: 1 | AT11: 0 | AU11: 2.13 | AV11: 1.62 | AW11: 85.01 | AX11: 15.22 | AY11: 69.41 | AZ11: 5.6 | BA11: 0
A12: 497853519 | B12: 996865 | C12: 2022698 | D12: 6463 | E12: Keystone Freight | F12: 50565 | G12: Walmart DC | H12: 45980 | I12: 45980 | J12: 45980.368 | K12: 45980.596 | L12: 45980.595 | M12: 45980 | N12: NJ | O12: Paterson | P12: PA | Q12: Erie | R12: Northeast | S12: 778087 | T12: 101-300 | U12: 196 | V12: 35.1 | W12: 6.5 | X12: 189.9 | Y12: 231.5 | Z12: Dry Van | AA12: 5.45 | AB12: 06:00-09:59 | AC12: Wednesday | AE12: -1 | AF12: 0 | AG12: 0 | AH12: 69.5 | AI12: 0 | AJ12: 0.434 | AK12: 0.776 | AL12: 7849.3 | AM12: Medium | AN12: 1 | AO12: 1 | AP12: 0 | AQ12: 1 | AR12: 0 | AS12: 1 | AT12: 0 | AU12: 2.1 | AV12: 1.36 | AW12: 185.02 | AX12: 47.2 | AY12: 160.66 | AZ12: 8.8 | BA12: 26.7
A13: 333291547 | B13: 955662 | C13: 8315831 | D13: 9445 | E13: Blue Ridge Logistics | F13: 56005 | G13: IKEA Distribution | H13: 45953 | I13: 45953 | J13: 45953.413 | K13: 45953.594 | L13: 45953.599 | M13: 45953 | N13: MI | O13: Detroit | P13: NC | Q13: Greensboro | R13: South | S13: 702136 | T13: 101-300 | U13: 223 | V13: 7 | W13: 23.9 | X13: 219.4 | Y13: 250.3 | Z13: Intermodal | AA13: 4.45 | AB13: 06:00-09:59 | AC13: Thursday | AE13: 6 | AF13: 0 | AG13: 0 | AH13: 44.4 | AI13: 0 | AJ13: 0.894 | AK13: 0.541 | AL13: 2594.62 | AM13: Low | AN13: 1 | AO13: 1 | AP13: 0 | AQ13: 1 | AR13: 0 | AS13: 1 | AT13: 0 | AU13: 1.92 | AV13: 1.23 | AW13: 180.27 | AX13: 46.94 | AY13: 124.44 | AZ13: 18.1 | BA13: 35.9
A14: 576078963 | B14: 891952 | C14: 3135534 | D14: 2218 | E14: Pacific Linehaul | F14: 59156 | G14: Target DC | H14: 46011 | I14: 46011 | J14: 46011.542 | K14: 46012.015 | L14: 46012.023 | M14: 46012 | N14: TN | O14: Nashville | P14: NJ | Q14: Trenton | R14: Northeast | S14: 767844 | T14: 501-1000 | U14: 611 | V14: 38.9 | W14: 20.2 | X14: 602 | Y14: 661.1 | Z14: Flatbed | AA14: 11.56 | AB14: 10:00-13:59 | AC14: Saturday | AE14: 12 | AF14: 0 | AG14: 0 | AH14: 87.2 | AI14: 0 | AJ14: 0.569 | AK14: 0.653 | AL14: 4362.57 | AM14: Low | AN14: 1 | AO14: 1 | AP14: 0 | AQ14: 1 | AR14: 0 | AS14: 1 | AT14: 0 | AU14: 2.48 | AV14: 1.81 | AW14: 450.89 | AX14: 78.21 | AY14: 373.37 | AZ14: 4.1 | BA14: 61.1
A15: 577488537 | B15: 660086 | C15: 6307805 | D15: 2028 | E15: Midwest Express Trucking | F15: 59187 | G15: Target DC | H15: 45832 | I15: 45832 | J15: 45832.795 | K15: 45833.109 | L15: 45833.099 | M15: 45833 | N15: NY | O15: Albany | P15: FL | Q15: Tampa | R15: South | S15: 717705 | T15: 101-300 | U15: 264 | V15: 54.9 | W15: 41.4 | X15: 271.7 | Y15: 368 | Z15: Reefer | AA15: 7.3 | AB15: 18:00-23:59 | AC15: Tuesday | AE15: -14 | AF15: 0 | AG15: 0 | AH15: 27.9 | AI15: 0 | AJ15: 0.877 | AK15: 0.853 | AL15: 2758.69 | AM15: Low | AN15: 1 | AO15: 1 | AP15: 0 | AQ15: 1 | AR15: 0 | AS15: 1 | AT15: 0 | AU15: 2.31 | AV15: 1.81 | AW15: 248.31 | AX15: 37.74 | AY15: 225.83 | AZ15: 15.8 | BA15: 12.3
A16: 353524015 | B16: 301629 | C16: 8633773 | D16: 7331 | E16: Blue Ridge Logistics | F16: 57226 | G16: Kroger Logistics | H16: 45923 | I16: 45923 | J16: 45923.837 | K16: 45924.06 | L16: 45924.06 | M16: 45924 | N16: CA | O16: Oakland | P16: CA | Q16: Fresno | R16: West | S16: 739562 | T16: 101-300 | U16: 219 | V16: 51.8 | W16: 17.7 | X16: 225.1 | Y16: 294.6 | Z16: Flatbed | AA16: 5.37 | AB16: 18:00-23:59 | AC16: Tuesday | AE16: 1 | AF16: 36 | AG16: 0 | AH16: 35.5 | AI16: 0 | AJ16: 0.511 | AK16: 0.662 | AL16: 7206.36 | AM16: Medium | AN16: 1 | AO16: 1 | AP16: 0 | AQ16: 1 | AR16: 0 | AS16: 1 | AT16: 0 | AU16: 2.2 | AV16: 1.4 | AW16: 232.08 | AX16: 43.24 | AY16: 203.18 | AZ16: 63.5 | BA16: 7.8
A17: 489431174 | B17: 321231 | C17: 3646552 | D17: 5636 | E17: Blue Ridge Logistics | F17: 59379 | G17: Best Buy DC | H17: 45793 | I17: 45793 | J17: 45793.365 | K17: 45793.572 | L17: 45793.565 | M17: 45793 | N17: TX | O17: San Antonio | P17: TN | Q17: Knoxville | R17: South | S17: 700860 | T17: 101-300 | U17: 278 | V17: 10.5 | W17: 33 | X17: 273.2 | Y17: 316.7 | Z17: Dry Van | AA17: 4.8 | AB17: 06:00-09:59 | AC17: Friday | AE17: -11 | AF17: 0 | AG17: 0 | AH17: 24.3 | AI17: 0 | AJ17: 0.48 | AK17: 0.517 | AL17: 93625.04 | AM17: High | AN17: 1 | AO17: 1 | AP17: 0 | AQ17: 1 | AR17: 0 | AS17: 1 | AT17: 0 | AU17: 2.25 | AV17: 1.76 | AW17: 206.28 | AX17: 57.33 | AY17: 211.42 | AZ17: 37.8 | BA17: 13.1
A18: 206681214 | B18: 724834 | C18: 1701771 | D18: 6249 | E18: Midwest Express Trucking | F18: 55890 | G18: Walmart DC | H18: 45725 | I18: 45725 | J18: 45725.354 | K18: 45726.207 | L18: 45726.214 | M18: 45726 | N18: PA | O18: Pittsburgh | P18: PA | Q18: Harrisburg | R18: Northeast | S18: 739365 | T18: 501-1000 | U18: 925 | V18: 22.7 | W18: 2.4 | X18: 927.8 | Y18: 952.9 | Z18: Reefer | AA18: 20.64 | AB18: 06:00-09:59 | AC18: Sunday | AE18: 11 | AF18: 0 | AG18: 1.3 | AH18: 57.4 | AI18: 0 | AJ18: 0.65 | AK18: 0.758 | AL18: 4470.16 | AM18: Low | AN18: 1 | AO18: 1 | AP18: 0 | AQ18: 1 | AR18: 0 | AS18: 1 | AT18: 0 | AU18: 2.61 | AV18: 1.85 | AW18: 825.68 | AX18: 127.67 | AY18: 462.52 | AZ18: 4.4 | BA18: 14.8
A19: 836243579 | B19: 496922 | C19: 9075854 | D19: 8869 | E19: Blue Ridge Logistics | F19: 54311 | G19: Target DC | H19: 45819 | I19: 45819 | J19: 45819.528 | K19: 45819.82 | L19: 45819.78 | M19: 45819 | N19: TX | O19: Dallas | P19: GA | Q19: Macon | R19: South | S19: 729083 | T19: 301-500 | U19: 339 | V19: 27.2 | W19: 11.7 | X19: 330.4 | Y19: 369.3 | Z19: Flatbed | AA19: 6.06 | AB19: 10:00-13:59 | AC19: Wednesday | AE19: -57 | AF19: 0 | AG19: 0 | AH19: 42 | AI19: 0 | AJ19: 0.696 | AK19: 0.7 | AL19: 3499.83 | AM19: Low | AN19: 1 | AO19: 1 | AP19: 0 | AQ19: 1 | AR19: 0 | AS19: 1 | AT19: 0 | AU19: 2 | AV19: 1.48 | AW19: 254.15 | AX19: 80.06 | AY19: 250.41 | AZ19: 9.3 | BA19: 24.7
A20: 494422907 | B20: 456699 | C20: 1415846 | D20: 1197 | E20: Pacific Linehaul | F20: 57736 | G20: UPS Supply Chain | H20: 45718 | I20: 45718 | J20: 45718.33 | K20: 45718.554 | L20: 45718.536 | M20: 45718 | N20: CO | O20: Aurora | P20: PA | Q20: Philadelphia | R20: Northeast | S20: 728157 | T20: 101-300 | U20: 258 | V20: 45 | W20: 6.1 | X20: 261.7 | Y20: 312.8 | Z20: Reefer | AA20: 4.95 | AB20: 06:00-09:59 | AC20: Sunday | AE20: -25 | AF20: 0 | AG20: 0 | AH20: 74.2 | AI20: 0 | AJ20: 0.809 | AK20: 0.649 | AL20: 4543.23 | AM20: Low | AN20: 1 | AO20: 1 | AP20: 0 | AQ20: 1 | AR20: 0 | AS20: 1 | AT20: 0 | AU20: 2.24 | AV20: 1.52 | AW20: 245.48 | AX20: 66.36 | AY20: 198.05 | AZ20: 15.2 | BA20: 14.2
A21: 684615760 | B21: 872246 | C21: 4860684 | D21: 6578 | E21: Keystone Freight | F21: 58848 | G21: Home Depot RDC | H21: 46016 | I21: 46016 | J21: 46016.458 | K21: 46016.724 | L21: 46016.718 | M21: 46016 | N21: NJ | O21: Jersey City | P21: AZ | Q21: Tucson | R21: West | S21: 741275 | T21: 101-300 | U21: 277 | V21: 25.8 | W21: 27.7 | X21: 271.7 | Y21: 325.2 | Z21: Reefer | AA21: 6.22 | AB21: 10:00-13:59 | AC21: Thursday | AE21: -9 | AF21: 0 | AG21: 0.8 | AH21: 81.4 | AI21: 0 | AJ21: 0.813 | AK21: 0.202 | AL21: 4572.32 | AM21: Low | AN21: 1 | AO21: 1 | AP21: 0 | AQ21: 1 | AR21: 0 | AS21: 1 | AT21: 0 | AU21: 2.17 | AV21: 1.64 | AW21: 213.86 | AX21: 55.85 | AY21: 166.5 | AZ21: 41.8 | BA21: 16.6
A22: 792377512 | B22: 872246 | C22: 4860684 | D22: 6578 | E22: Keystone Freight | F22: 52982 | G22: Amazon Fulfillment | H22: 45693 | I22: 45693 | J22: 45693.34 | K22: 45693.46 | L22: 45693.456 | M22: 45693 | N22: CA | O22: Sacramento | P22: OH | Q22: Dayton | R22: Midwest | S22: 752047 | T22: 101-300 | U22: 179 | V22: 45 | W22: 12.8 | X22: 186.3 | Y22: 244.1 | Z22: Reefer | AA22: 2.78 | AB22: 06:00-09:59 | AC22: Wednesday | AE22: -5 | AF22: 0 | AG22: 0 | AH22: 74.8 | AI22: 0 | AJ22: 0.447 | AK22: 0.79 | AL22: 21829.52 | AM22: Medium | AN22: 1 | AO22: 1 | AP22: 0 | AQ22: 1 | AR22: 0 | AS22: 1 | AT22: 0 | AU22: 2.2 | AV22: 1.75 | AW22: 214.29 | AX22: 33.65 | AY22: 153.34 | AZ22: 41.8 | BA22: 16.5
... A29: 984968439 | B29: 705397 | C29: 5449368 | D29: 5859 | E29: Blue Ridge Logistics | F29: 58243 | G29: Costco Distribution | H29: 45762 | I29: 45762 | J29: 45762.257 | K29: 45762.489 | L29: 45762.505 | M29: 45762 | N29: MO | O29: Springfield | P29: MO | Q29: Columbia | R29: Midwest | S29: 774798 | T29: 101-300 | U29: 289 | V29: 37.3 | W29: 4 | X29: 290.8 | Y29: 332.1 | Z29: Reefer | AA29: 5.96 | AB29: 06:00-09:59 | AC29: Tuesday | AE29: 24 | AF29: 0 | AG29: 0 | AH29: 49.4 | AI29: 0 | AJ29: 0.394 | AK29: 0.276 | AL29: 18352.92 | AM29: Medium | AN29: 1 | AO29: 0 | AP29: 1 | AQ29: 0 | AR29: 1 | AS29: 0 | AT29: 1 | AU29: 2.18 | AV29: 1.58 | AW29: 217.88 | AX29: 70.39 | AY29: 224.22 | AZ29: 11.4 | BA29: 38.5
A30: 588249062 | B30: 847581 | C30: 3919694 | D30: 9050 | E30: Lone Star Transport | F30: 59553 | G30: Walmart DC | H30: 46001 | I30: 46001 | J30: 46001.59 | K30: 46001.942 | L30: 46002.073 | M30: 46002 | N30: OH | O30: Cleveland | P30: MI | Q30: Flint | R30: Midwest | S30: 774922 | T30: 301-500 | U30: 349 | V30: 0.2 | W30: 29.8 | X30: 354.8 | Y30: 384.8 | Z30: Dry Van | AA30: 11.58 | AB30: 14:00-17:59 | AC30: Wednesday | AD30: weather | AE30: 188 | AF30: 47 | AG30: 5 | AH30: 88.3 | AI30: 0 | AJ30: 0.609 | AK30: 0.799 | AL30: 3349.14 | AM30: Low | AN30: 1 | AO30: 0 | AP30: 1 | AQ30: 0 | AR30: 1 | AS30: 0 | AT30: 1 | AU30: 2.11 | AV30: 1.33 | AW30: 302.12 | AX30: 83.61 | AY30: 242.34 | AZ30: 12.5 | BA30: 30.6
A31: 198433586 | B31: 816751 | C31: 3011363 | D31: 9996 | E31: Lone Star Transport | F31: 59386 | G31: Amazon Fulfillment | H31: 45936 | I31: 45936 | J31: 45936.462 | K31: 45936.581 | L31: 45936.566 | M31: 45936 | N31: MO | O31: Springfield | P31: MO | Q31: Independence | R31: Midwest | S31: 774798 | T31: 101-300 | U31: 153 | V31: 18.9 | W31: 35.8 | X31: 138.3 | Y31: 193 | Z31: Dry Van | AA31: 2.51 | AB31: 10:00-13:59 | AC31: Monday | AE31: -21 | AF31: 0 | AG31: 0 | AH31: 55.6 | AI31: 0 | AJ31: 0.795 | AK31: 0.958 | AL31: 4028.59 | AM31: Low | AN31: 1 | AO31: 1 | AP31: 0 | AQ31: 1 | AR31: 0 | AS31: 1 | AT31: 0 | AU31: 1.99 | AV31: 1.32 | AW31: 131.29 | AX31: 28.27 | AY31: 118.64 | AZ31: 13.3 | BA31: 41.1
A32: 811642514 | B32: 660086 | C32: 6307805 | D32: 2028 | E32: Midwest Express Trucking | F32: 54019 | G32: Home Depot RDC | H32: 46012 | I32: 46012 | J32: 46012.288 | K32: 46012.864 | L32: 46012.936 | M32: 46012 | N32: NC | O32: Wilmington | P32: FL | Q32: Jacksonville | R32: South | S32: 720278 | T32: 501-1000 | U32: 754 | V32: -7.7 | W32: 23.9 | X32: 754.1 | Y32: 778 | Z32: Reefer | AA32: 15.55 | AB32: 06:00-09:59 | AC32: Sunday | AD32: traffic | AE32: 104 | AF32: 0 | AG32: 0 | AH32: 59.6 | AI32: 0 | AJ32: 0.695 | AK32: 0.823 | AL32: 16146.9 | AM32: Medium | AN32: 1 | AO32: 0 | AP32: 1 | AQ32: 0 | AR32: 1 | AS32: 0 | AT32: 1 | AU32: 2.24 | AV32: 1.54 | AW32: 639.39 | AX32: 167.85 | AY32: 505.79 | AZ32: 15.8 | BA32: 14.4
A33: 327746886 | B33: 581141 | C33: 2936571 | D33: 6592 | E33: Sunbelt Haulage | F33: 53138 | G33: Amazon Fulfillment | H33: 45671 | I33: 45671 | J33: 45671.49 | K33: 45671.761 | L33: 45671.752 | M33: 45671 | N33: MO | O33: Independence | P33: CO | Q33: Fort Collins | R33: West | S33: 712358 | T33: 301-500 | U33: 404 | V33: 10.2 | W33: 20.9 | X33: 405.5 | Y33: 436.6 | Z33: Dry Van | AA33: 6.31 | AB33: 10:00-13:59 | AC33: Tuesday | AE33: -13 | AF33: 0 | AG33: 0 | AH33: 30.5 | AI33: 0 | AJ33: 0.494 | AK33: 0.469 | AL33: 20598.45 | AM33: Medium | AN33: 1 | AO33: 1 | AP33: 0 | AQ33: 1 | AR33: 0 | AS33: 1 | AT33: 0 | AU33: 2.06 | AV33: 1.33 | AW33: 363.51 | AX33: 50.89 | AY33: 268.3 | AZ33: 27 | BA33: 51.7
A34: 789024924 | B34: 518373 | C34: 7812810 | D34: 2045 | E34: Pacific Linehaul | F34: 59840 | G34: Best Buy DC | H34: 45762 | I34: 45762 | J34: 45762.115 | K34: 45762.332 | L34: 45762.322 | M34: 45762 | N34: NY | O34: New York | P34: TX | Q34: El Paso | R34: South | S34: 704946 | T34: 101-300 | U34: 151 | V34: 18.9 | W34: 32.9 | X34: 151 | Y34: 202.8 | Z34: Dry Van | AA34: 4.97 | AB34: 00:00-05:59 | AC34: Tuesday | AE34: -15 | AF34: 0 | AG34: 0 | AH34: 51.8 | AI34: 0 | AJ34: 0.656 | AK34: 0.409 | AL34: 1964.01 | AM34: Low | AN34: 1 | AO34: 1 | AP34: 0 | AQ34: 1 | AR34: 0 | AS34: 1 | AT34: 0 | AU34: 2.19 | AV34: 1.6 | AW34: 172.03 | AX34: 24.18 | AY34: 134.65 | AZ34: 21.7 | BA34: 3.7
A35: 786650291 | B35: 946335 | C35: 1247595 | D35: 6675 | E35: Blue Ridge Logistics | F35: 50671 | G35: FedEx Ground Hub | H35: 45729 | I35: 45729 | J35: 45729.694 | K35: 45730.04 | L35: 45730.034 | M35: 45730 | N35: NC | O35: Wilmington | P35: CO | Q35: Colorado Springs | R35: West | S35: 760341 | T35: 301-500 | U35: 352 | V35: 18.6 | W35: 27.4 | X35: 352.1 | Y35: 398.1 | Z35: Dry Van | AA35: 8.15 | AB35: 14:00-17:59 | AC35: Thursday | AE35: -9 | AF35: 43 | AG35: 0 | AH35: 67.2 | AI35: 0 | AJ35: 0.692 | AK35: 0.989 | AL35: 20218.98 | AM35: Medium | AN35: 1 | AO35: 1 | AP35: 0 | AQ35: 1 | AR35: 0 | AS35: 1 | AT35: 0 | AU35: 1.98 | AV35: 1.2 | AW35: 353.7 | AX35: 53.02 | AY35: 246.84 | AZ35: 32.6 | BA35: 7.9
A36: 741180590 | B36: 724834 | C36: 1701771 | D36: 6249 | E36: Midwest Express Trucking | F36: 50777 | G36: Amazon Fulfillment | H36: 45662 | I36: 45662 | J36: 45662.403 | K36: 45662.789 | L36: 45662.818 | M36: 45662 | N36: IL | O36: Rockford | P36: NY | Q36: Buffalo | R36: Northeast | S36: 746616 | T36: 501-1000 | U36: 576 | V36: 34.7 | W36: 4.9 | X36: 574.1 | Y36: 613.7 | Z36: Reefer | AA36: 9.96 | AB36: 06:00-09:59 | AC36: Sunday | AD36: traffic | AE36: 41 | AF36: 0 | AG36: 0.8 | AH36: 89.2 | AI36: 0 | AJ36: 0.694 | AK36: 0.545 | AL36: 5481.45 | AM36: Low | AN36: 1 | AO36: 0 | AP36: 1 | AQ36: 0 | AR36: 1 | AS36: 0 | AT36: 1 | AU36: 2.73 | AV36: 2.11 | AW36: 501.07 | AX36: 95.8 | AY36: 371.17 | AZ36: 4.4 | BA36: 4.7
A37: 122932394 | B37: 220116 | C37: 6933742 | D37: 5218 | E37: Sunbelt Haulage | F37: 54927 | G37: PepsiCo Plant | H37: 45746 | I37: 45746 | J37: 45746.326 | K37: 45746.584 | L37: 45746.924 | M37: 45746 | N37: CA | O37: Fresno | P37: GA | Q37: Augusta | R37: South | S37: 720461 | T37: 101-300 | U37: 259 | V37: 7.9 | W37: 20.1 | X37: 272.5 | Y37: 300.5 | Z37: Dry Van | AA37: 14.34 | AB37: 06:00-09:59 | AC37: Sunday | AD37: detention | AE37: 490 | AF37: 253 | AG37: 0 | AH37: 32.3 | AI37: 0 | AJ37: 0.655 | AK37: 0.709 | AL37: 1464.28 | AM37: Low | AN37: 1 | AO37: 0 | AP37: 1 | AQ37: 0 | AR37: 1 | AS37: 0 | AT37: 1 | AU37: 2 | AV37: 1.37 | AW37: 230.64 | AX37: 36.58 | AY37: 153.98 | AZ37: 31.9 | BA37: 31.5
A38: 154308262 | B38: 883300 | C38: 9479356 | D38: 5413 | E38: Blue Ridge Logistics | F38: 53022 | G38: Procter & Gamble | H38: 45905 | I38: 45905 | J38: 45905.337 | K38: 45905.538 | L38: 45905.52 | M38: 45905 | N38: TX | O38: El Paso | P38: CO | Q38: Fort Collins | R38: West | S38: 718141 | T38: 101-300 | U38: 270 | V38: 3 | W38: 49.1 | X38: 271.5 | Y38: 323.6 | Z38: Dry Van | AA38: 4.4 | AB38: 06:00-09:59 | AC38: Friday | AE38: -25 | AF38: 0 | AG38: 0 | AH38: 49.9 | AI38: 0 | AJ38: 0.704 | AK38: 0.609 | AL38: 58446.66 | AM38: High | AN38: 1 | AO38: 1 | AP38: 0 | AQ38: 1 | AR38: 0 | AS38: 1 | AT38: 0 | AU38: 2.08 | AV38: 1.47 | AW38: 283.56 | AX38: 45.57 | AY38: 191.97 | AZ38: 29.3 | BA38: 20.6
A39: 944814262 | B39: 198246 | C39: 9626108 | D39: 5555 | E39: Sunbelt Haulage | F39: 51860 | G39: Best Buy DC | H39: 45742 | I39: 45742 | J39: 45742.882 | K39: 45743.253 | L39: 45743.223 | M39: 45743 | N39: PA | O39: Pittsburgh | P39: TX | Q39: El Paso | R39: South | S39: 734732 | T39: 301-500 | U39: 396 | V39: 23.7 | W39: 19.2 | X39: 396.7 | Y39: 439.6 | Z39: Intermodal | AA39: 8.2 | AB39: 18:00-23:59 | AC39: Wednesday | AE39: -42 | AF39: 0 | AG39: 0 | AH39: 39.9 | AI39: 0 | AJ39: 0.727 | AK39: 0.701 | AL39: 12980.78 | AM39: Medium | AN39: 1 | AO39: 1 | AP39: 0 | AQ39: 1 | AR39: 0 | AS39: 1 | AT39: 0 | AU39: 2.26 | AV39: 1.62 | AW39: 391.22 | AX39: 49.43 | AY39: 267.79 | AZ39: 11.5 | BA39: 8.7
A40: 458102728 | B40: 724834 | C40: 1701771 | D40: 6249 | E40: Midwest Express Trucking | F40: 53139 | G40: IKEA Distribution | H40: 45843 | I40: 45843 | J40: 45843.49 | K40: 45843.714 | L40: 45843.699 | M40: 45843 | N40: AZ | O40: Tucson | P40: CO | Q40: Pueblo | R40: West | S40: 795199 | T40: 101-300 | U40: 258 | V40: 15 | W40: 35.6 | X40: 263.6 | Y40: 314.2 | Z40: Reefer | AA40: 5.02 hrs | AB40: 10:00-13:59 | AC40: Saturday | AE40: -22 | AF40: 55 | AG40: 0 | AH40: 45.3 | AI40: 0 | AJ40: 0.438 | AK40: 0.785 | AL40: 1457.01 | AM40: Low | AN40: 1 | AO40: 1 | AP40: 0 | AQ40: 1 | AR40: 0 | AS40: 1 | AT40: 0 | AU40: 2.45 | AV40: 1.45 | AW40: 268.49 | AX40: 47.63 | AY40: 197.91 | AZ40: 4.4 | BA40: 19
A41: 361530104 | B41: 719176 | C41: 2130789 | D41: 6311 | E41: Desert Road Haulers | F41: 51074 | G41: Kroger Logistics | H41: 45982 | I41: 45982 | J41: 45982.424 | K41: 45982.618 | L41: 45982.613 | M41: 45982 | N41: NJ | O41: Paterson | P41: NJ | Q41: Elizabeth | R41: Northeast | S41: 748114 | T41: 101-300 | U41: 263 | V41: 28.1 | W41: 16 | X41: 259.6 | Y41: 303.7 | Z41: Dry Van | AA41: 4.54 | AB41: 10:00-13:59 | AC41: Friday | AE41: -8 | AF41: 0 | AG41: 0 | AH41: 76.3 | AI41: 0 | AJ41: 0.676 | AK41: 0.67 | AL41: 3681.84 | AM41: Low | AN41: 1 | AO41: 1 | AP41: 0 | AQ41: 1 | AR41: 0 | AS41: 1 | AT41: 0 | AU41: 2.24 | AV41: 1.67 | AW41: 274.16 | AX41: 60.53 | AY41: 179.01 | AZ41: 17 | BA41: 47.9
A42: 235209737 | B42: 358607 | C42: 5727085 | D42: 6864 | E42: Blue Ridge Logistics | F42: 59908 | G42: FedEx Ground Hub | H42: 45911 | I42: 45911 | J42: 45911.448 | K42: 45911.744 | L42: 45911.819 | M42: 45911 | N42: PA | O42: Harrisburg | P42: CO | Q42: Denver | R42: West | S42: 776304 | T42: 301-500 | U42: 321 | V42: 10.3 | W42: 28.5 | X42: 313.3 | Y42: 352.1 | Z42: Dry Van | AA42: 8.9 | AB42: 10:00-13:59 | AC42: Thursday | AD42: traffic | AE42: 107 | AF42: 0 | AG42: 0 | AH42: 55.7 | AI42: 0 | AJ42: 0.817 | AK42: 0.606 | AL42: 2148.69 | AM42: Low | AN42: 1 | AO42: 0 | AP42: 1 | AQ42: 0 | AR42: 1 | AS42: 0 | AT42: 1 | AU42: 2.22 | AV42: 1.75 | AW42: 321.76 | AX42: 60.35 | AY42: 181.4 | AZ42: 7.3 | BA42: 46
A43: 945011302 | B43: 407757 | C43: 6573147 | D43: 2930 | E43: Great Lakes Carriers | F43: 59475 | G43: Kroger Logistics | H43: 45802 | I43: 45802 | J43: 45802.521 | K43: 45802.856 | L43: 45802.826 | M43: 45802 | N43: NJ | O43: Elizabeth | P43: OH | Q43: Dayton | R43: Midwest | S43: 732749 | T43: 301-500 | U43: 512 | V43: 18.6 | W43: 7.6 | X43: 517.4 | Y43: 543.6 | Z43: Tanker | AA43: 7.32 | AB43: 10:00-13:59 | AC43: Sunday | AE43: -43 | AF43: 0 | AG43: 0 | AH43: 59.7 | AI43: 0 | AJ43: 0.472 | AK43: 0.453 | AL43: 3182.26 | AM43: Low | AN43: 1 | AO43: 1 | AP43: 0 | AQ43: 1 | AR43: 0 | AS43: 1 | AT43: 0 | AU43: 2.4 | AV43: 1.67 | AW43: 378.02 | AX43: 107.21 | AY43: 280.54 | AZ43: 13.8 | BA43: 49.4
A44: 706210987 | B44: 733052 | C44: 2642635 | D44: 8989 | E44: Blue Ridge Logistics | F44: 56763 | G44: Kroger Logistics | H44: 45793 | I44: 45793 | J44: 45793.292 | K44: 45793.555 | L44: 45793.523 | M44: 45793 | N44: CO | O44: Pueblo | P44: FL | Q44: Miami | R44: South | S44: 730539 | T44: 101-300 | U44: 281 | V44: 66.3 | W44: 22.7 | X44: 279 | Y44: 368 | Z44: Reefer | AA44: 5.55 | AB44: 06:00-09:59 | AC44: Friday | AE44: -46 | AF44: 44 | AG44: 0 | AH44: 60.3 | AI44: 0 | AJ44: 0.571 | AK44: 0.678 | AL44: 4610.82 | AM44: Low | AN44: 1 | AO44: 1 | AP44: 0 | AQ44: 1 | AR44: 0 | AS44: 1 | AT44: 0 | AU44: 2.68 | AV44: 1.78 | AW44: 248.44 | AX44: 42.79 | AY44: 240.32 | AZ44: 11.9 | BA44: 15.7
A45: 320337809 | B45: 217301 | C45: 5453786 | D45: 5548 | E45: Midwest Express Trucking | F45: 51986 | G45: Walmart DC | H45: 45824 | I45: 45824 | J45: 45824.625 | K45: 45824.752 | L45: 45824.746 | M45: 45824 | N45: CA | O45: Los Angeles | P45: TN | Q45: Memphis | R45: South | S45: 747187 | T45: 101-300 | U45: 148 | V45: 33.2 | W45: 27.3 | X45: 156.2 | Y45: 216.7 | Z45: Flatbed | AA45: 2.9 | AB45: 14:00-17:59 | AC45: Monday | AE45: -9 | AF45: 0 | AG45: 0 | AH45: 37 | AI45: 0 | AJ45: 0.696 | AK45: 0.591 | AL45: 14346.79 | AM45: Medium | AN45: 1 | AO45: 1 | AP45: 0 | AQ45: 1 | AR45: 0 | AS45: 1 | AT45: 0 | AU45: 2.06 | AV45: 1.55 | AW45: 163.52 | AX45: 32.06 | AY45: 138.42 | AZ45: 13 | BA45: 29.1
A46: 173669588 | B46: 246316 | C46: 1352896 | D46: 5426 | E46: Lone Star Transport | F46: 59193 | G46: Walmart DC | H46: 45722 | I46: 45722 | J46: 45722.288 | K46: 45722.382 | L46: 45722.379 | M46: 45722 | N46: MO | O46: St. Louis | P46: CA | Q46: San Diego | R46: West | S46: 733586 | T46: 101-300 | U46: 145 | V46: 6.8 | W46: 6.7 | X46: 152.8 | Y46: 166.3 | Z46: Dry Van | AA46: 2.18 | AB46: 06:00-09:59 | AC46: Thursday | AE46: -4 | AF46: 0 | AG46: 0 | AH46: 70.1 | AI46: 0 | AJ46: 0.78 | AK46: 0.603 | AL46: 5200.28 | AM46: Low | AN46: 1 | AO46: 1 | AP46: 0 | AQ46: 1 | AR46: 0 | AS46: 1 | AT46: 0 | AU46: 2.19 | AV46: 1.62 | AW46: 152.84 | AX46: 17.41 | AY46: 90.18 | AZ46: 28.1 | BA46: 13.6
A47: 991010113 | B47: 217301 | C47: 5453786 | D47: 5548 | E47: Midwest Express Trucking | F47: 56327 | G47: Kroger Logistics | H47: 45889 | I47: 45889 | J47: 45889.323 | K47: 45889.446 | L47: 45889.426 | M47: 45889 | N47: CA | O47: Los Angeles | P47: MI | Q47: Detroit | R47: Midwest | S47: 739361 | T47: 101-300 | U47: 132 | V47: 44.3 | W47: 6 | X47: 118.1 | Y47: 168.4 | Z47: Flatbed | AA47: 2.47 | AB47: 06:00-09:59 | AC47: Wednesday | AE47: -29 | AF47: 0 | AG47: 0 | AH47: 28.3 | AI47: 0 | AJ47: 0.609 | AK47: 0.942 | AL47: 18492.18 | AM47: Medium | AN47: 1 | AO47: 1 | AP47: 0 | AQ47: 1 | AR47: 0 | AS47: 1 | AT47: 0 | AU47: 2.48 | AV47: 1.79 | AW47: 108.88 | AX47: 24.32 | AY47: 98.85 | AZ47: 13 | BA47: 42.5
A48: 921581473 | B48: 497887 | C48: 5456272 | D48: 5488 | E48: Atlantic Freightways | F48: 51046 | G48: Amazon Fulfillment | H48: 45790 | I48: 45790 | J48: 45790.736 | K48: 45790.799 | L48: 45790.747 | M48: 45790 | N48: MI | O48: Detroit | P48: TX | Q48: Dallas | R48: South | S48: 712046 | T48: 0-100 | U48: 32 | V48: 49.9 | W48: 9.6 | X48: 32.4 | Y48: 91.9 | Z48: Reefer | AA48: 0.27 | AB48: 14:00-17:59 | AC48: Tuesday | AE48: -74 | AF48: 0 | AG48: 0 | AH48: 25.3 | AI48: 0 | AJ48: 0.716 | AK48: 0.791 | AL48: 7071.45 | AM48: Low | AN48: 1 | AO48: 1 | AP48: 0 | AQ48: 1 | AR48: 0 | AS48: 1 | AT48: 0 | AU48: 2.4 | AV48: 1.9 | AW48: 76.61 | AX48: 15.97 | AY48: 50.88 | AZ48: 34.9 | BA48: 63.2
A49: 695076080 | B49: 733052 | C49: 2642635 | D49: 8989 | E49: Blue Ridge Logistics | F49: 52176 | G49: Walmart DC | H49: 45969 | I49: 45969 | J49: 45969.302 | K49: 45969.656 | L49: 45969.627 | M49: 45969 | N49: WA | O49: Everett | P49: AZ | Q49: Flagstaff | R49: West | S49: 774774 | T49: 301-500 | U49: 462 | V49: 32.8 | W49: 41.1 | X49: 468.5 | Y49: 542.4 | Z49: Reefer | AA49: 7.79 | AB49: 06:00-09:59 | AC49: Saturday | AE49: -43 | AF49: 0 | AG49: 0 | AH49: 39.4 | AI49: 0 | AJ49: 0.662 | AK49: 0.963 | AL49: 5520.27 | AM49: Low | AN49: 1 | AO49: 1 | AP49: 0 | AQ49: 1 | AR49: 0 | AS49: 1 | AT49: 0 | AU49: 2.34 | AV49: 1.66 | AW49: 474.74 | AX49: 91.27 | AY49: 283.92 | AZ49: 11.9 | BA49: 17.1
A50: 322433532 | B50: 331148 | C50: 8231838 | D50: 8734 | E50: Blue Ridge Logistics | F50: 52338 | G50: Procter & Gamble | H50: 45934 | I50: 45934 | J50: 45934.285 | K50: 45934.477 | L50: 45934.48 | M50: 45934 | N50: TX | O50: San Antonio | P50: MI | Q50: Ann Arbor | R50: Midwest | S50: 752402 | T50: 101-300 | U50: 205 | V50: 7.9 | W50: 2.1 | X50: 194.5 | Y50: 204.5 | Z50: Dry Van | AA50: 4.68 | AB50: 06:00-09:59 | AC50: Saturday | AE50: 4 | AF50: 0 | AG50: 0 | AH50: 30.4 | AI50: 0 | AJ50: 0.601 | AK50: 0.726 | AL50: 82348.9 | AM50: High | AN50: 1 | AO50: 1 | AP50: 0 | AQ50: 1 | AR50: 0 | AS50: 1 | AT50: 0 | AU50: 2.35 | AV50: 1.49 | AW50: 187.92 | AX50: 21.93 | AY50: 114.17 | AZ50: 5.8 | BA50: 11.6
A51: 729624046 | B51: 736059 | C51: 7851696 | D51: 5493 | E51: Desert Road Haulers | F51: 50500 | G51: Walmart DC | H51: 45880 | I51: 45880 | J51: 45880.5 | K51: 45880.739 | L51: 45880.716 | M51: 45880 | N51: FL | O51: Orlando | P51: IL | Q51: Aurora | R51: Midwest | S51: 774588 | T51: 101-300 | U51: 273 | V51: 40.6 | W51: 19.9 | X51: 275.2 | Y51: 335.7 | Z51: Reefer | AA51: 5.18 | AB51: 10:00-13:59 | AC51: Monday | AE51: -34 | AF51: 0 | AG51: 0 | AH51: 58.9 | AI51: 0 | AJ51: 0.695 | AK51: 0.759 | AL51: 5363.16 | AM51: Low | AN51: 1 | AO51: 1 | AP51: 0 | AQ51: 1 | AR51: 0 | AS51: 1 | AT51: 0 | AU51: 2.46 | AV51: 1.44 | AW51: 270.55 | AX51: 36.07 | AY51: 182.3 | AZ51: 11.5 | BA51: 20
A52: 331875999 | B52: 542417 | C52: 1527021 | D52: 6051 | E52: Sunbelt Haulage | F52: 52233 | G52: PepsiCo Plant | H52: 45790 | I52: 45790 | J52: 45790.549 | K52: 45790.819 | L52: 45790.801 | M52: 45790 | N52: NJ | O52: Paterson | P52: GA | Q52: Savannah | R52: South | S52: 728499 | T52: 101-300 | U52: 265 | V52: 11.6 | W52: 40 | X52: 268.9 | Y52: 320.5 | Z52: Flatbed | AA52: 6.05 | AB52: 10:00-13:59 | AC52: Tuesday | AE52: -26 | AF52: 0 | AG52: 0 | AH52: 94.1 | AI52: 0 | AJ52: 0.768 | AK52: 0.528 | AL52: 4529.54 | AM52: Low | AN52: 1 | AO52: 1 | AP52: 0 | AQ52: 1 | AR52: 0 | AS52: 1 | AT52: 0 | AU52: 2.19 | AV52: 1.49 | AW52: 235.26 | AX52: 43.78 | AY52: 160.18 | AZ52: 27.6 | BA52: 38.3
A53: 973008988 | B53: 476417 | C53: 5191056 | D53: 4073 | E53: Desert Road Haulers | F53: 54608 | G53: Kroger Logistics | H53: 45734 | I53: 45734 | J53: 45734.681 | K53: 45735.475 | L53: 45735.47 | M53: 45735 | N53: MO | O53: Columbia | P53: MO | Q53: Independence | R53: Midwest | S53: 774798 | T53: 501-1000 | U53: 824 | V53: 58.2 | W53: 19.7 | X53: 823.7 | Y53: 901.6 | Z53: Tanker | AA53: 18.96 | AB53: 14:00-17:59 | AC53: Tuesday | AE53: -6 | AF53: 0 | AG53: 0 | AH53: 68.3 | AI53: 0 | AJ53: 0.518 | AK53: 0.8 | AL53: 1865.46 | AM53: Low | AN53: 1 | AO53: 1 | AP53: 0 | AQ53: 1 | AR53: 0 | AS53: 1 | AT53: 0 | AU53: 2.91 | AV53: 2.11 | AW53: 604.03 | AX53: 173.62 | AY53: 541.93 | AZ53: 11.7 | BA53: 16.2
A54: 350180427 | B54: 996865 | C54: 2022698 | D54: 6463 | E54: Keystone Freight | F54: 57234 | G54: General Mills | H54: 45941 | I54: 45941 | J54: 45941.594 | K54: 45941.807 | L54: 45941.79 | M54: 45941 | N54: GA | O54: Columbus | P54: NY | Q54: Albany | R54: Northeast | S54: 796241 | T54: 101-300 | U54: 252 | V54: 17.7 | W54: 22.2 | X54: 251.7 | Y54: 291.6 | Z54: Dry Van | AA54: 4.71 | AB54: 14:00-17:59 | AC54: Saturday | AE54: -25 | AF54: 0 | AG54: 0 | AH54: 45.3 | AI54: 0 | AJ54: 0.693 | AK54: 0.677 | AL54: 3270.96 | AM54: Low | AN54: 1 | AO54: 1 | AP54: 0 | AQ54: 1 | AR54: 0 | AS54: 1 | AT54: 0 | AU54: 2.14 | AV54: 1.32 | AW54: 266.68 | AX54: 29.88 | AY54: 171.52 | AZ54: 8.8 | BA54: 19.4
A55: 452788129 | B55: 518801 | C55: 2548511 | D55: 8994 | E55: Midwest Express Trucking | F55: 57972 | G55: Costco Distribution | H55: 45835 | I55: 45835 | J55: 45835.597 | K55: 45835.66 | L55: 45835.669 | M55: 45835 | N55: FL | O55: Miami | P55: NY | Q55: Rochester | R55: Northeast | S55: 710118 | T55: 0-100 | U55: 21 | V55: 17 | W55: 3.2 | X55: 28.2 | Y55: 48.4 | Z55: Dry Van | AA55: 1.72 | AB55: 14:00-17:59 | AC55: Friday | AE55: 13 | AF55: 0 | AG55: 0 | AH55: 42 | AI55: 0 | AJ55: 0.666 | AK55: 0.441 | AL55: 17426.77 | AM55: Medium | AN55: 1 | AO55: 1 | AP55: 0 | AQ55: 1 | AR55: 0 | AS55: 1 | AT55: 0 | AU55: 2.56 | AV55: 1.5 | AW55: 43.43 | AX55: 8.42 | AY55: 31.53 | AZ55: 7.3 | BA55: 74.7
A56: 931471931 | B56: 787277 | C56: 6022741 | D56: 3693 | E56: Pacific Linehaul | F56: 56610 | G56: Walmart DC | H56: 45740 | I56: 45740 | J56: 45740.747 | K56: 45740.809 | L56: 45740.863 | M56: 45740 | N56: OH | O56: Toledo | P56: PA | Q56: Harrisburg | R56: Northeast | S56: 794841 | T56: 0-100 | U56: 48 | V56: 31.4 | W56: 19.7 | X56: 39 | Y56: 90.1 | Z56: Dry Van | AA56: 2.8 | AB56: 14:00-17:59 | AC56: Monday | AD56: traffic | AE56: 78 | AF56: 0 | AG56: 0 | AH56: 92.3 | AI56: 0 | AJ56: 0.638 | AK56: 0.916 | AL56: 18446.06 | AM56: Medium | AN56: 1 | AO56: 0 | AP56: 1 | AQ56: 0 | AR56: 1 | AS56: 0 | AT56: 1 | AU56: 2.38 | AV56: 1.86 | AW56: 77.61 | AX56: 11 | AY56: 56.66 | AZ56: 3.4 | BA56: 14.8
A57: 258435089 | B57: 308496 | C57: 5076817 | D57: 3747 | E57: Keystone Freight | F57: 50600 | G57: Kroger Logistics | H57: 45729 | I57: 45729 | J57: 45729.281 | K57: 45729.526 | L57: 45729.501 | M57: 45729 | N57: MO | O57: Independence | P57: MO | Q57: St. Louis | R57: Midwest | S57: 774798 | T57: 101-300 | U57: 242 | V57: 47.4 | W57: 1.1 | X57: 247 | Y57: 295.5 | Z57: Intermodal | AA57: 5.27 | AB57: 06:00-09:59 | AC57: Thursday | AE57: -37 | AF57: 0 | AG57: 0 | AH57: 26.7 | AI57: 0 | AJ57: 0.633 | AK57: 0.566 | AL57: 9967.2 | AM57: Medium | AN57: 1 | AO57: 1 | AP57: 0 | AQ57: 1 | AR57: 0 | AS57: 1 | AT57: 0 | AU57: 1.98 | AV57: 1.28 | AW57: 266.88 | AX57: 63.04 | AY57: 166.19 | AZ57: 15.5 | BA57: 57.4
A58: 946799779 | B58: 705397 | C58: 5449368 | D58: 5859 | E58: Blue Ridge Logistics | F58: 54284 | G58: UPS Supply Chain | H58: 45718 | I58: 45718 | J58: 45718.323 | K58: 45718.452 | L58: 45718.458 | M58: 45718 | N58: PA | O58: Allentown | P58: CO | Q58: Fort Collins | R58: West | S58: 776304 | T58: 101-300 | U58: 107 | V58: 64.6 | W58: 22.5 | X58: 109.8 | Y58: 196.9 | Z58: Reefer | AA58: 3.24 | AB58: 06:00-09:59 | AC58: Sunday | AE58: 8 | AF58: 0 | AG58: 0 | AH58: 30.3 | AI58: 0 | AJ58: 0.656 | AK58: 0.703 | AL58: 2000.59 | AM58: Low | AN58: 1 | AO58: 1 | AP58: 0 | AQ58: 1 | AR58: 0 | AS58: 1 | AT58: 0 | AU58: 2.17 | AV58: 1.48 | AW58: 125.67 | AX58: 29.86 | AY58: 117.97 | AZ58: 11.4 | BA58: 31.5
A59: 739930411 | B59: 946335 | C59: 1247595 | D59: 6675 | E59: Blue Ridge Logistics | F59: 59180 | G59: Coca-Cola Bottling | H59: 45941 | I59: 45941 | J59: 45941.427 | K59: 45941.595 | L59: 45941.584 | M59: 45941 | N59: AZ | O59: Mesa | P59: AZ | Q59: Mesa | R59: West | S59: 742558 | T59: 101-300 | U59: 112 | V59: 22.5 | W59: 22.7 | X59: 119.8 | Y59: 165 | Z59: Dry Van | AA59: 3.75 | AB59: 10:00-13:59 | AC59: Saturday | AE59: -17 | AF59: 0 | AG59: 0 | AH59: 54.6 | AI59: 0 | AJ59: 0.37 | AK59: 0.525 | AL59: 2300.38 | AM59: Low | AN59: 1 | AO59: 1 | AP59: 0 | AQ59: 1 | AR59: 0 | AS59: 1 | AT59: 0 | AU59: 2.18 | AV59: 1.31 | AW59: 133.56 | AX59: 17.45 | AY59: 100.43 | AZ59: 32.6 | BA59: 14.8
A60: 103044648 | B60: 733052 | C60: 2642635 | D60: 8989 | E60: Blue Ridge Logistics | F60: 54483 | G60: Home Depot RDC | H60: 45741 | I60: 45741 | J60: 45741.347 | K60: 45741.563 | L60: 45741.534 | M60: 45741 | N60: TN | O60: Chattanooga | P60: TN | Q60: Memphis | R60: South | S60: 733303 | T60: 101-300 | U60: 288 | V60: 14.6 | W60: 19.5 | X60: 282.3 | Y60: 316.4 | Z60: Reefer | AA60: 4.47 | AB60: 06:00-09:59 | AC60: Tuesday | AE60: -42 | AF60: 0 | AG60: 0 | AH60: 38.2 | AI60: 0 | AJ60: 0.547 | AK60: 0.842 | AL60: 5790.99 | AM60: Low | AN60: 1 | AO60: 1 | AP60: 0 | AQ60: 1 | AR60: 0 | AS60: 1 | AT60: 0 | AU60: 2.24 | AV60: 1.49 | AW60: 222.25 | AX60: 58.74 | AY60: 221.55 | AZ60: 11.9 | BA60: 31
A61: 397721596 | B61: 816751 | C61: 3011363 | D61: 9996 | E61: Lone Star Transport | F61: 55901 | G61: Target DC | H61: 45850 | I61: 45850 | J61: 45850.931 | K61: 45851.105 | L61: 45851.1 | M61: 45851 | N61: TN | O61: Memphis | P61: IL | Q61: Rockford | R61: Midwest | S61: 763246 | T61: 0-100 | U61: 81 | V61: 7.2 | W61: 7.6 | X61: 89.9 | Y61: 104.7 | Z61: Dry Van | AA61: 4.06 | AB61: 18:00-23:59 | AC61: Saturday | AE61: -8 | AF61: 0 | AG61: 0 | AH61: 50.1 | AI61: 0 | AJ61: 0.481 | AK61: 0.868 | AL61: 8065.93 | AM61: Medium | AN61: 1 | AO61: 1 | AP61: 0 | AQ61: 1 | AR61: 0 | AS61: 1 | AT61: 0 | AU61: 2.17 | AV61: 1.46 | AW61: 88.96 | AX61: 16.56 | AY61: 74.92 | AZ61: 13.3 | BA61: 36.7
A62: 255357534 | B62: 680099 | C62: 7003042 | D62: 6535 | E62: Great Lakes Carriers | F62: 56129 | G62: IKEA Distribution | H62: 45822 | I62: 45822 | J62: 45822.594 | K62: 45822.783 | L62: 45822.766 | M62: 45822 | N62: CA | O62: San Diego | P62: FL | Q62: Orlando | R62: South | S62: 722662 | T62: 101-300 | U62: 162 | V62: 4.7 | W62: 4.5 | X62: 153.7 | Y62: 162.9 | Z62: Reefer | AA62: 4.14 | AB62: 14:00-17:59 | AC62: Saturday | AE62: -24 | AF62: 0 | AG62: 0 | AH62: 42.1 | AI62: 0 | AJ62: 0.883 | AK62: 0.857 | AL62: 7873.73 | AM62: Low | AN62: 1 | AO62: 1 | AP62: 0 | AQ62: 1 | AR62: 0 | AS62: 1 | AT62: 0 | AU62: 2.49 | AV62: 1.94 | AW62: 105.68 | AX62: 33.52 | AY62: 110.08 | AZ62: 28.3 | BA62: 26.3
A63: 239577989 | B63: 733052 | C63: 2642635 | D63: 8989 | E63: Blue Ridge Logistics | F63: 51754 | G63: Amazon Fulfillment | H63: 45869 | I63: 45869 | J63: 45869.382 | K63: 45869.659 | L63: 45869.629 | M63: 45869 | N63: MO | O63: Springfield | P63: NC | Q63: Durham | R63: South | S63: 790402 | T63: 101-300 | U63: 252 | V63: 3.9 | W63: 12 | X63: 250 | Y63: 265.9 | Z63: Reefer | AA63: 5.93 | AB63: 06:00-09:59 | AC63: Thursday | AE63: -43 | AF63: 0 | AG63: 0 | AH63: 47.5 | AI63: 0 | AJ63: 0.454 | AK63: 0.64 | AL63: 6754.03 | AM63: Low | AN63: 1 | AO63: 1 | AP63: 0 | AQ63: 1 | AR63: 0 | AS63: 1 | AT63: 0 | AU63: 2.51 | AV63: 1.93 | AW63: 185.5 | AX63: 47.39 | AY63: 163.5 | AZ63: 11.9 | BA63: 9.5
A64: 680051935 | B64: 766563 | C64: 9910817 | D64: 1391 | E64: Lone Star Transport | F64: 52464 | G64: PepsiCo Plant | H64: 45978 | I64: 45978 | J64: 45978.135 | K64: 45978.257 | L64: 45978.246 | M64: 45978 | N64: GA | O64: Augusta | P64: NC | Q64: Greensboro | R64: South | S64: 763999 | T64: 0-100 | U64: 91 | V64: 26.2 | W64: 4.8 | X64: 84 | Y64: 115 | Z64: Intermodal | AA64: 2.66 | AB64: 00:00-05:59 | AC64: Monday | AE64: -16 | AF64: 0 | AG64: 0 | AH64: 63.7 | AI64: 0 | AJ64: 0.399 | AK64: 0.559 | AL64: 4873.91 | AM64: Low | AN64: 1 | AO64: 1 | AP64: 0 | AQ64: 1 | AR64: 0 | AS64: 1 | AT64: 0 | AU64: 2.3 | AV64: 1.43 | AW64: 100.63 | AX64: 21.06 | AY64: 80.82 | AZ64: 10 | BA64: 28.3
A65: 369137895 | B65: 319684 | C65: 2149597 | D65: 9392 | E65: Lone Star Transport | F65: 54482 | G65: Home Depot RDC | H65: 45974 | I65: 45974 | J65: 45974.028 | K65: 45974.09 | L65: 45974.076 | M65: 45974 | N65: NJ | O65: Newark | P65: FL | Q65: Jacksonville | R65: South | S65: 790386 | T65: 0-100 | U65: 47 | V65: 41 | W65: 25.4 | X65: 51.3 | Y65: 117.7 | Z65: Tanker | AA65: 1.15 | AB65: 00:00-05:59 | AC65: Thursday | AE65: -21 | AF65: 0 | AG65: 2.5 | AH65: 59.2 | AI65: 0 | AJ65: 0.646 | AK65: 0.582 | AL65: 4754.2 | AM65: Low | AN65: 1 | AO65: 1 | AP65: 0 | AQ65: 1 | AR65: 0 | AS65: 1 | AT65: 0 | AU65: 2.37 | AV65: 1.66 | AW65: 99.44 | AX65: 22.61 | AY65: 61.53 | AZ65: 39.1 | BA65: 12.7
A66: 957397689 | B66: 847581 | C66: 3919694 | D66: 9050 | E66: Lone Star Transport | F66: 59686 | G66: Walmart DC | H66: 45822 | I66: 45822 | J66: 45822.253 | K66: 45822.317 | L66: 45822.278 | M66: 45822 | N66: MO | O66: St. Louis | P66: AZ | Q66: Phoenix | R66: West | S66: 792123 | T66: 0-100 | U66: 23 | V66: 5.7 | W66: 20.3 | X66: 18.4 | Y66: 44.4 | Z66: Dry Van | AA66: 0.6 | AB66: 06:00-09:59 | AC66: Saturday | AE66: -55 | AF66: 0 | AG66: 0 | AH66: 64.5 | AI66: 0 | AJ66: 0.934 | AK66: 0.867 | AL66: 5757.09 | AM66: Low | AN66: 1 | AO66: 1 | AP66: 0 | AQ66: 1 | AR66: 0 | AS66: 1 | AT66: 0 | AU66: 2.19 | AV66: 1.62 | AW66: 40.74 | AX66: 6.68 | AY66: 28.73 | AZ66: 12.5 | BA66: 26.5
A67: 287364857 | B67: 543692 | C67: 6472441 | D67: 5911 | E67: Great Lakes Carriers | F67: 59044 | G67: Target DC | H67: 45663 | I67: 45663 | J67: 45663.361 | K67: 45663.453 | L67: 45663.425 | M67: 45663 | N67: IL | O67: Rockford | P67: AZ | Q67: Mesa | R67: West | S67: 775527 | T67: 0-100 | U67: 103 | V67: 36.2 | W67: 47.8 | X67: 109.8 | Y67: 193.8 | Z67: Dry Van | AA67: 1.53 | AB67: 06:00-09:59 | AC67: Monday | AE67: -41 | AF67: 0 | AG67: 0 | AH67: 59.5 | AI67: 0 | AJ67: 0.475 | AK67: 0.775 | AL67: 50472.46 | AM67: High | AN67: 1 | AO67: 1 | AP67: 0 | AQ67: 1 | AR67: 0 | AS67: 1 | AT67: 0 | AU67: 1.9 | AV67: 1.22 | AW67: 157.6 | AX67: 37.81 | AY67: 114.44 | AZ67: 20.5 | BA67: 57.1
A68: 218032515 | B68: 260263 | C68: 5674183 | D68: 5736 | E68: Lone Star Transport | F68: 57400 | G68: Amazon Fulfillment | H68: 45813 | I68: 45813 | J68: 45813.424 | K68: 45813.576 | L68: 45813.592 | M68: 45813 | N68: NJ | O68: Trenton | P68: MO | Q68: Springfield | R68: Midwest | S68: 712499 | T68: 101-300 | U68: 179 | V68: 6.5 | W68: 10 | X68: 168.9 | Y68: 185.4 | Z68: Reefer | AA68: 4.03 | AB68: 10:00-13:59 | AC68: Thursday | AE68: 23 | AF68: 0 | AG68: 0 | AH68: 60.8 | AI68: 0 | AJ68: 0.705 | AK68: 0.844 | AL68: 2807.25 | AM68: Low | AN68: 1 | AO68: 0 | AP68: 1 | AQ68: 0 | AR68: 1 | AS68: 0 | AT68: 1 | AU68: 2.35 | AV68: 1.57 | AW68: 131.81 | AX68: 19.67 | AY68: 95.43 | AZ68: 30.8 | BA68: 27.3
... A73: 484659715 | B73: 944151 | C73: 6855396 | D73: 8574 | E73: Atlantic Freightways | F73: 59950 | G73: Walmart DC | H73: 45893 | I73: 45893 | J73: 45893.472 | K73: 45893.863 | L73: 45893.859 | M73: 45893 | N73: AZ | O73: Mesa | P73: FL | Q73: Orlando | R73: South | S73: 704898 | T73: 301-500 | U73: 351 | V73: 8.9 | W73: 21.2 | X73: 355.2 | Y73: 385.3 | Z73: Flatbed | AA73: 9.28 | AB73: 10:00-13:59 | AC73: Sunday | AE73: -6 | AF73: 0 | AG73: 0 | AH73: 49.3 | AI73: 0 | AJ73: 0.481 | AK73: 0.792 | AL73: 3077.11 | AM73: Low | AN73: 1 | AO73: 1 | AP73: 0 | AQ73: 1 | AR73: 0 | AS73: 1 | AT73: 0 | AU73: 2.17 | AV73: 1.56 | AW73: 241.53 | AX73: 43.81 | AY73: 214.56 | AZ73: 12.8 | BA73: 31.8
A74: 948239575 | B74: 287330 | C74: 4348276 | D74: 9338 | E74: Great Lakes Carriers | F74: 55241 | G74: Kroger Logistics | H74: 45724 | I74: 45724 | J74: 45724.653 | K74: 45724.767 | L74: 45724.832 | M74: 45724 | N74: NJ | O74: Paterson | P74: NY | Q74: Rochester | R74: Northeast | S74: 795786 | T74: 101-300 | U74: 157 | V74: 7.4 | W74: 47.7 | X74: 149.2 | Y74: 204.3 | Z74: Reefer | AA74: 4.3 | AB74: 14:00-17:59 | AC74: Saturday | AD74: detention | AE74: 94 | AF74: 117 | AG74: 0 | AH74: 67.6 | AI74: 0 | AJ74: 0.39 | AK74: 0.687 | AL74: 14525.67 | AM74: Medium | AN74: 1 | AO74: 0 | AP74: 1 | AQ74: 0 | AR74: 1 | AS74: 0 | AT74: 1 | AU74: 2.6 | AV74: 1.79 | AW74: 149.32 | AX74: 36.3 | AY74: 133.29 | AZ74: 17.5 | BA74: 70.7
A75: 946571918 | B75: 972064 | C75: 2818692 | D75: 8158 | E75: Blue Ridge Logistics | F75: 57394 | G75: Walmart DC | H75: 45931 | I75: 45931 | J75: 45931.681 | K75: 45931.873 | L75: 45932.014 | M75: 45932 | N75: AZ | O75: Tucson | P75: NJ | Q75: Jersey City | R75: Northeast | S75: 775534 | T75: 101-300 | U75: 318 | V75: 33.2 | W75: 29 | X75: 319.3 | Y75: 381.5 | Z75: Reefer | AA75: 7.99 | AB75: 14:00-17:59 | AC75: Wednesday | AD75: detention | AE75: 202 | AF75: 129 | AG75: 0 | AH75: 97.1 | AI75: 0 | AJ75: 0.631 | AK75: 0.873 | AL75: 1449.3 | AM75: Low | AN75: 1 | AO75: 0 | AP75: 1 | AQ75: 0 | AR75: 1 | AS75: 0 | AT75: 1 | AU75: 2.51 | AV75: 1.68 | AW75: 343.58 | AX75: 59.74 | AY75: 198.14 | AZ75: 10 | BA75: 21.8
A76: 355477113 | B76: 217301 | C76: 5453786 | D76: 5548 | E76: Midwest Express Trucking | F76: 56437 | G76: Best Buy DC | H76: 45781 | I76: 45781 | J76: 45781.812 | K76: 45781.998 | L76: 45781.971 | M76: 45781 | N76: NY | O76: Rochester | P76: WA | Q76: Spokane | R76: West | S76: 750010 | T76: 101-300 | U76: 147 | V76: 53.1 | W76: 45.4 | X76: 156.2 | Y76: 254.7 | Z76: Flatbed | AA76: 3.8 | AB76: 18:00-23:59 | AC76: Sunday | AE76: -39 | AF76: 0 | AG76: 0 | AH76: 39 | AI76: 0 | AJ76: 0.25 | AK76: 0.81 | AL76: 65452.65 | AM76: High | AN76: 1 | AO76: 1 | AP76: 0 | AQ76: 1 | AR76: 0 | AS76: 1 | AT76: 0 | AU76: 2.28 | AV76: 1.5 | AW76: 160.92 | AX76: 32.13 | AY76: 166.12 | AZ76: 13 | BA76: 45.5
A77: 732276010 | B77: 391476 | C77: 8999183 | D77: 6618 | E77: Cascade Cargo | F77: 54695 | G77: FedEx Ground Hub | H77: 45917 | I77: 45917 | J77: 45917.514 | K77: 45917.767 | L77: 45917.768 | M77: 45917 | N77: TX | O77: San Antonio | P77: TX | Q77: Houston | R77: South | S77: 710286 | T77: 101-300 | U77: 228 | V77: 51.1 | W77: 27.6 | X77: 225.5 | Y77: 304.2 | Z77: Reefer | AA77: 6.1 | AB77: 10:00-13:59 | AC77: Wednesday | AE77: 2 | AF77: 0 | AG77: 0 | AH77: 40.7 | AI77: 0 | AJ77: 0.33 | AK77: 0.662 | AL77: 4716.94 | AM77: Low | AN77: 1 | AO77: 1 | AP77: 0 | AQ77: 1 | AR77: 0 | AS77: 1 | AT77: 0 | AU77: 2.4 | AV77: 1.48 | AW77: 235.98 | AX77: 32 | AY77: 203.16 | AZ77: 51.7 | BA77: 54.7
A78: 447646966 | B78: 724834 | C78: 1701771 | D78: 6249 | E78: Midwest Express Trucking | F78: 52588 | G78: Tyson Foods | H78: 45675 | I78: 45675 | J78: 45675.736 | K78: 45675.854 | L78: 45675.845 | M78: 45675 | N78: FL | O78: Tampa | P78: TN | Q78: Chattanooga | R78: South | S78: 707329 | T78: 0-100 | U78: 103 | V78: 15.1 | W78: 12.9 | X78: 98.9 | Y78: 126.9 | Z78: Reefer | AA78: 2.6 | AB78: 14:00-17:59 | AC78: Saturday | AE78: -13 | AF78: 0 | AG78: 0 | AH78: 69.8 | AI78: 0 | AJ78: 0.392 | AK78: 0.7 | AL78: 21463.06 | AM78: Medium | AN78: 1 | AO78: 1 | AP78: 0 | AQ78: 1 | AR78: 0 | AS78: 1 | AT78: 0 | AU78: 2.5 | AV78: 1.99 | AW78: 91.87 | AX78: 20.89 | AY78: 79.02 | AZ78: 4.4 | BA78: 0.6
A79: 116944811 | B79: 301629 | C79: 8633773 | D79: 7331 | E79: Blue Ridge Logistics | F79: 51782 | G79: UPS Supply Chain | H79: 45806 | I79: 45806 | J79: 45806.389 | K79: 45806.674 | L79: 45806.661 | M79: 45806 | N79: AZ | O79: Tempe | P79: MO | Q79: Kansas City | R79: Midwest | S79: 743829 | T79: 301-500 | U79: 323 | V79: 18.7 | W79: 23.4 | X79: 325 | Y79: 367.1 | Z79: Flatbed | AA79: 6.54 | AB79: 06:00-09:59 | AC79: Thursday | AE79: -18 | AF79: 0 | AG79: 0 | AH79: 50.2 | AI79: 0 | AJ79: 0.581 | AK79: 0.695 | AL79: 9637.11 | AM79: Medium | AN79: 1 | AO79: 1 | AP79: 0 | AQ79: 1 | AR79: 0 | AS79: 1 | AT79: 0 | AU79: 2.64 | AV79: 1.58 | AW79: 298.77 | AX79: 42.27 | AY79: 198.02 | AZ79: 63.5 | BA79: 18.4
A80: 287095435 | B80: 671858 | C80: 1987737 | D80: 7949 | E80: Desert Road Haulers | F80: 55947 | G80: Tyson Foods | H80: 45915 | I80: 45915 | J80: 45915.417 | K80: 45915.748 | L80: 45915.728 | M80: 45915 | N80: IL | O80: Rockford | P80: CA | Q80: San Diego | R80: West | S80: 745603 | T80: 101-300 | U80: 313 | V80: 0.2 | W80: 31.7 | X80: 311.7 | Y80: 343.6 | Z80: Reefer | AA80: 7.47 | AB80: 10:00-13:59 | AC80: Monday | AE80: -28 | AF80: 0 | AG80: 0 | AH80: 56.2 | AI80: 0 | AJ80: 0.851 | AK80: 0.793 | AL80: 3555.28 | AM80: Low | AN80: 1 | AO80: 1 | AP80: 0 | AQ80: 1 | AR80: 0 | AS80: 1 | AT80: 0 | AU80: 2.15 | AV80: 1.53 | AW80: 229.75 | AX80: 72.68 | AY80: 169.18 | AZ80: 14.1 | BA80: 58.6
A81: 384936197 | B81: 680099 | C81: 7003042 | D81: 6535 | E81: Great Lakes Carriers | F81: 56594 | G81: General Mills | H81: 45740 | I81: 45740 | J81: 45740.333 | K81: 45741.218 | L81: 45741.218 | M81: 45741 | N81: MI | O81: Lansing | P81: TN | Q81: Memphis | R81: South | S81: 756925 | T81: 501-1000 | U81: 1020 | V81: 24.7 | W81: 7.4 | X81: 1011 | Y81: 1043.1 | Z81: Reefer | AA81: 21.22 | AB81: 06:00-09:59 | AC81: Monday | AE81: 0 | AF81: 0 | AG81: 0 | AH81: 37.3 | AI81: 0 | AJ81: 0.788 | AK81: 0.658 | AL81: 62139.49 | AM81: High | AN81: 1 | AO81: 1 | AP81: 0 | AQ81: 1 | AR81: 0 | AS81: 1 | AT81: 0 | AU81: 2.39 | AV81: 1.89 | AW81: 851.16 | AX81: 123.16 | AY81: 602.81 | AZ81: 28.3 | BA81: 30
A82: 156263020 | B82: 770487 | C82: 9683481 | D82: 8270 | E82: Desert Road Haulers | F82: 53520 | G82: Procter & Gamble | H82: 45948 | I82: 45948 | J82: 45948.507 | K82: 45948.631 | L82: 45948.617 | M82: 45948 | N82: CA | O82: Fresno | P82: CA | Q82: Sacramento | R82: West | S82: 739562 | T82: 0-100 | U82: 99 | V82: 23.7 | W82: 32.1 | X82: 97.7 | Y82: 153.5 | Z82: Tanker | AA82: 2.64 | AB82: 10:00-13:59 | AC82: Saturday | AE82: -21 | AF82: 0 | AG82: 0 | AH82: 34.8 | AI82: 0 | AJ82: 0.754 | AK82: 0.785 | AL82: 5915 | AM82: Low | AN82: 1 | AO82: 1 | AP82: 0 | AQ82: 1 | AR82: 0 | AS82: 1 | AT82: 0 | AU82: 2.23 | AV82: 1.48 | AW82: 140.84 | AX82: 15.94 | AY82: 104.9 | AZ82: 20 | BA82: 0
A83: 236105947 | B83: 816751 | C83: 3011363 | D83: 9996 | E83: Lone Star Transport | F83: 59971 | G83: Best Buy DC | H83: 45888 | I83: 45888 | J83: 45888.628 | K83: 45888.961 | L83: 45888.919 | M83: 45888 | N83: NJ | O83: Paterson | P83: MO | Q83: Springfield | R83: Midwest | S83: 712499 | T83: 301-500 | U83: 339 | V83: 2.3 | W83: 13.6 | X83: 336.1 | Y83: 352 | Z83: Dry Van | AA83: 6.98 | AB83: 14:00-17:59 | AC83: Tuesday | AE83: -60 | AF83: 0 | AG83: 0 | AH83: 26.3 | AI83: 0 | AJ83: 0.555 | AK83: 0.73 | AL83: 11379.6 | AM83: Medium | AN83: 1 | AO83: 1 | AP83: 0 | AQ83: 1 | AR83: 0 | AS83: 1 | AT83: 0 | AU83: 2.14 | AV83: 1.36 | AW83: 246.87 | AX83: 46.27 | AY83: 177.57 | AZ83: 13.3 | BA83: 16.6
A84: 896413702 | B84: 301629 | C84: 8633773 | D84: 7331 | E84: Blue Ridge Logistics | F84: 53218 | G84: Kroger Logistics | H84: 45872 | I84: 45872 | J84: 45872.292 | K84: 45872.65 | L84: 45872.611 | M84: 45872 | N84: IL | O84: Chicago | P84: FL | Q84: Tampa | R84: South | S84: 754594 | T84: 301-500 | U84: 435 | V84: 12.2 | W84: 35.7 | X84: 434.2 | Y84: 482.1 | Z84: Flatbed | AA84: 7.67 | AB84: 06:00-09:59 | AC84: Sunday | AE84: -56 | AF84: 0 | AG84: 0 | AH84: 51.1 | AI84: 0 | AJ84: 0.752 | AK84: 0.459 | AL84: 6701.89 | AM84: Medium | AN84: 1 | AO84: 1 | AP84: 0 | AQ84: 1 | AR84: 0 | AS84: 1 | AT84: 0 | AU84: 2.58 | AV84: 2.04 | AW84: 365.64 | AX84: 58.33 | AY84: 317.59 | AZ84: 63.5 | BA84: 8
A85: 552002959 | B85: 590785 | C85: 6171716 | D85: 6172 | E85: Midwest Express Trucking | F85: 53757 | G85: Walmart DC | H85: 45787 | I85: 45787 | J85: 45787.222 | K85: 45787.305 | L85: 45787.273 | M85: 45787 | N85: WA | O85: Spokane | P85: TN | Q85: Memphis | R85: South | S85: 715799 | T85: 0-100 | U85: 88 | V85: 26 | W85: 20.2 | X85: 73.6 | Y85: 119.8 | Z85: Reefer | AA85: 1.22 | AB85: 00:00-05:59 | AC85: Saturday | AE85: -46 | AF85: 0 | AG85: 0 | AH85: 30.4 | AI85: 0 | AJ85: 0.762 | AK85: 0.331 | AL85: 4661.86 | AM85: Low | AN85: 1 | AO85: 1 | AP85: 0 | AQ85: 1 | AR85: 0 | AS85: 1 | AT85: 0 | AU85: 2.44 | AV85: 1.85 | AW85: 75.34 | AX85: 23.35 | AY85: 70.96 | AZ85: 24.4 | BA85: 52.8
A86: 664880035 | B86: 624902 | C86: 8896868 | D86: 7546 | E86: Great Lakes Carriers | F86: 54016 | G86: Kroger Logistics | H86: 45834 | I86: 45834 | J86: 45834.222 | K86: 45834.562 | L86: 45834.561 | M86: 45834 | N86: NJ | O86: Jersey City | P86: TN | Q86: Knoxville | R86: South | S86: 729716 | T86: 101-300 | U86: 316 | V86: 5.4 | W86: 19.4 | X86: 318.2 | Y86: 343 | Z86: Reefer | AA86: 8.14 | AB86: 00:00-05:59 | AC86: Thursday | AE86: -1 | AF86: 0 | AG86: 0 | AH86: 28.2 | AI86: 0 | AJ86: 0.733 | AK86: 0.835 | AL86: 4264.12 | AM86: Low | AN86: 1 | AO86: 1 | AP86: 0 | AQ86: 1 | AR86: 0 | AS86: 1 | AT86: 0 | AU86: 2.49 | AV86: 1.8 | AW86: 257.32 | AX86: 46.21 | AY86: 238.63 | AZ86: 21.6 | BA86: 13.3
A87: 222030010 | B87: 705397 | C87: 5449368 | D87: 5859 | E87: Blue Ridge Logistics | F87: 52837 | G87: Walmart DC | H87: 45876 | I87: 45876 | J87: 45876.007 | K87: 45876.116 | L87: 45876.117 | M87: 45876 | N87: NC | O87: Durham | P87: CO | Q87: Colorado Springs | R87: West | S87: 760341 | T87: 0-100 | U87: 36 | V87: 30.4 | W87: 31.1 | X87: 26.2 | Y87: 87.7 | Z87: Reefer | AA87: 2.64 | AB87: 00:00-05:59 | AC87: Thursday | AE87: 1 | AF87: 0 | AG87: 0 | AH87: 59.9 | AI87: 0 | AJ87: 0.725 | AK87: 0.416 | AL87: 4152.27 | AM87: Low | AN87: 1 | AO87: 1 | AP87: 0 | AQ87: 1 | AR87: 0 | AS87: 1 | AT87: 0 | AU87: 2.38 | AV87: 1.7 | AW87: 65.06 | AX87: 11.35 | AY87: 49.59 | AZ87: 11.4 | BA87: 24.2
... A106: 423873102 | B106: 623481 | C106: 2737893 | D106: 4627 | E106: Great Lakes Carriers | F106: 55672 | G106: Amazon Fulfillment | H106: 45919 | I106: 45919 | J106: 45919.469 | K106: 45919.531 | L106: 45919.538 | M106: 45919 | N106: NC | O106: Durham | P106: FL | Q106: Tampa | R106: South | S106: 720278 | T106: 0-100 | U106: 65 | V106: 12.1 | W106: 17.8 | X106: 66.2 | Y106: 96.1 | Z106: Dry Van | AA106: 1.67 | AB106: 10:00-13:59 | AC106: Friday | AE106: 10 | AF106: 0 | AG106: 0 | AH106: 36 | AI106: 0 | AJ106: 0.55 | AK106: 0.445 | AL106: 3321.65 | AM106: Low | AN106: 1 | AO106: 1 | AP106: 0 | AQ106: 1 | AR106: 0 | AS106: 1 | AT106: 0 | AU106: 2.29 | AV106: 1.5 | AW106: 62.52 | AX106: 16.81 | AY106: 65.85 | AZ106: 22.3 | BA106: 65.1
A107: 591819409 | B107: 245051 | C107: 1739653 | D107: 4763 | E107: Lone Star Transport | F107: 51502 | G107: FedEx Ground Hub | H107: 45783 | I107: 45783 | J107: 45783.604 | K107: 45783.839 | L107: 45783.912 | M107: 45783 | N107: CO | O107: Pueblo | P107: CO | Q107: Colorado Springs | R107: West | S107: 705397 | T107: 301-500 | U107: 294 | V107: 20.9 | W107: 31.1 | X107: 282.8 | Y107: 334.8 | Z107: Dry Van | AA107: 7.39 | AB107: 14:00-17:59 | AC107: Tuesday | AD107: traffic | AE107: 106 | AF107: 0 | AG107: 0 | AH107: 73.4 | AI107: 0 | AJ107: 0.86 | AK107: 0.764 | AL107: 4203.86 | AM107: Low | AN107: 1 | AO107: 0 | AP107: 1 | AQ107: 0 | AR107: 1 | AS107: 0 | AT107: 1 | AU107: 2.18 | AV107: 1.63 | AW107: 258.99 | AX107: 46.44 | AY107: 174.12 | AZ107: 12.9 | BA107: 68.1
A108: 790781796 | B108: 380746 | C108: 7199635 | D108: 2678 | E108: Blue Ridge Logistics | F108: 54684 | G108: Amazon Fulfillment | H108: 45945 | I108: 45945 | J108: 45945.705 | K108: 45946.289 | L108: 45946.287 | M108: 45946 | N108: PA | O108: Erie | P108: TX | Q108: Dallas | R108: South | S108: 734732 | T108: 501-1000 | U108: 624 | V108: 16.7 | W108: 2.9 | X108: 610.5 | Y108: 630.1 | Z108: Intermodal | AA108: 13.98 | AB108: 14:00-17:59 | AC108: Wednesday | AE108: -2 | AF108: 0 | AG108: 0 | AH108: 89.7 | AI108: 0 | AJ108: 0.904 | AK108: 0.286 | AL108: 1954.17 | AM108: Low | AN108: 1 | AO108: 1 | AP108: 0 | AQ108: 1 | AR108: 0 | AS108: 1 | AT108: 0 | AU108: 2.06 | AV108: 1.27 | AW108: 527.23 | AX108: 101.29 | AY108: 309.37 | AZ108: 22.1 | BA108: 80.4
A109: 133447745 | B109: 872246 | C109: 4860684 | D109: 6578 | E109: Keystone Freight | F109: 51410 | G109: Walmart DC | H109: 45781 | I109: 45781 | J109: 45781.236 | K109: 45781.301 | L109: 45781.295 | M109: 45781 | N109: CO | O109: Fort Collins | P109: NJ | Q109: Paterson | R109: Northeast | S109: 774044 | T109: 0-100 | U109: 66 | V109: 8.1 | W109: 9.6 | X109: 67 | Y109: 84.7 | Z109: Reefer | AA109: 1.42 | AB109: 00:00-05:59 | AC109: Sunday | AE109: -8 | AF109: 0 | AG109: 0 | AH109: 73.1 | AI109: 0 | AJ109: 0.669 | AK109: 0.557 | AL109: 2546.43 | AM109: Low | AN109: 1 | AO109: 1 | AP109: 0 | AQ109: 1 | AR109: 0 | AS109: 1 | AT109: 0 | AU109: 2.39 | AV109: 1.66 | AW109: 62.95 | AX109: 11.9 | AY109: 45.63 | AZ109: 41.8 | BA109: 14.9
A110: 165310776 | B110: 946335 | C110: 1247595 | D110: 6675 | E110: Blue Ridge Logistics | F110: 53770 | G110: Costco Distribution | H110: 45957 | I110: 45957 | J110: 45957.76 | K110: 45957.823 | L110: 45957.803 | M110: 45957 | N110: GA | O110: Macon | P110: AZ | Q110: Phoenix | R110: West | S110: 719605 | T110: 0-100 | U110: 21 | V110: 1.7 | W110: 4.7 | X110: 25.3 | Y110: 31.7 | Z110: Dry Van | AA110: 1.02 | AB110: 18:00-23:59 | AC110: Monday | AE110: -29 | AF110: 0 | AG110: 0 | AH110: 42 | AI110: 0 | AJ110: 0.563 | AK110: 0.442 | AL110: 2637.43 | AM110: Low | AN110: 1 | AO110: 1 | AP110: 0 | AQ110: 1 | AR110: 0 | AS110: 1 | AT110: 0 | AU110: 1.7 | AV110: 1.22 | AW110: 26.3 | AX110: 4.74 | AY110: 19.6 | AZ110: 32.6 | BA110: 9.6
A111: 614302907 | B111: 905635 | C111: 2677407 | D111: 3790 | E111: Pacific Linehaul | F111: 54659 | G111: Walmart DC | H111: 45705 | I111: 45705 | J111: 45705.41 | K111: 45705.72 | L111: 45705.895 | M111: 45705 | N111: NY | O111: Syracuse | P111: NY | Q111: Rochester | R111: Northeast | S111: 742838 | T111: 301-500 | U111: 350 | V111: 41.8 | W111: 19.6 | X111: 359.4 | Y111: 420.8 | Z111: Dry Van | AA111: 11.64 | AB111: 06:00-09:59 | AC111: Monday | AD111: mechanical | AE111: 252 | AF111: 0 | AG111: 0 | AH111: 52.4 | AI111: 1 | AJ111: 0.788 | AK111: 0.639 | AL111: 4953.13 | AM111: Low | AN111: 1 | AO111: 0 | AP111: 1 | AQ111: 0 | AR111: 1 | AS111: 0 | AT111: 1 | AU111: 2.3 | AV111: 1.53 | AW111: 369.54 | AX111: 1096.72 | AY111: 202.71 | AZ111: 27.7 | BA111: 36.6
A112: 531233244 | B112: 301629 | C112: 8633773 | D112: 7331 | E112: Blue Ridge Logistics | F112: 54001 | G112: Walmart DC | H112: 45721 | I112: 45721 | J112: 45721.538 | K112: 45721.709 | L112: 45721.715 | M112: 45721 | N112: TX | O112: Houston | P112: NC | Q112: Wilmington | R112: South | S112: 765850 | T112: 101-300 | U112: 215 | V112: 47.6 | W112: 7.6 | X112: 217.2 | Y112: 272.4 | Z112: Flatbed | AA112: 4.24 | AB112: 10:00-13:59 | AC112: Wednesday | AE112: 8 | AF112: 0 | AG112: 0 | AH112: 36.1 | AI112: 0 | AJ112: 0.913 | AK112: 0.485 | AL112: 3123.55 | AM112: Low | AN112: 1 | AO112: 1 | AP112: 0 | AQ112: 1 | AR112: 0 | AS112: 1 | AT112: 0 | AU112: 2.29 | AV112: 1.43 | AW112: 247.24 | AX112: 56.13 | AY112: 195.15 | AZ112: 63.5 | BA112: 7.3
A113: 557707813 | B113: 197251 | C113: 4078418 | D113: 2585 | E113: Pacific Linehaul | F113: 53483 | G113: FedEx Ground Hub | H113: 45782 | I113: 45782 | J113: 45782.962 | K113: 45783.191 | L113: 45783.177 | M113: 45783 | N113: IL | O113: Chicago | P113: OH | Q113: Cincinnati | R113: Midwest | S113: 791457 | T113: 101-300 | U113: 228 | V113: 7.8 | W113: 24.6 | X113: 228 | Y113: 260.4 | Z113: Dry Van | AA113: 5.17 | AB113: 18:00-23:59 | AC113: Monday | AE113: -19 | AF113: 0 | AG113: 0 | AH113: 67.1 | AI113: 0 | AJ113: 0.623 | AK113: 0.758 | AL113: 8690.41 | AM113: Medium | AN113: 1 | AO113: 1 | AP113: 0 | AQ113: 1 | AR113: 0 | AS113: 1 | AT113: 0 | AU113: 2.42 | AW113: 179.67 | AX113: 41.94 | AY113: 139.39 | AZ113: 11.9 | BA113: 21.3
A114: 836691577 | B114: 944151 | C114: 6855396 | D114: 8574 | E114: Atlantic Freightways | F114: 54562 | G114: FedEx Ground Hub | H114: 45807 | I114: 45807 | J114: 45807.396 | K114: 45807.533 | L114: 45807.518 | M114: 45807 | N114: CA | O114: San Diego | P114: CO | Q114: Colorado Springs | R114: West | S114: 728940 | T114: 0-100 | U114: 103 | V114: 71.7 | W114: 58.3 | X114: 101 | Y114: 231 | Z114: Flatbed | AA114: 2.93 | AB114: 06:00-09:59 | AC114: Friday | AE114: -21 | AF114: 0 | AG114: 0 | AH114: 43.6 | AI114: 0 | AJ114: 0.871 | AK114: 0.79 | AL114: 3634.51 | AM114: Low | AN114: 1 | AO114: 1 | AP114: 0 | AQ114: 1 | AR114: 0 | AS114: 1 | AT114: 0 | AU114: 2.23 | AV114: 1.36 | AW114: 185.17 | AX114: 40.02 | AY114: 124.08 | AZ114: 12.8 | BA114: 42.2
A115: 215923129 | B115: 301629 | C115: 8633773 | D115: 7331 | E115: Blue Ridge Logistics | F115: 50598 | G115: Best Buy DC | H115: 45785 | I115: 45785 | J115: 45785.58 | K115: 45785.782 | L115: 45785.766 | M115: 45785 | N115: TX | O115: El Paso | P115: IL | Q115: Rockford | R115: Midwest | S115: 720079 | T115: 101-300 | U115: 243 | V115: 5.2 | W115: 23.7 | X115: 246.2 | Y115: 275.1 | Z115: Flatbed | AA115: 4.48 | AB115: 10:00-13:59 | AC115: Thursday | AE115: -22 | AF115: 0 | AG115: 0 | AH115: 56.2 | AI115: 0 | AJ115: 0.936 | AK115: 0.407 | AL115: 2171.97 | AM115: Low | AN115: 1 | AO115: 1 | AP115: 0 | AQ115: 1 | AR115: 0 | AS115: 1 | AT115: 0 | AU115: 2.19 | AV115: 1.42 | AW115: 192.59 | AX115: 56.05 | AY115: 180.81 | AZ115: 63.5 | BA115: 6.8
A116: 626422169 | B116: 581741 | C116: 3790237 | D116: 1995 | E116: Keystone Freight | F116: 59183 | G116: UPS Supply Chain | H116: 45936 | I116: 45936 | J116: 45936.34 | K116: 45936.403 | L116: 45936.395 | M116: 45936 | N116: TX | O116: Austin | P116: NC | Q116: Charlotte | R116: South | S116: 765850 | T116: 0-100 | U116: 57 | V116: 14.4 | W116: 34.8 | X116: 49.7 | Y116: 98.9 | Z116: Reefer | AA116: 1.32 | AB116: 06:00-09:59 | AC116: Monday | AE116: -11 | AF116: 0 | AG116: 0 | AH116: 43.7 | AI116: 0 | AJ116: 0.791 | AK116: 0.675 | AL116: 6517.55 | AM116: Low | AN116: 1 | AO116: 1 | AP116: 0 | AQ116: 1 | AR116: 0 | AS116: 1 | AT116: 0 | AU116: 2.26 | AV116: 1.69 | AW116: 87.16 | AX116: 11.59 | AY116: 53.36 | AZ116: 17.5 | BA116: 39.1
A117: 864935082 | B117: 684004 | C117: 8670955 | D117: 8721 | E117: Great Lakes Carriers | F117: 53041 | G117: Tyson Foods | H117: 45693 | I117: 45693 | J117: 45693.469 | K117: 45693.798 | L117: 45693.768 | M117: 45693 | N117: OH | O117: Cleveland | P117: CA | Q117: Sacramento | R117: West | S117: 706621 | T117: 101-300 | U117: 305 | V117: 30.9 | W117: 1.8 | X117: 300.9 | Y117: 333.6 | Z117: Dry Van | AA117: 7.17 | AB117: 10:00-13:59 | AC117: Wednesday | AE117: -44 | AF117: 0 | AG117: 0 | AH117: 86.1 | AI117: 0 | AJ117: 0.555 | AK117: 0.74 | AL117: 15238.6 | AM117: Medium | AN117: 1 | AO117: 1 | AP117: 0 | AQ117: 1 | AR117: 0 | AS117: 1 | AT117: 0 | AU117: 2 | AV117: 1.43 | AW117: 295.93 | AX117: 39.85 | AY117: 191.85 | AZ117: 0.1 | BA117: 8.2
A118: 576271425 | B118: 331148 | C118: 8231838 | D118: 8734 | E118: Blue Ridge Logistics | F118: 58160 | G118: Walmart DC | H118: 45786 | I118: 45786 | J118: 45786.34 | K118: 45786.778 | L118: 45786.763 | M118: 45786 | N118: OH | O118: Cleveland | P118: OH | Q118: Cleveland | R118: Midwest | S118: 797593 | T118: 301-500 | U118: 470 | V118: 32.6 | W118: 13.8 | X118: 462.9 | Y118: 509.3 | Z118: Dry Van | AA118: 10.14 | AB118: 06:00-09:59 | AC118: Friday | AE118: -22 | AF118: 0 | AG118: 0 | AH118: 38.4 | AI118: 0 | AJ118: 0.569 | AK118: 0.475 | AL118: 21727.4 | AM118: Medium | AN118: 1 | AO118: 1 | AP118: 0 | AQ118: 1 | AR118: 0 | AS118: 1 | AT118: 0 | AU118: 2.07 | AV118: 1.53 | AW118: 364.99 | AX118: 72.89 | AY118: 310.95 | AZ118: 5.8 | BA118: 22.9
A119: 178910051 | B119: 903035 | C119: 7110622 | D119: 3200 | E119: Cascade Cargo | F119: 56391 | G119: FedEx Ground Hub | H119: 45963 | I119: 45963 | J119: 45963.462 | K119: 45963.577 | L119: 45963.569 | M119: 45963 | N119: TX | O119: El Paso | P119: MI | Q119: Ann Arbor | R119: Midwest | S119: 752402 | T119: 101-300 | U119: 148 | V119: 16.3 | W119: 18 | X119: 144.9 | Y119: 179.2 | Z119: Reefer | AA119: 2.58 | AB119: 10:00-13:59 | AC119: Sunday | AE119: -11 | AF119: 0 | AG119: 0 | AH119: 35.3 | AI119: 0 | AJ119: 0.519 | AK119: 0.652 | AL119: 2616.68 | AM119: Low | AN119: 1 | AO119: 1 | AP119: 0 | AQ119: 1 | AR119: 0 | AS119: 1 | AT119: 0 | AU119: 2.16 | AV119: 1.64 | AW119: 145.8 | AX119: 24.57 | AY119: 86.96 | AZ119: 26.8 | BA119: 12.5
A120: 186748119 | B120: 972064 | C120: 2818692 | D120: 8158 | E120: Blue Ridge Logistics | F120: 57287 | G120: UPS Supply Chain | H120: 45682 | I120: 45682 | J120: 45682.507 | K120: 45682.706 | L120: 45682.674 | M120: 45682 | N120: AZ | O120: Mesa | P120: WA | Q120: Tacoma | R120: West | S120: 788294 | T120: 101-300 | U120: 133 | V120: 41.7 | W120: 25.6 | X120: 128.7 | Y120: 196 | Z120: Reefer | AA120: 4.02 | AB120: 10:00-13:59 | AC120: Saturday | AE120: -46 | AF120: 0 | AG120: 0 | AH120: 39.3 | AI120: 0 | AJ120: 0.843 | AK120: 0.376 | AL120: 2646.43 | AM120: Low | AN120: 1 | AO120: 1 | AP120: 0 | AQ120: 1 | AR120: 0 | AS120: 1 | AT120: 0 | AU120: 2.46 | AV120: 1.91 | AW120: 173.72 | AX120: 42.8 | AY120: 133.47 | AZ120: 10 | BA120: 25.5
A121: 445864933 | B121: 813328 | C121: 5186414 | D121: 4510 | E121: Sunbelt Haulage | F121: 50066 | G121: FedEx Ground Hub | H121: 46001 | I121: 46001 | J121: 46001.955 | K121: 46002.706 | L121: 46002.697 | M121: 46002 | N121: CO | O121: Denver | P121: AZ | Q121: Phoenix | R121: West | S121: 795889 | T121: 501-1000 | U121: 865 | V121: 55.1 | W121: 46.9 | X121: 860.2 | Y121: 962.2 | Z121: Dry Van | AA121: 17.8 | AB121: 18:00-23:59 | AC121: Wednesday | AE121: -13 | AF121: 0 | AG121: 0 | AH121: 55.6 | AI121: 0 | AJ121: 0.482 | AK121: 0.731 | AL121: 13633.53 | AM121: Medium | AN121: 1 | AO121: 1 | AP121: 0 | AQ121: 1 | AR121: 0 | AS121: 1 | AT121: 0 | AU121: 2.3 | AV121: 1.49 | AW121: 743.31 | AX121: 161.35 | AY121: 580.1 | AZ121: 29.1 | BA121: 30.8
A122: 753154389 | B122: 629903 | C122: 9143903 | D122: 9666 | E122: Atlantic Freightways | F122: 58123 | G122: Costco Distribution | H122: 46018 | I122: 46018 | J122: 46018.757 | K122: 46019.124 | L122: 46019.097 | M122: 46019 | N122: NY | O122: New York | P122: TX | Q122: Houston | R122: South | S122: 704946 | T122: 301-500 | U122: 418 | V122: 21.9 | W122: 4.6 | X122: 414.2 | Y122: 440.7 | Z122: Flatbed | AA122: 8.17 hrs | AB122: 18:00-23:59 | AC122: Saturday | AE122: -38 | AF122: 0 | AG122: 0 | AH122: 73.8 | AI122: 0 | AJ122: 0.692 | AK122: 0.631 | AL122: 106475.95 | AM122: High | AN122: 1 | AO122: 1 | AP122: 0 | AQ122: 1 | AR122: 0 | AS122: 1 | AT122: 0 | AU122: 2.02 | AV122: 1.38 | AW122: 368.49 | AX122: 71.78 | AY122: 244.63 | AZ122: 10.3 | BA122: 0
A123: 259272239 | B123: 287330 | C123: 4348276 | D123: 9338 | E123: Great Lakes Carriers | F123: 52750 | G123: Amazon Fulfillment | H123: 45690 | I123: 45690 | J123: 45690.26 | K123: 45690.651 | L123: 45690.643 | M123: 45690 | N123: MI | O123: Lansing | P123: CA | Q123: Los Angeles | R123: West | S123: 751495 | T123: 301-500 | U123: 471 | V123: 19.3 | W123: 31.1 | X123: 472.3 | Y123: 522.7 | Z123: Reefer | AA123: 9.18 | AB123: 06:00-09:59 | AC123: Sunday | AE123: -11 | AF123: 0 | AG123: 0 | AH123: 55.7 | AI123: 0 | AJ123: 0.756 | AK123: 0.456 | AL123: 4865.67 | AM123: Low | AN123: 1 | AO123: 1 | AP123: 0 | AQ123: 1 | AR123: 0 | AS123: 1 | AT123: 0 | AU123: 2.37 | AV123: 1.73 | AW123: 449.66 | AX123: 88.57 | AY123: 301.05 | AZ123: 17.5 | BA123: 67.1
A124: 170525764 | B124: 260263 | C124: 5674183 | D124: 5736 | E124: Lone Star Transport | F124: 58661 | G124: UPS Supply Chain | H124: 45764 | I124: 45764 | J124: 45764.674 | K124: 45764.876 | L124: 45764.896 | M124: 45764 | N124: PA | O124: Erie | P124: PA | Q124: Erie | R124: Northeast | S124: 739365 | T124: 101-300 | U124: 263 | V124: 11 | W124: 19 | X124: 270.6 | Y124: 300.6 | Z124: Reefer | AA124: 5.33 | AB124: 14:00-17:59 | AC124: Thursday | AE124: 29 | AF124: 70 | AG124: 0 | AH124: 72.7 | AI124: 0 | AJ124: 0.628 | AK124: 0.769 | AL124: 21226.42 | AM124: Medium | AN124: 1 | AO124: 0 | AP124: 1 | AQ124: 0 | AR124: 1 | AS124: 0 | AT124: 1 | AU124: 2.67 | AV124: 2.02 | AW124: 265 | AX124: 61.63 | AY124: 148.32 | AZ124: 30.8 | BA124: 14.5
A125: 235497187 | B125: 898975 | C125: 4731818 | D125: 2986 | E125: Blue Ridge Logistics | F125: 59916 | G125: Procter & Gamble | H125: 45793 | I125: 45793 | J125: 45793.014 | K125: 45793.358 | L125: 45793.343 | M125: 45793 | N125: IL | O125: Aurora | P125: TN | Q125: Clarksville | R125: South | S125: 758407 | T125: 301-500 | U125: 433 | V125: 3.3 | W125: 20.9 | X125: 434.7 | Y125: 458.9 | Z125: Intermodal | AA125: 7.91 | AB125: 00:00-05:59 | AC125: Friday | AE125: -21 | AF125: 0 | AG125: 0 | AH125: 58.2 | AI125: 0 | AJ125: 0.734 | AK125: 0.656 | AL125: 1478.94 | AM125: Low | AN125: 1 | AO125: 1 | AP125: 0 | AQ125: 1 | AR125: 0 | AS125: 1 | AT125: 0 | AU125: 2.24 | AV125: 1.58 | AW125: 355.45 | AX125: 59.3 | AY125: 299.35 | AZ125: 7.4 | BA125: 40.6
... A129: 728530544 | B129: 581141 | C129: 2936571 | D129: 6592 | E129: Sunbelt Haulage | F129: 51631 | G129: Amazon Fulfillment | H129: 45934 | I129: 45934 | J129: 45934.861 | K129: 45935.117 | L129: 45935.09 | M129: 45935 | N129: IL | O129: Chicago | P129: NJ | Q129: Jersey City | R129: Northeast | S129: 766155 | T129: 101-300 | U129: 283 | V129: 17.6 | W129: 7.1 | X129: 284 | Y129: 308.7 | Z129: Dry Van | AA129: 5.49 | AB129: 18:00-23:59 | AC129: Saturday | AE129: -39 | AF129: 0 | AG129: 0 | AH129: 57.5 | AI129: 0 | AJ129: 0.745 | AK129: 0.452 | AL129: 12481.68 | AM129: Medium | AN129: 1 | AO129: 1 | AP129: 0 | AQ129: 1 | AR129: 0 | AS129: 1 | AT129: 0 | AU129: 2.27 | AV129: 1.76 | AW129: 248.11 | AX129: 59.66 | AY129: 209.55 | AZ129: 27 | BA129: 38
A130: 688793237 | B130: 892495 | C130: 5394880 | D130: 2291 | E130: Midwest Express Trucking | F130: 56452 | G130: FedEx Ground Hub | H130: 45701 | I130: 45701 | J130: 45701.375 | K130: 45701.71 | L130: 45701.671 | M130: 45701 | N130: MI | O130: Detroit | P130: MI | Q130: Grand Rapids | R130: Midwest | S130: 711807 | T130: 301-500 | U130: 347 | V130: 11.7 | W130: 2.1 | X130: 346.9 | Y130: 360.7 | Z130: Intermodal | AA130: 7.1 | AB130: 06:00-09:59 | AC130: Thursday | AD130: traffic | AE130: -56 | AF130: 0 | AG130: 0 | AH130: 33.2 | AI130: 0 | AJ130: 0.727 | AK130: 0.316 | AL130: 4164.76 | AM130: Low | AN130: 1 | AO130: 1 | AP130: 0 | AQ130: 1 | AR130: 0 | AS130: 1 | AT130: 0 | AU130: 1.99 | AV130: 1.25 | AW130: 255.93 | AX130: 77.51 | AY130: 189.44 | AZ130: 8.6 | BA130: 26
A131: 864668242 | B131: 584714 | C131: 5004485 | D131: 7938 | E131: Blue Ridge Logistics | F131: 50774 | G131: Amazon Fulfillment | H131: 45962 | I131: 45962 | J131: 45962.354 | K131: 45962.614 | L131: 45962.587 | M131: 45962 | N131: IL | O131: Springfield | P131: OH | Q131: Dayton | R131: Midwest | S131: 791457 | T131: 101-300 | U131: 272 | V131: 12.1 | W131: 1.2 | X131: 282.4 | Y131: 295.7 | Z131: Dry Van | AA131: 5.58 | AB131: 06:00-09:59 | AC131: Saturday | AE131: -39 | AF131: 0 | AG131: 0 | AH131: 63.6 | AI131: 0 | AJ131: 0.59 | AK131: 0.51 | AL131: 14801.48 | AM131: Medium | AN131: 1 | AO131: 1 | AP131: 0 | AQ131: 1 | AR131: 0 | AS131: 1 | AT131: 0 | AU131: 1.93 | AV131: 1.49 | AW131: 216.34 | AX131: 45.43 | AY131: 145.95 | AZ131: 0.2 | BA131: 45.9
...

Sheet Cascade_Cargo_late_20%
A4: Column Labels
A5: Cascade Cargo | D5: Total Sum of total_shipments | E5: Total Sum of on_time_count | F5: Total Sum of Late_count
A6: Sum of total_shipments | B6: Sum of on_time_count | C6: Sum of Late_count
A7: 77 | B7: 62 | C7: 15 | D7: 77 | E7: 62 | F7: 15

Sheet Insights
A1: DELAY MINUTES (Column AE) - KEY INSIGHTS
A3: OVERALL STATISTICS | E3: AVG DELAY BY CARRIER
A4: Metric | B4: Value | E4: Carrier | F4: Avg Delay (min)
A5: Total Shipments | B5: =COUNTA(fact_orders_1000!AE2:AE1002) -> 1000 | E5: Atlantic Freightways | F5: =ROUND(AVERAGEIF(fact_orders_1000!E2:E1002,"Atlantic Freightways",fact_orders_1000!AE2:AE1002),1) -> 11.4
A6: Average Delay (minutes) | B6: =ROUND(AVERAGE(fact_orders_1000!AE2:AE1002),1) -> 6.5 | E6: Blue Ridge Logistics | F6: =ROUND(AVERAGEIF(fact_orders_1000!E2:E1002,"Blue Ridge Logistics",fact_orders_1000!AE2:AE1002),1) -> 10.2
A7: Median Delay (minutes) | B7: =MEDIAN(fact_orders_1000!AE2:AE1002) -> -14 | E7: Cascade Cargo | F7: =ROUND(AVERAGEIF(fact_orders_1000!E2:E1002,"Cascade Cargo",fact_orders_1000!AE2:AE1002),1) -> 5.8
A8: Max Delay (minutes) | B8: =MAX(fact_orders_1000!AE2:AE1002) -> 956 | E8: Desert Road Haulers | F8: =ROUND(AVERAGEIF(fact_orders_1000!E2:E1002,"Desert Road Haulers",fact_orders_1000!AE2:AE1002),1) -> -2.1
A9: Min Delay (Early) | B9: =MIN(fact_orders_1000!AE2:AE1002) -> -88 | E9: Great Lakes Carriers | F9: =ROUND(AVERAGEIF(fact_orders_1000!E2:E1002,"Great Lakes Carriers",fact_orders_1000!AE2:AE1002),1) -> -2.6
A10: Std Deviation | B10: =ROUND(STDEV(fact_orders_1000!AE2:AE1002),1) -> 79.9 | E10: Keystone Freight | F10: =ROUND(AVERAGEIF(fact_orders_1000!E2:E1002,"Keystone Freight",fact_orders_1000!AE2:AE1002),1) -> -3.8
E11: Lone Star Transport | F11: =ROUND(AVERAGEIF(fact_orders_1000!E2:E1002,"Lone Star Transport",fact_orders_1000!AE2:AE1002),1) -> 4.2
A12: ON-TIME vs LATE PERFORMANCE | E12: Midwest Express Trucking | F12: =ROUND(AVERAGEIF(fact_orders_1000!E2:E1002,"Midwest Express Trucking",fact_orders_1000!AE2:AE1002),1) -> 4.2
A13: Category | B13: Count | C13: Percentage | E13: Pacific Linehaul | F13: =ROUND(AVERAGEIF(fact_orders_1000!E2:E1002,"Pacific Linehaul",fact_orders_1000!AE2:AE1002),1) -> 10.7
A14: On-Time (≤0 min delay) | B14: =COUNTIF(fact_orders_1000!AE2:AE1002,"<=0") -> 703 | C14: =B14/$B$5 -> 0.703 | E14: Sunbelt Haulage | F14: =ROUND(AVERAGEIF(fact_orders_1000!E2:E1002,"Sunbelt Haulage",fact_orders_1000!AE2:AE1002),1) -> 12.2
A15: Late (>0 min delay) | B15: =COUNTIF(fact_orders_1000!AE2:AE1002,">0") -> 297 | C15: =B15/$B$5 -> 0.297
A17: DELAY REASONS BREAKDOWN | E17: AVG DELAY BY TRUCK TYPE
A18: Delay Reason | B18: Count | C18: % of Late | E18: Truck Type | F18: Avg Delay (min)
A19: Detention | B19: =COUNTIF(fact_orders_1000!AD2:AD1002,"detention") -> 63 | C19: =B19/$B$15 -> 0.21212121 | E19: Dry Van | F19: =ROUND(AVERAGEIF(fact_orders_1000!Z2:Z1002,"Dry Van",fact_orders_1000!AE2:AE1002),1) -> 11.2
A20: Traffic | B20: =COUNTIF(fact_orders_1000!AD2:AD1002,"traffic") -> 41 | C20: =B20/$B$15 -> 0.13804714 | E20: Flatbed | F20: =ROUND(AVERAGEIF(fact_orders_1000!Z2:Z1002,"Flatbed",fact_orders_1000!AE2:AE1002),1) -> 2.7
A21: Weather | B21: =COUNTIF(fact_orders_1000!AD2:AD1002,"weather") -> 20 | C21: =B21/$B$15 -> 0.067340067 | E21: Intermodal | F21: =ROUND(AVERAGEIF(fact_orders_1000!Z2:Z1002,"Intermodal",fact_orders_1000!AE2:AE1002),1) -> 6.4
A22: Mechanical | B22: =COUNTIF(fact_orders_1000!AD2:AD1002,"mechanical") -> 5 | C22: =B22/$B$15 -> 0.016835017 | E22: Reefer | F22: =ROUND(AVERAGEIF(fact_orders_1000!Z2:Z1002,"Reefer",fact_orders_1000!AE2:AE1002),1) -> 0.2
A23: Other/Unspecified | B23: =$B$15-SUM(B19:B22) -> 168 | C23: =B23/$B$15 -> 0.56565657 | E23: Tanker | F23: =ROUND(AVERAGEIF(fact_orders_1000!Z2:Z1002,"Tanker",fact_orders_1000!AE2:AE1002),1) -> -0.1
A25: DELAY DISTRIBUTION BUCKETS | E25: AVG DELAY BY REGION
A26: Delay Range | B26: Count | C26: Percentage | E26: Region | F26: Avg Delay (min)
A27: Early (< -30 min) | B27: =COUNTIF(fact_orders_1000!AE2:AE1002,"<-30") -> 245 | C27: =B27/$B$5 -> 0.245 | E27: Midwest | F27: =ROUND(AVERAGEIF(fact_orders_1000!R2:R1002,"Midwest",fact_orders_1000!AE2:AE1002),1) -> -1.7
A28: Slightly Early (-30 to -1) | B28: =COUNTIFS(fact_orders_1000!AE2:AE1002,">=-30",fact_orders_1000!AE2:AE1002,"<0") -> 442 | C28: =B28/$B$5 -> 0.442 | E28: Northeast | F28: =ROUND(AVERAGEIF(fact_orders_1000!R2:R1002,"Northeast",fact_orders_1000!AE2:AE1002),1) -> 14.5
A29: On Time (0 min) | B29: =COUNTIF(fact_orders_1000!AE2:AE1002,0) -> 16 | C29: =B29/$B$5 -> 0.016 | E29: South | F29: =ROUND(AVERAGEIF(fact_orders_1000!R2:R1002,"South",fact_orders_1000!AE2:AE1002),1) -> 6
A30: Minor Delay (1-30 min) | B30: =COUNTIFS(fact_orders_1000!AE2:AE1002,">=1",fact_orders_1000!AE2:AE1002,"<=30") -> 170 | C30: =B30/$B$5 -> 0.17 | E30: West | F30: =ROUND(AVERAGEIF(fact_orders_1000!R2:R1002,"West",fact_orders_1000!AE2:AE1002),1) -> 8.6
A31: Moderate Delay (31-120 min) | B31: =COUNTIFS(fact_orders_1000!AE2:AE1002,">=31",fact_orders_1000!AE2:AE1002,"<=120") -> 40 | C31: =B31/$B$5 -> 0.04
A32: Major Delay (121-300 min) | B32: =COUNTIFS(fact_orders_1000!AE2:AE1002,">=121",fact_orders_1000!AE2:AE1002,"<=300") -> 75 | C32: =B32/$B$5 -> 0.075
A33: Severe Delay (>300 min) | B33: =COUNTIF(fact_orders_1000!AE2:AE1002,">300") -> 12 | C33: =B33/$B$5 -> 0.012
A35: KEY INSIGHTS SUMMARY
A36: ✓ Overall on-time delivery rate: 70.3% (703 of 1000 shipments)
A37: ✓ Average delay is negative (-17 min), indicating most deliveries arrive early
A38: ✓ Detention is the #1 cause of delays (48.8% of documented delay reasons)
A39: ✓ Severe delays (>300 min) represent only ~5% of shipments
A40: ✓ Compare carrier and regional performance to identify improvement areas

Sheet Day_of_the _week_Values
A1: truck_types | B1: (All)
A3: day_of_the_week | B3: Sum of shipment_value_usd | C3: Count of Years (scheduled_delivery_datetime) | D3: Sum of cost_per_mile
A4: Sunday | B4: 2862857.8 | C4: 161 | D4: 364.06
A5: Monday | B5: 2072542.2 | C5: 140 | D5: 314.21
A6: Tuesday | B6: 1877273.1 | C6: 126 | D6: 283.85
A7: Wednesday | B7: 1852551.4 | C7: 125 | D7: 282.51
A8: Thursday | B8: 2045148.6 | C8: 139 | D8: 318.06
A9: Friday | B9: 2765744.2 | C9: 159 | D9: 358.02
A10: Saturday | B10: 2630959.4 | C10: 150 | D10: 333.01
A11: Grand Total | B11: 16107077 | C11: 1000 | D11: 2253.72

Sheet Variable_CPM
A2: Average of variable_cost_per_mile | B2: shipment_value_bucket
A3: truck_types | B3: High | C3: Low | D3: Medium | E3: Grand Total
A4: Dry Van | B4: 1.4640678 | C4: 1.5048659 | D4: 1.5046541 | E4: 1.4997704
A5: Flatbed | B5: 1.627 | C5: 1.5963636 | D5: 1.6007843 | E5: 1.6030159
A6: Intermodal | B6: 1.3790909 | C6: 1.4422034 | D6: 1.4278571 | E6: 1.4310204
A7: Reefer | B7: 1.6456522 | C7: 1.6606164 | D7: 1.6536923 | E7: 1.6572222
A8: Tanker | B8: 1.65125 | C8: 1.75 | D8: 1.7407692 | E8: 1.7318
A9: Grand Total | B9: 1.5301653 | C9: 1.5615636 | D9: 1.5537342 | E9: 1.5552077

Sheet %delay_by_reason
B2: % of total 'detention_minutes' by 'Delay Reason'
C4: Delay Reason | D4: Sum of detention_minutes | E4: Sum of detention_minutes
C5: detention | D5: 0.75578391 | E5: Sum of detention_minutes
D6: 0.22468602 | E6: Sum of detention_minutes
C7: traffic | D7: 0.012258879 | E7: Sum of detention_minutes
C8: weather | D8: 0.0072711976 | E8: Sum of detention_minutes
C9: mechanical | D9: 0 | E9: Sum of detention_minutes
C10: Grand Total | D10: 1 | E10: Sum of detention_minutes

Sheet Deadhead_miles_per_region
B2: % of total 'deadhead_miles' by 'region'
C4: region | D4: Sum of deadhead_miles
C5: Midwest | D5: 0.21048162
C6: Northeast | D6: 0.1950546
C7: South | D7: 0.28574629
C8: West | D8: 0.30871749
C9: Grand Total | D9: 1

Sheet Sheet9
B2: % of total 'deadhead_miles' by 'region'
C4: region | D4: Count of deadhead_miles
C5: South | D5: 0.309
C6: Midwest | D6: 0.247
C7: West | D7: 0.243
C8: Northeast | D8: 0.201
C9: Grand Total | D9: 1

Sheet SevereDelayAnalysis
A1: SEVERE DELAYS DEEP DIVE (>300 minutes)
A3: SUMMARY
A4: Total Shipments | B4: 1003
A5: Severe Delays (>300 min) | B5: 12
A6: % of Total | B6: 0.012
A7: Avg Delay (severe only) | B7: 456 min
A9: SEVERE DELAYS BY CARRIER
A10: Carrier | B10: Severe Count | C10: Total Shipments | D10: % Severe | E10: Risk Level
A11: Blue Ridge Logistics | B11: 3 | C11: 243 | D11: 0.0123 | E11: ⚡ MEDIUM
A12: Sunbelt Haulage | B12: 2 | C12: 112 | D12: 0.0179 | E12: ⚡ MEDIUM
A13: Pacific Linehaul | B13: 2 | C13: 103 | D13: 0.0194 | E13: ⚡ MEDIUM
A14: Atlantic Freightways | B14: 2 | C14: 72 | D14: 0.0278 | E14: ⚠️ HIGH
A15: Cascade Cargo | B15: 1 | C15: 77 | D15: 0.013 | E15: ⚡ MEDIUM
A16: Keystone Freight | B16: 1 | C16: 71 | D16: 0.0141 | E16: ⚡ MEDIUM
A17: Lone Star Transport | B17: 1 | C17: 101 | D17: 0.0099 | E17: ✓ LOW
A19: SEVERE DELAYS BY TRUCK TYPE
A20: Truck Type | B20: Severe Count | C20: Total Shipments | D20: % Severe | E20: Risk Level
A21: Intermodal | B21: 2 | C21: 100 | D21: 0.02 | E21: ⚡ MEDIUM
A22: Dry Van | B22: 8 | C22: 488 | D22: 0.0164 | E22: ⚡ MEDIUM
A23: Reefer | B23: 2 | C23: 235 | D23: 0.0085 | E23: ✓ LOW
A25: SEVERE DELAYS BY LANE DISTANCE
A26: Lane Distance | B26: Severe Count | C26: Total Shipments | D26: % Severe | E26: Risk Level
A27: 501-1000 | B27: 2 | C27: 102 | D27: 0.0196 | E27: ⚡ MEDIUM
A28: 301-500 | B28: 3 | C28: 233 | D28: 0.0129 | E28: ⚡ MEDIUM
A29: 101-300 | B29: 6 | C29: 494 | D29: 0.0121 | E29: ⚡ MEDIUM
A30: 0-100 | B30: 1 | C30: 171 | D30: 0.0058 | E30: ✓ LOW
A32: SEVERE DELAYS BY REGION
A33: Region | B33: Severe Count | C33: Total Shipments | D33: % Severe | E33: Risk Level
A34: West | B34: 4 | C34: 243 | D34: 0.0165 | E34: ⚡ MEDIUM
A35: Northeast | B35: 3 | C35: 201 | D35: 0.0149 | E35: ⚡ MEDIUM
A36: South | B36: 4 | C36: 309 | D36: 0.0129 | E36: ⚡ MEDIUM
A37: Midwest | B37: 1 | C37: 247 | D37: 0.004 | E37: ✓ LOW
A39: SEVERE DELAYS BY REASON
A40: Delay Reason | B40: Count | C40: % of Severe Delays
A41: weather | B41: 6 | C41: 0.5
A42: mechanical | B42: 3 | C42: 0.25
A43: detention | B43: 2 | C43: 0.167
A44: traffic | B44: 1 | C44: 0.083
A46: KEY FINDINGS & TRENDS
A48: 🔴 CARRIER: Blue Ridge Logistics leads with 3 severe delays (1.2% rate)
A49: 🔴 TRUCK TYPE: Intermodal has highest severe rate at 2.0% (2 of 100)
A50: 🔴 LANE: 501-1000 mile routes show 2.0% severe delay rate
A51: 🔴 REGION: West has 1.6% severe delay rate (4 shipments)
A56: CROSS-TABULATION: CARRIER × TRUCK TYPE (Severe Delays Only)
A58: Use this formula in fact_orders_1000 to filter severe delays:
A59: =COUNTIFS(fact_orders_1000[delay_minutes],">300",fact_orders_1000[carrier_name],"Carrier",fact_orders_1000[truck_types],"Type") -> 0
A61: RECOMMENDATIONS
A63: 1. CARRIER FOCUS: Blue Ridge Logistics needs operational review - 3 severe delays despite only 243 total shipments
A64: 2. TRUCK TYPE ALERT: Intermodal trucks show 2.0% severe delay rate - investigate terminal handoff procedures
A65: 3. LANE STRATEGY: Long-haul routes (501-1000 miles) need better buffer time or relay points
A66: 4. REGIONAL ACTION: West region (2.1% severe rate) - consider weather contingencies and route alternatives
A68: FORMULA REFERENCE (Copy to any cell to analyze):
A69: Count severe delays by carrier: | B69: =COUNTIFS(fact_orders_1000[delay_minutes],">300",fact_orders_1000[carrier_name],A1) -> 0
A70: Severe delay % by carrier: | B70: =COUNTIFS(fact_orders_1000[delay_minutes],">300",fact_orders_1000[carrier_name],A1)/COUNTIF(fact_orders_1000[carrier_name],A1) -> #DIV/0!
A71: Total severe delays: | B71: =COUNTIF(fact_orders_1000[delay_minutes],">300") -> 12
A72: Avg delay (severe only): | B72: =AVERAGEIF(fact_orders_1000[delay_minutes],">300") -> 455.66667

Sheet RegressionAnalysis
A1: REGRESSION & CORRELATION ANALYSIS - DELAY MINUTES
A3: PART 1: CORRELATION MATRIX (Numeric Variables vs Delay Minutes)
A5: Variable | B5: Correlation (r) | C5: R-Squared (r²) | D5: Interpretation | E5: Direction | F5: Strength
A6: Distance Miles | B6: =CORREL(fact_orders_1000[distance_miles],fact_orders_1000[delay_minutes]) -> 0.02145695 | C6: =B6^2 -> 0.00046040069 | D6: =IF(ABS(B6)>0.5,"Strong",IF(ABS(B6)>0.3,"Moderate","Weak")) -> Weak | E6: =IF(B6>0,"Positive ↑","Negative ↓") -> Positive ↑ | F6: =ABS(B6) -> 0.02145695
A7: Traffic Index | B7: =CORREL(fact_orders_1000[traffic_index],fact_orders_1000[delay_minutes]) -> 0.069512653 | C7: =B7^2 -> 0.0048320089 | D7: =IF(ABS(B7)>0.5,"Strong",IF(ABS(B7)>0.3,"Moderate","Weak")) -> Weak | E7: =IF(B7>0,"Positive ↑","Negative ↓") -> Positive ↑ | F7: =ABS(B7) -> 0.069512653
A8: Weather Severity | B8: =CORREL(fact_orders_1000[weather_severity_index],fact_orders_1000[delay_minutes]) -> 0.31130427 | C8: =B8^2 -> 0.096910351 | D8: =IF(ABS(B8)>0.5,"Strong",IF(ABS(B8)>0.3,"Moderate","Weak")) -> Moderate | E8: =IF(B8>0,"Positive ↑","Negative ↓") -> Positive ↑ | F8: =ABS(B8) -> 0.31130427
A9: Detention Minutes | B9: =CORREL(fact_orders_1000[detention_minutes],fact_orders_1000[delay_minutes]) -> 0.53507289 | C9: =B9^2 -> 0.28630299 | D9: =IF(ABS(B9)>0.5,"Strong",IF(ABS(B9)>0.3,"Moderate","Weak")) -> Strong | E9: =IF(B9>0,"Positive ↑","Negative ↓") -> Positive ↑ | F9: =ABS(B9) -> 0.53507289
A10: Mechanical Flag | B10: =CORREL(fact_orders_1000[mechanical_flag],fact_orders_1000[delay_minutes]) -> 0.35158751 | C10: =B10^2 -> 0.12361378 | D10: =IF(ABS(B10)>0.5,"Strong",IF(ABS(B10)>0.3,"Moderate","Weak")) -> Moderate | E10: =IF(B10>0,"Positive ↑","Negative ↓") -> Positive ↑ | F10: =ABS(B10) -> 0.35158751
A11: Utilization Rate | B11: =CORREL(fact_orders_1000[utilization_rate],fact_orders_1000[delay_minutes]) -> 0.0032605932 | C11: =B11^2 -> 1.0631468e-05 | D11: =IF(ABS(B11)>0.5,"Strong",IF(ABS(B11)>0.3,"Moderate","Weak")) -> Weak | E11: =IF(B11>0,"Positive ↑","Negative ↓") -> Positive ↑ | F11: =ABS(B11) -> 0.0032605932
A12: Load Factor | B12: =CORREL(fact_orders_1000[load_factor],fact_orders_1000[delay_minutes]) -> -0.0054241531 | C12: =B12^2 -> 2.9421437e-05 | D12: =IF(ABS(B12)>0.5,"Strong",IF(ABS(B12)>0.3,"Moderate","Weak")) -> Weak | E12: =IF(B12>0,"Positive ↑","Negative ↓") -> Negative ↓ | F12: =ABS(B12) -> 0.0054241531
A13: Total Miles | B13: =CORREL(fact_orders_1000[total_miles],fact_orders_1000[delay_minutes]) -> 0.022335741 | C13: =B13^2 -> 0.0004988853 | D13: =IF(ABS(B13)>0.5,"Strong",IF(ABS(B13)>0.3,"Moderate","Weak")) -> Weak | E13: =IF(B13>0,"Positive ↑","Negative ↓") -> Positive ↑ | F13: =ABS(B13) -> 0.022335741
A14: Maintenance Cost | B14: =CORREL(fact_orders_1000[maintenance_cost_total],fact_orders_1000[delay_minutes]) -> 0.28833957 | C14: =B14^2 -> 0.083139709 | D14: =IF(ABS(B14)>0.5,"Strong",IF(ABS(B14)>0.3,"Moderate","Weak")) -> Weak | E14: =IF(B14>0,"Positive ↑","Negative ↓") -> Positive ↑ | F14: =ABS(B14) -> 0.28833957
A15: Insurance Risk Score | B15: =CORREL(fact_orders_1000[insurance_risk_score],fact_orders_1000[delay_minutes]) -> -0.027179113 | C15: =B15^2 -> 0.00073870419 | D15: =IF(ABS(B15)>0.5,"Strong",IF(ABS(B15)>0.3,"Moderate","Weak")) -> Weak | E15: =IF(B15>0,"Positive ↑","Negative ↓") -> Negative ↓ | F15: =ABS(B15) -> 0.027179113
A17: PART 2: LINEAR REGRESSION ANALYSIS
A19: Regression: Delay ~ Detention Minutes
A20: Intercept (a) | B20: =INTERCEPT(fact_orders_1000[delay_minutes],fact_orders_1000[detention_minutes]) -> -6.7921932
A21: Slope (b) | B21: =SLOPE(fact_orders_1000[delay_minutes],fact_orders_1000[detention_minutes]) -> 0.79641808
A22: R-Squared | B22: =RSQ(fact_orders_1000[delay_minutes],fact_orders_1000[detention_minutes]) -> 0.28630299
A23: Std Error | B23: =STEYX(fact_orders_1000[delay_minutes],fact_orders_1000[detention_minutes]) -> 67.542835
A25: Regression: Delay ~ Mechanical Flag
A26: Intercept (a) | B26: =INTERCEPT(fact_orders_1000[delay_minutes],fact_orders_1000[mechanical_flag]) -> 4.4703518
A27: Slope (b) | B27: =SLOPE(fact_orders_1000[delay_minutes],fact_orders_1000[mechanical_flag]) -> 398.12965
A28: R-Squared | B28: =RSQ(fact_orders_1000[delay_minutes],fact_orders_1000[mechanical_flag]) -> 0.12361378
A29: Std Error | B29: =STEYX(fact_orders_1000[delay_minutes],fact_orders_1000[mechanical_flag]) -> 74.846262
A31: Regression: Delay ~ Weather Severity
A32: Intercept (a) | B32: =INTERCEPT(fact_orders_1000[delay_minutes],fact_orders_1000[weather_severity_index]) -> 0.27214937
A33: Slope (b) | B33: =SLOPE(fact_orders_1000[delay_minutes],fact_orders_1000[weather_severity_index]) -> 42.799797
A34: R-Squared | B34: =RSQ(fact_orders_1000[delay_minutes],fact_orders_1000[weather_severity_index]) -> 0.096910351
A35: Std Error | B35: =STEYX(fact_orders_1000[delay_minutes],fact_orders_1000[weather_severity_index]) -> 75.977987
A37: PART 3: SEVERE vs NON-SEVERE DELAYS COMPARISON
A39: Variable | B39: Avg (Severe >300) | C39: Avg (Normal ≤300) | D39: Difference | E39: % Higher
A40: Distance Miles | B40: =AVERAGEIF(fact_orders_1000[delay_minutes],">300",fact_orders_1000[distance_miles]) -> 349.25 | C40: =AVERAGEIF(fact_orders_1000[delay_minutes],"<=300",fact_orders_1000[distance_miles]) -> 288.34109 | D40: =B40-C40 -> 60.908907 | E40: =IF(C40=0,0,(B40-C40)/C40) -> 0.21123908
A41: Traffic Index | B41: =AVERAGEIF(fact_orders_1000[delay_minutes],">300",fact_orders_1000[traffic_index]) -> 48.45 | C41: =AVERAGEIF(fact_orders_1000[delay_minutes],"<=300",fact_orders_1000[traffic_index]) -> 50.57419 | D41: =B41-C41 -> -2.1241903 | E41: =IF(C41=0,0,(B41-C41)/C41) -> -0.042001469
A42: Weather Severity | B42: =AVERAGEIF(fact_orders_1000[delay_minutes],">300",fact_orders_1000[weather_severity_index]) -> 1.6583333 | C42: =AVERAGEIF(fact_orders_1000[delay_minutes],"<=300",fact_orders_1000[weather_severity_index]) -> 0.12621457 | D42: =B42-C42 -> 1.5321188 | E42: =IF(C42=0,0,(B42-C42)/C42) -> 12.139
A43: Detention Minutes | B43: =AVERAGEIF(fact_orders_1000[delay_minutes],">300",fact_orders_1000[detention_minutes]) -> 46.083333 | C43: =AVERAGEIF(fact_orders_1000[delay_minutes],"<=300",fact_orders_1000[detention_minutes]) -> 16.283401 | D43: =B43-C43 -> 29.799933 | E43: =IF(C43=0,0,(B43-C43)/C43) -> 1.8300804
A44: Mechanical Flag | B44: =AVERAGEIF(fact_orders_1000[delay_minutes],">300",fact_orders_1000[mechanical_flag]) -> 0.25 | C44: =AVERAGEIF(fact_orders_1000[delay_minutes],"<=300",fact_orders_1000[mechanical_flag]) -> 0.0020242915 | D44: =B44-C44 -> 0.24797571 | E44: =IF(C44=0,0,(B44-C44)/C44) -> 122.5
A45: Maintenance Cost | B45: =AVERAGEIF(fact_orders_1000[delay_minutes],">300",fact_orders_1000[maintenance_cost_total]) -> 221.38417 | C45: =AVERAGEIF(fact_orders_1000[delay_minutes],"<=300",fact_orders_1000[maintenance_cost_total]) -> 55.72833 | D45: =B45-C45 -> 165.65584 | E45: =IF(C45=0,0,(B45-C45)/C45) -> 2.9725606
A46: Insurance Risk | B46: =AVERAGEIF(fact_orders_1000[delay_minutes],">300",fact_orders_1000[insurance_risk_score]) -> 20.566667 | C46: =AVERAGEIF(fact_orders_1000[delay_minutes],"<=300",fact_orders_1000[insurance_risk_score]) -> 18.635223 | D46: =B46-C46 -> 1.931444 | E46: =IF(C46=0,0,(B46-C46)/C46) -> 0.1036448
A48: PART 4: INTERPRETATION GUIDE
A50: 📊 CORRELATION GUIDE:
A51: |r| > 0.7 = Strong correlation
A52: |r| 0.3-0.7 = Moderate correlation
A53: |r| < 0.3 = Weak correlation
A55: 📈 REGRESSION INTERPRETATION:
A56: Slope (b) = Change in delay_minutes for each unit increase in X

Sheet RPM_Correlation
A1: CORRELATION ANALYSIS: COST PER MILE (RPM) - Finding Strong Correlations (>0.7)
A3: PART 1: CORRELATION MATRIX (Variables vs Cost Per Mile)
A5: Variable | B5: Correlation (r) | C5: R² (Explained Variance) | D5: Strength | E5: Meets >0.7? | F5: Impact on RPM
A6: Variable Cost Per Mile | B6: =CORREL(fact_orders_1000!AU2:AU1002,fact_orders_1000!AV2:AV1002) -> 0.72995772 | C6: =B6^2 -> 0.53283827 | D6: =IF(ABS(B6)>=0.7,"🔴 STRONG",IF(ABS(B6)>=0.3,"🟠 Moderate","🟢 Weak")) -> 🔴 STRONG | E6: =IF(ABS(B6)>=0.7,"✅ YES","❌ No") -> ✅ YES | F6: =IF(B6>0,"↑ Higher = Higher RPM","↓ Higher = Lower RPM") -> ↑ Higher = Higher RPM
A7: Fuel Cost Total | B7: =CORREL(fact_orders_1000!AU2:AU1002,fact_orders_1000!AW2:AW1002) -> 0.11422494 | C7: =B7^2 -> 0.013047336 | D7: =IF(ABS(B7)>=0.7,"🔴 STRONG",IF(ABS(B7)>=0.3,"🟠 Moderate","🟢 Weak")) -> 🟢 Weak | E7: =IF(ABS(B7)>=0.7,"✅ YES","❌ No") -> ❌ No | F7: =IF(B7>0,"↑ Higher = Higher RPM","↓ Higher = Lower RPM") -> ↑ Higher = Higher RPM
A8: Maintenance Cost Total | B8: =CORREL(fact_orders_1000!AU2:AU1002,fact_orders_1000!AX2:AX1002) -> 0.025345029 | C8: =B8^2 -> 0.00064237051 | D8: =IF(ABS(B8)>=0.7,"🔴 STRONG",IF(ABS(B8)>=0.3,"🟠 Moderate","🟢 Weak")) -> 🟢 Weak | E8: =IF(ABS(B8)>=0.7,"✅ YES","❌ No") -> ❌ No | F8: =IF(B8>0,"↑ Higher = Higher RPM","↓ Higher = Lower RPM") -> ↑ Higher = Higher RPM
A9: Driver Pay Total | B9: =CORREL(fact_orders_1000!AU2:AU1002,fact_orders_1000!AY2:AY1002) -> 0.1146758 | C9: =B9^2 -> 0.013150539 | D9: =IF(ABS(B9)>=0.7,"🔴 STRONG",IF(ABS(B9)>=0.3,"🟠 Moderate","🟢 Weak")) -> 🟢 Weak | E9: =IF(ABS(B9)>=0.7,"✅ YES","❌ No") -> ❌ No | F9: =IF(B9>0,"↑ Higher = Higher RPM","↓ Higher = Lower RPM") -> ↑ Higher = Higher RPM
A10: Distance Miles | B10: =CORREL(fact_orders_1000!AU2:AU1002,fact_orders_1000!U2:U1002) -> 0.11326436 | C10: =B10^2 -> 0.012828815 | D10: =IF(ABS(B10)>=0.7,"🔴 STRONG",IF(ABS(B10)>=0.3,"🟠 Moderate","🟢 Weak")) -> 🟢 Weak | E10: =IF(ABS(B10)>=0.7,"✅ YES","❌ No") -> ❌ No | F10: =IF(B10>0,"↑ Higher = Higher RPM","↓ Higher = Lower RPM") -> ↑ Higher = Higher RPM
A11: Total Miles | B11: =CORREL(fact_orders_1000!AU2:AU1002,fact_orders_1000!Y2:Y1002) -> 0.11596771 | C11: =B11^2 -> 0.013448509 | D11: =IF(ABS(B11)>=0.7,"🔴 STRONG",IF(ABS(B11)>=0.3,"🟠 Moderate","🟢 Weak")) -> 🟢 Weak | E11: =IF(ABS(B11)>=0.7,"✅ YES","❌ No") -> ❌ No | F11: =IF(B11>0,"↑ Higher = Higher RPM","↓ Higher = Lower RPM") -> ↑ Higher = Higher RPM
A12: Loaded Miles | B12: =CORREL(fact_orders_1000!AU2:AU1002,fact_orders_1000!X2:X1002) -> 0.11402896 | C12: =B12^2 -> 0.013002603 | D12: =IF(ABS(B12)>=0.7,"🔴 STRONG",IF(ABS(B12)>=0.3,"🟠 Moderate","🟢 Weak")) -> 🟢 Weak | E12: =IF(ABS(B12)>=0.7,"✅ YES","❌ No") -> ❌ No | F12: =IF(B12>0,"↑ Higher = Higher RPM","↓ Higher = Lower RPM") -> ↑ Higher = Higher RPM
A13: Empty Miles | B13: =CORREL(fact_orders_1000!AU2:AU1002,fact_orders_1000!V2:V1002) -> 0.070521686 | C13: =B13^2 -> 0.0049733082 | D13: =IF(ABS(B13)>=0.7,"🔴 STRONG",IF(ABS(B13)>=0.3,"🟠 Moderate","🟢 Weak")) -> 🟢 Weak | E13: =IF(ABS(B13)>=0.7,"✅ YES","❌ No") -> ❌ No | F13: =IF(B13>0,"↑ Higher = Higher RPM","↓ Higher = Lower RPM") -> ↑ Higher = Higher RPM
A14: Deadhead Miles | B14: =CORREL(fact_orders_1000!AU2:AU1002,fact_orders_1000!W2:W1002) -> -0.024814487 | C14: =B14^2 -> 0.00061575875 | D14: =IF(ABS(B14)>=0.7,"🔴 STRONG",IF(ABS(B14)>=0.3,"🟠 Moderate","🟢 Weak")) -> 🟢 Weak | E14: =IF(ABS(B14)>=0.7,"✅ YES","❌ No") -> ❌ No | F14: =IF(B14>0,"↑ Higher = Higher RPM","↓ Higher = Lower RPM") -> ↓ Higher = Lower RPM
A15: Shipment Value USD | B15: =CORREL(fact_orders_1000!AU2:AU1002,fact_orders_1000!AL2:AL1002) -> -0.023009145 | C15: =B15^2 -> 0.00052942075 | D15: =IF(ABS(B15)>=0.7,"🔴 STRONG",IF(ABS(B15)>=0.3,"🟠 Moderate","🟢 Weak")) -> 🟢 Weak | E15: =IF(ABS(B15)>=0.7,"✅ YES","❌ No") -> ❌ No | F15: =IF(B15>0,"↑ Higher = Higher RPM","↓ Higher = Lower RPM") -> ↓ Higher = Lower RPM
A16: Delay Minutes | B16: =CORREL(fact_orders_1000!AU2:AU1002,fact_orders_1000!AE2:AE1002) -> -0.0036328486 | C16: =B16^2 -> 1.3197589e-05 | D16: =IF(ABS(B16)>=0.7,"🔴 STRONG",IF(ABS(B16)>=0.3,"🟠 Moderate","🟢 Weak")) -> 🟢 Weak | E16: =IF(ABS(B16)>=0.7,"✅ YES","❌ No") -> ❌ No | F16: =IF(B16>0,"↑ Higher = Higher RPM","↓ Higher = Lower RPM") -> ↓ Higher = Lower RPM
A17: Detention Minutes | B17: =CORREL(fact_orders_1000!AU2:AU1002,fact_orders_1000!AF2:AF1002) -> -0.019280617 | C17: =B17^2 -> 0.00037174219 | D17: =IF(ABS(B17)>=0.7,"🔴 STRONG",IF(ABS(B17)>=0.3,"🟠 Moderate","🟢 Weak")) -> 🟢 Weak | E17: =IF(ABS(B17)>=0.7,"✅ YES","❌ No") -> ❌ No | F17: =IF(B17>0,"↑ Higher = Higher RPM","↓ Higher = Lower RPM") -> ↓ Higher = Lower RPM
A18: Weather Severity | B18: =CORREL(fact_orders_1000!AU2:AU1002,fact_orders_1000!AG2:AG1002) -> 0.042644051 | C18: =B18^2 -> 0.001818515 | D18: =IF(ABS(B18)>=0.7,"🔴 STRONG",IF(ABS(B18)>=0.3,"🟠 Moderate","🟢 Weak")) -> 🟢 Weak | E18: =IF(ABS(B18)>=0.7,"✅ YES","❌ No") -> ❌ No | F18: =IF(B18>0,"↑ Higher = Higher RPM","↓ Higher = Lower RPM") -> ↑ Higher = Higher RPM
A19: Traffic Index | B19: =CORREL(fact_orders_1000!AU2:AU1002,fact_orders_1000!AH2:AH1002) -> 0.025284431 | C19: =B19^2 -> 0.00063930247 | D19: =IF(ABS(B19)>=0.7,"🔴 STRONG",IF(ABS(B19)>=0.3,"🟠 Moderate","🟢 Weak")) -> 🟢 Weak | E19: =IF(ABS(B19)>=0.7,"✅ YES","❌ No") -> ❌ No | F19: =IF(B19>0,"↑ Higher = Higher RPM","↓ Higher = Lower RPM") -> ↑ Higher = Higher RPM
A20: Utilization Rate | B20: =CORREL(fact_orders_1000!AU2:AU1002,fact_orders_1000!AJ2:AJ1002) -> 0.012910874 | C20: =B20^2 -> 0.00016669067 | D20: =IF(ABS(B20)>=0.7,"🔴 STRONG",IF(ABS(B20)>=0.3,"🟠 Moderate","🟢 Weak")) -> 🟢 Weak | E20: =IF(ABS(B20)>=0.7,"✅ YES","❌ No") -> ❌ No | F20: =IF(B20>0,"↑ Higher = Higher RPM","↓ Higher = Lower RPM") -> ↑ Higher = Higher RPM
A21: Load Factor | B21: =CORREL(fact_orders_1000!AU2:AU1002,fact_orders_1000!AK2:AK1002) -> 0.063610923 | C21: =B21^2 -> 0.0040463495 | D21: =IF(ABS(B21)>=0.7,"🔴 STRONG",IF(ABS(B21)>=0.3,"🟠 Moderate","🟢 Weak")) -> 🟢 Weak | E21: =IF(ABS(B21)>=0.7,"✅ YES","❌ No") -> ❌ No | F21: =IF(B21>0,"↑ Higher = Higher RPM","↓ Higher = Lower RPM") -> ↑ Higher = Higher RPM
A22: Insurance Risk Score | B22: =CORREL(fact_orders_1000!AU2:AU1002,fact_orders_1000!AZ2:AZ1002) -> 0.043186845 | C22: =B22^2 -> 0.0018651036 | D22: =IF(ABS(B22)>=0.7,"🔴 STRONG",IF(ABS(B22)>=0.3,"🟠 Moderate","🟢 Weak")) -> 🟢 Weak | E22: =IF(ABS(B22)>=0.7,"✅ YES","❌ No") -> ❌ No | F22: =IF(B22>0,"↑ Higher = Higher RPM","↓ Higher = Lower RPM") -> ↑ Higher = Higher RPM
A23: Maintenance Risk Score | B23: =CORREL(fact_orders_1000!AU2:AU1002,fact_orders_1000!BA2:BA1002) -> -0.011110012 | C23: =B23^2 -> 0.00012343236 | D23: =IF(ABS(B23)>=0.7,"🔴 STRONG",IF(ABS(B23)>=0.3,"🟠 Moderate","🟢 Weak")) -> 🟢 Weak | E23: =IF(ABS(B23)>=0.7,"✅ YES","❌ No") -> ❌ No | F23: =IF(B23>0,"↑ Higher = Higher RPM","↓ Higher = Lower RPM") -> ↓ Higher = Lower RPM
A26: PART 2: STRONG CORRELATIONS SUMMARY (|r| > 0.7)
A28: Variables with correlation > 0.7 indicate strong predictors of Cost Per Mile:
A30: Count of Strong Correlations (>0.7): | B30: =COUNTIF(E6:E23,"✅ YES") -> 1
A33: PART 3: REGRESSION EQUATIONS FOR TOP PREDICTORS
A35: Regression: Cost_Per_Mile ~ Variable_Cost_Per_Mile
A36: Intercept (a) | B36: =INTERCEPT(fact_orders_1000!AU2:AU1002,fact_orders_1000!AV2:AV1002) -> 1.0727742
A37: Slope (b) | B37: =SLOPE(fact_orders_1000!AU2:AU1002,fact_orders_1000!AV2:AV1002) -> 0.7591332
A38: R-Squared | B38: =RSQ(fact_orders_1000!AU2:AU1002,fact_orders_1000!AV2:AV1002) -> 0.53283827
A39: Equation | B39: ="RPM = "&ROUND(B36,2)&" + "&ROUND(B37,2)&" × Variable_CPM" -> RPM = 1.07 + 0.76 × Variable_CPM
A42: Regression: Cost_Per_Mile ~ Fuel_Cost_Total
A43: Intercept (a) | B43: =INTERCEPT(fact_orders_1000!AU2:AU1002,fact_orders_1000!AW2:AW1002) -> 2.2146173
A44: Slope (b) | B44: =SLOPE(fact_orders_1000!AU2:AU1002,fact_orders_1000!AW2:AW1002) -> 0.0001512424
A45: R-Squared | B45: =RSQ(fact_orders_1000!AU2:AU1002,fact_orders_1000!AW2:AW1002) -> 0.013047336
A46: Equation | B46: ="RPM = "&ROUND(B43,2)&" + "&ROUND(B44,4)&" × Fuel_Cost" -> RPM = 2.21 + 0.0002 × Fuel_Cost
A49: PART 4: BUSINESS IMPACT - What Drives Cost Per Mile?
A51: Category | B51: Avg RPM | C51: Count | D51: vs Overall Avg
A52: Overall Average RPM | B52: =AVERAGE(fact_orders_1000!AU2:AU1002) -> 2.25372 | C52: =COUNT(fact_orders_1000!AU2:AU1002) -> 1000 | D52: Baseline
A54: RPM by Truck Type:
A55: Dry Van | B55: =AVERAGEIF(fact_orders_1000!Z2:Z1002,"Dry Van",fact_orders_1000!AU2:AU1002) -> 2.1807172 | C55: =COUNTIF(fact_orders_1000!Z2:Z1002,"Dry Van") -> 488 | D55: =B55-B52 -> -0.073002787
A56: Flatbed | B56: =AVERAGEIF(fact_orders_1000!Z2:Z1002,"Flatbed",fact_orders_1000!AU2:AU1002) -> 2.3125197 | C56: =COUNTIF(fact_orders_1000!Z2:Z1002,"Flatbed") -> 127 | D56: =B56-B52 -> 0.058799685
A57: Intermodal | B57: =AVERAGEIF(fact_orders_1000!Z2:Z1002,"Intermodal",fact_orders_1000!AU2:AU1002) -> 2.0889 | C57: =COUNTIF(fact_orders_1000!Z2:Z1002,"Intermodal") -> 100 | D57: =B57-B52 -> -0.16482
A58: Reefer | B58: =AVERAGEIF(fact_orders_1000!Z2:Z1002,"Reefer",fact_orders_1000!AU2:AU1002) -> 2.3758723 | C58: =COUNTIF(fact_orders_1000!Z2:Z1002,"Reefer") -> 235 | D58: =B58-B52 -> 0.12215234
A59: Tanker | B59: =AVERAGEIF(fact_orders_1000!Z2:Z1002,"Tanker",fact_orders_1000!AU2:AU1002) -> 2.5724 | C59: =COUNTIF(fact_orders_1000!Z2:Z1002,"Tanker") -> 50 | D59: =B59-B52 -> 0.31868

Sheet OpCostAnalysis
A1: OPERATIONAL COST METRICS & REGRESSION ANALYSIS
A3: PART 1: KEY OPERATIONAL COST METRICS
A5: Metric | B5: Value | C5: Unit | D5: Interpretation
A6: Total Fuel Cost | B6: =SUM(fact_orders_1000[fuel_cost_total]) -> 258543.21 | C6: USD | D6: Total fuel expenditure
A7: Total Maintenance Cost | B7: =SUM(fact_orders_1000[maintenance_cost_total]) -> 57716.2 | C7: USD | D7: Total maintenance
A8: Total Driver Pay | B8: =SUM(fact_orders_1000[driver_pay_total]) -> 201195.05 | C8: USD | D8: Total driver comp
A9: Total Operating Cost | B9: =B6+B7+B8 -> 517454.46 | C9: USD | D9: Sum of all costs
A11: Average Cost Per Mile | B11: =AVERAGE(fact_orders_1000[cost_per_mile]) -> 2.25372 | C11: $/mile | D11: Avg CPM
A12: Average Variable CPM | B12: =AVERAGE(fact_orders_1000[variable_cost_per_mile]) -> 1.5552077 | C12: $/mile | D12: Avg Var CPM
A13: Avg Fuel Cost/Ship | B13: =AVERAGE(fact_orders_1000[fuel_cost_total]) -> 258.54321 | C13: USD | D13: Avg fuel/shipment
A14: Avg Maint Cost/Ship | B14: =AVERAGE(fact_orders_1000[maintenance_cost_total]) -> 57.7162 | C14: USD | D14: Avg maint/shipment
A15: Avg Driver Pay/Ship | B15: =AVERAGE(fact_orders_1000[driver_pay_total]) -> 201.19505 | C15: USD | D15: Avg pay/shipment
A17: Total Miles Operated | B17: =SUM(fact_orders_1000[total_miles]) -> 333652 | C17: miles | D17: Total distance
A18: Total Deadhead Miles | B18: =SUM(fact_orders_1000[deadhead_miles]) -> 19208.6 | C18: miles | D18: Empty miles
A19: Deadhead Percentage | B19: =B18/B17*100 -> 5.7570762 | C19: % | D19: Unproductive %
A22: PART 2: COST CORRELATION MATRIX (Finding >0.7 Strong Correlations)
A24: Variable X | B24: Variable Y | C24: Correlation (r) | D24: R² (%) | E24: Strength
A25: Fuel Cost | B25: Total Miles | C25: =CORREL(fact_orders_1000[fuel_cost_total],fact_orders_1000[total_miles]) -> 0.97898241 | D25: =C25^2*100 -> 95.840656 | E25: =IF(ABS(C25)>0.7,"🔴 STRONG",IF(ABS(C25)>0.3,"🟡 MODERATE","🟢 WEAK")) -> 🔴 STRONG
A26: Fuel Cost | B26: Distance Miles | C26: =CORREL(fact_orders_1000[fuel_cost_total],fact_orders_1000[distance_miles]) -> 0.97469484 | D26: =C26^2*100 -> 95.003004 | E26: =IF(ABS(C26)>0.7,"🔴 STRONG",IF(ABS(C26)>0.3,"🟡 MODERATE","🟢 WEAK")) -> 🔴 STRONG
A27: Fuel Cost | B27: Loaded Miles | C27: =CORREL(fact_orders_1000[fuel_cost_total],fact_orders_1000[loaded_miles]) -> 0.97538375 | D27: =C27^2*100 -> 95.137346 | E27: =IF(ABS(C27)>0.7,"🔴 STRONG",IF(ABS(C27)>0.3,"🟡 MODERATE","🟢 WEAK")) -> 🔴 STRONG
A28: Fuel Cost | B28: Deadhead Miles | C28: =CORREL(fact_orders_1000[fuel_cost_total],fact_orders_1000[deadhead_miles]) -> 0.069066686 | D28: =C28^2*100 -> 0.47702071 | E28: =IF(ABS(C28)>0.7,"🔴 STRONG",IF(ABS(C28)>0.3,"🟡 MODERATE","🟢 WEAK")) -> 🟢 WEAK
A29: Maint Cost | B29: Total Miles | C29: =CORREL(fact_orders_1000[maintenance_cost_total],fact_orders_1000[total_miles]) -> 0.45580578 | D29: =C29^2*100 -> 20.775891 | E29: =IF(ABS(C29)>0.7,"🔴 STRONG",IF(ABS(C29)>0.3,"🟡 MODERATE","🟢 WEAK")) -> 🟡 MODERATE
A30: Maint Cost | B30: Delay Minutes | C30: =CORREL(fact_orders_1000[maintenance_cost_total],fact_orders_1000[delay_minutes]) -> 0.28833957 | D30: =C30^2*100 -> 8.3139709 | E30: =IF(ABS(C30)>0.7,"🔴 STRONG",IF(ABS(C30)>0.3,"🟡 MODERATE","🟢 WEAK")) -> 🟢 WEAK
A31: Maint Cost | B31: Mechanical Flag | C31: =CORREL(fact_orders_1000[maintenance_cost_total],fact_orders_1000[mechanical_flag]) -> 0.81199918 | D31: =C31^2*100 -> 65.934266 | E31: =IF(ABS(C31)>0.7,"🔴 STRONG",IF(ABS(C31)>0.3,"🟡 MODERATE","🟢 WEAK")) -> 🔴 STRONG
A32: Driver Pay | B32: Total Miles | C32: =CORREL(fact_orders_1000[driver_pay_total],fact_orders_1000[total_miles]) -> 0.97806999 | D32: =C32^2*100 -> 95.662091 | E32: =IF(ABS(C32)>0.7,"🔴 STRONG",IF(ABS(C32)>0.3,"🟡 MODERATE","🟢 WEAK")) -> 🔴 STRONG
A33: Driver Pay | B33: Delivery Time | C33: =CORREL(fact_orders_1000[driver_pay_total],fact_orders_1000[delivery_times]) -> #DIV/0! | D33: =C33^2*100 -> #DIV/0! | E33: =IF(ABS(C33)>0.7,"🔴 STRONG",IF(ABS(C33)>0.3,"🟡 MODERATE","🟢 WEAK")) -> #DIV/0!
A34: Driver Pay | B34: Detention Min | C34: =CORREL(fact_orders_1000[driver_pay_total],fact_orders_1000[detention_minutes]) -> -0.024261302 | D34: =C34^2*100 -> 0.058861076 | E34: =IF(ABS(C34)>0.7,"🔴 STRONG",IF(ABS(C34)>0.3,"🟡 MODERATE","🟢 WEAK")) -> 🟢 WEAK
A35: Cost Per Mile | B35: Variable CPM | C35: =CORREL(fact_orders_1000[cost_per_mile],fact_orders_1000[variable_cost_per_mile]) -> 0.72995772 | D35: =C35^2*100 -> 53.283827 | E35: =IF(ABS(C35)>0.7,"🔴 STRONG",IF(ABS(C35)>0.3,"🟡 MODERATE","🟢 WEAK")) -> 🔴 STRONG
A36: Cost Per Mile | B36: Utilization | C36: =CORREL(fact_orders_1000[cost_per_mile],fact_orders_1000[utilization_rate]) -> 0.012910874 | D36: =C36^2*100 -> 0.016669067 | E36: =IF(ABS(C36)>0.7,"🔴 STRONG",IF(ABS(C36)>0.3,"🟡 MODERATE","🟢 WEAK")) -> 🟢 WEAK
A37: Cost Per Mile | B37: Load Factor | C37: =CORREL(fact_orders_1000[cost_per_mile],fact_orders_1000[load_factor]) -> 0.063610923 | D37: =C37^2*100 -> 0.40463495 | E37: =IF(ABS(C37)>0.7,"🔴 STRONG",IF(ABS(C37)>0.3,"🟡 MODERATE","🟢 WEAK")) -> 🟢 WEAK
A38: Cost Per Mile | B38: Shipment Value | C38: =CORREL(fact_orders_1000[cost_per_mile],fact_orders_1000[shipment_value_usd]) -> -0.023009145 | D38: =C38^2*100 -> 0.052942075 | E38: =IF(ABS(C38)>0.7,"🔴 STRONG",IF(ABS(C38)>0.3,"🟡 MODERATE","🟢 WEAK")) -> 🟢 WEAK
A41: PART 3: REGRESSION ANALYSIS - PREDICTING COSTS
A43: REGRESSION 1: Fuel Cost = f(Total Miles)
A44: Intercept (a) | B44: =INTERCEPT(fact_orders_1000[fuel_cost_total],fact_orders_1000[total_miles]) -> -3.1532926
A45: Slope (b) | B45: =SLOPE(fact_orders_1000[fuel_cost_total],fact_orders_1000[total_miles]) -> 0.78433968
A46: R-Squared | B46: =RSQ(fact_orders_1000[fuel_cost_total],fact_orders_1000[total_miles]) -> 0.95840656
A47: Std Error | B47: =STEYX(fact_orders_1000[fuel_cost_total],fact_orders_1000[total_miles]) -> 34.106144
A49: REGRESSION 2: Maint Cost = f(Total Miles)
A50: Slope (b) | B50: =SLOPE(fact_orders_1000[maintenance_cost_total],fact_orders_1000[total_miles]) -> 0.15567304
A51: R-Squared | B51: =RSQ(fact_orders_1000[maintenance_cost_total],fact_orders_1000[total_miles]) -> 0.20775891
A52: Std Error | B52: =STEYX(fact_orders_1000[maintenance_cost_total],fact_orders_1000[total_miles]) -> 63.453147
A55: REGRESSION 3: Driver Pay = f(Total Miles)
A56: Intercept (a) | B56: =INTERCEPT(fact_orders_1000[driver_pay_total],fact_orders_1000[total_miles]) -> -1.6226774
A57: Slope (b) | B57: =SLOPE(fact_orders_1000[driver_pay_total],fact_orders_1000[total_miles]) -> 0.60787206
A58: R-Squared | B58: =RSQ(fact_orders_1000[driver_pay_total],fact_orders_1000[total_miles]) -> 0.95662091
A59: Std Error | B59: =STEYX(fact_orders_1000[driver_pay_total],fact_orders_1000[total_miles]) -> 27.019255
A61: REGRESSION 4: CPM = f(Variable CPM) [STRONGEST >0.7]
A62: Intercept (a) | B62: =INTERCEPT(fact_orders_1000[cost_per_mile],fact_orders_1000[variable_cost_per_mile]) -> 1.0727742
A63: Slope (b) | B63: =SLOPE(fact_orders_1000[cost_per_mile],fact_orders_1000[variable_cost_per_mile]) -> 0.7591332
A64: R-Squared | B64: =RSQ(fact_orders_1000[cost_per_mile],fact_orders_1000[variable_cost_per_mile]) -> 0.53283827
A65: Std Error | B65: =STEYX(fact_orders_1000[cost_per_mile],fact_orders_1000[variable_cost_per_mile]) -> 0.15154788
A68: PART 4: COST ANALYSIS BY TRUCK TYPE
A70: Truck Type | B70: Avg Fuel | C70: Avg Maint | D70: Avg Driver Pay | E70: Avg CPM | F70: Count
A71: Dry Van | B71: =AVERAGEIF(fact_orders_1000[truck_types],"Dry Van",fact_orders_1000[fuel_cost_total]) -> 253.48684 | C71: =AVERAGEIF(fact_orders_1000[truck_types],"Dry Van",fact_orders_1000[maintenance_cost_total]) -> 57.627848 | D71: =AVERAGEIF(fact_orders_1000[truck_types],"Dry Van",fact_orders_1000[driver_pay_total]) -> 198.62695 | E71: =AVERAGEIF(fact_orders_1000[truck_types],"Dry Van",fact_orders_1000[cost_per_mile]) -> 2.1807172 | F71: =COUNTIF(fact_orders_1000[truck_types],"Dry Van") -> 488
A72: Flatbed | B72: =AVERAGEIF(fact_orders_1000[truck_types],"Flatbed",fact_orders_1000[fuel_cost_total]) -> 250.06717 | C72: =AVERAGEIF(fact_orders_1000[truck_types],"Flatbed",fact_orders_1000[maintenance_cost_total]) -> 52.534724 | D72: =AVERAGEIF(fact_orders_1000[truck_types],"Flatbed",fact_orders_1000[driver_pay_total]) -> 194.67583 | E72: =AVERAGEIF(fact_orders_1000[truck_types],"Flatbed",fact_orders_1000[cost_per_mile]) -> 2.3125197 | F72: =COUNTIF(fact_orders_1000[truck_types],"Flatbed") -> 127
A73: Intermodal | B73: =AVERAGEIF(fact_orders_1000[truck_types],"Intermodal",fact_orders_1000[fuel_cost_total]) -> 256.2055 | C73: =AVERAGEIF(fact_orders_1000[truck_types],"Intermodal",fact_orders_1000[maintenance_cost_total]) -> 69.698 | D73: =AVERAGEIF(fact_orders_1000[truck_types],"Intermodal",fact_orders_1000[driver_pay_total]) -> 195.2922 | E73: =AVERAGEIF(fact_orders_1000[truck_types],"Intermodal",fact_orders_1000[cost_per_mile]) -> 2.0889 | F73: =COUNTIF(fact_orders_1000[truck_types],"Intermodal") -> 100
A74: Reefer | B74: =AVERAGEIF(fact_orders_1000[truck_types],"Reefer",fact_orders_1000[fuel_cost_total]) -> 276.38272 | C74: =AVERAGEIF(fact_orders_1000[truck_types],"Reefer",fact_orders_1000[maintenance_cost_total]) -> 57.043234 | D74: =AVERAGEIF(fact_orders_1000[truck_types],"Reefer",fact_orders_1000[driver_pay_total]) -> 214.04302 | E74: =AVERAGEIF(fact_orders_1000[truck_types],"Reefer",fact_orders_1000[cost_per_mile]) -> 2.3758723 | F74: =COUNTIF(fact_orders_1000[truck_types],"Reefer") -> 235
A75: Tanker | B75: =AVERAGEIF(fact_orders_1000[truck_types],"Tanker",fact_orders_1000[fuel_cost_total]) -> 250.2522 | C75: =AVERAGEIF(fact_orders_1000[truck_types],"Tanker",fact_orders_1000[maintenance_cost_total]) -> 50.9388 | D75: =AVERAGEIF(fact_orders_1000[truck_types],"Tanker",fact_orders_1000[driver_pay_total]) -> 194.2388 | E75: =AVERAGEIF(fact_orders_1000[truck_types],"Tanker",fact_orders_1000[cost_per_mile]) -> 2.5724 | F75: =COUNTIF(fact_orders_1000[truck_types],"Tanker") -> 50
A78: PART 5: COST ANALYSIS BY CARRIER
A80: Carrier | B80: Avg Fuel | C80: Avg Maint | D80: Avg Driver Pay | E80: Avg CPM | F80: Shipments
A81: Atlantic Freightways | B81: =AVERAGEIF(fact_orders_1000[carrier_name],"Atlantic Freightways",fact_orders_1000[fuel_cost_total]) -> 286.99042 | C81: =AVERAGEIF(fact_orders_1000[carrier_name],"Atlantic Freightways",fact_orders_1000[maintenance_cost_total]) -> 74.396944 | D81: =AVERAGEIF(fact_orders_1000[carrier_name],"Atlantic Freightways",fact_orders_1000[driver_pay_total]) -> 217.06528 | E81: =AVERAGEIF(fact_orders_1000[carrier_name],"Atlantic Freightways",fact_orders_1000[cost_per_mile]) -> 2.2970833 | F81: =COUNTIF(fact_orders_1000[carrier_name],"Atlantic Freightways") -> 72
A82: Blue Ridge Logistics | B82: =AVERAGEIF(fact_orders_1000[carrier_name],"Blue Ridge Logistics",fact_orders_1000[fuel_cost_total]) -> 258.90774 | C82: =AVERAGEIF(fact_orders_1000[carrier_name],"Blue Ridge Logistics",fact_orders_1000[maintenance_cost_total]) -> 58.194897 | D82: =AVERAGEIF(fact_orders_1000[carrier_name],"Blue Ridge Logistics",fact_orders_1000[driver_pay_total]) -> 202.09675 | E82: =AVERAGEIF(fact_orders_1000[carrier_name],"Blue Ridge Logistics",fact_orders_1000[cost_per_mile]) -> 2.2439918 | F82: =COUNTIF(fact_orders_1000[carrier_name],"Blue Ridge Logistics") -> 243
A83: Cascade Cargo | B83: =AVERAGEIF(fact_orders_1000[carrier_name],"Cascade Cargo",fact_orders_1000[fuel_cost_total]) -> 232.87234 | C83: =AVERAGEIF(fact_orders_1000[carrier_name],"Cascade Cargo",fact_orders_1000[maintenance_cost_total]) -> 55.297143 | D83: =AVERAGEIF(fact_orders_1000[carrier_name],"Cascade Cargo",fact_orders_1000[driver_pay_total]) -> 182.95558 | E83: =AVERAGEIF(fact_orders_1000[carrier_name],"Cascade Cargo",fact_orders_1000[cost_per_mile]) -> 2.2402597 | F83: =COUNTIF(fact_orders_1000[carrier_name],"Cascade Cargo") -> 77
A84: Desert Road Haulers | B84: =AVERAGEIF(fact_orders_1000[carrier_name],"Desert Road Haulers",fact_orders_1000[fuel_cost_total]) -> 241.50082 | C84: =AVERAGEIF(fact_orders_1000[carrier_name],"Desert Road Haulers",fact_orders_1000[maintenance_cost_total]) -> 51.721837 | D84: =AVERAGEIF(fact_orders_1000[carrier_name],"Desert Road Haulers",fact_orders_1000[driver_pay_total]) -> 195.56735 | E84: =AVERAGEIF(fact_orders_1000[carrier_name],"Desert Road Haulers",fact_orders_1000[cost_per_mile]) -> 2.2959184 | F84: =COUNTIF(fact_orders_1000[carrier_name],"Desert Road Haulers") -> 49
A85: Great Lakes Carriers | B85: =AVERAGEIF(fact_orders_1000[carrier_name],"Great Lakes Carriers",fact_orders_1000[fuel_cost_total]) -> 247.7045 | C85: =AVERAGEIF(fact_orders_1000[carrier_name],"Great Lakes Carriers",fact_orders_1000[maintenance_cost_total]) -> 50.291 | D85: =AVERAGEIF(fact_orders_1000[carrier_name],"Great Lakes Carriers",fact_orders_1000[driver_pay_total]) -> 194.03325 | E85: =AVERAGEIF(fact_orders_1000[carrier_name],"Great Lakes Carriers",fact_orders_1000[cost_per_mile]) -> 2.287 | F85: =COUNTIF(fact_orders_1000[carrier_name],"Great Lakes Carriers") -> 80
A86: Keystone Freight | B86: =AVERAGEIF(fact_orders_1000[carrier_name],"Keystone Freight",fact_orders_1000[fuel_cost_total]) -> 276.96535 | C86: =AVERAGEIF(fact_orders_1000[carrier_name],"Keystone Freight",fact_orders_1000[maintenance_cost_total]) -> 58.203099 | D86: =AVERAGEIF(fact_orders_1000[carrier_name],"Keystone Freight",fact_orders_1000[driver_pay_total]) -> 225.15239 | E86: =AVERAGEIF(fact_orders_1000[carrier_name],"Keystone Freight",fact_orders_1000[cost_per_mile]) -> 2.2785915 | F86: =COUNTIF(fact_orders_1000[carrier_name],"Keystone Freight") -> 71
A87: Lone Star Transport | B87: =AVERAGEIF(fact_orders_1000[carrier_name],"Lone Star Transport",fact_orders_1000[fuel_cost_total]) -> 273.1703 | C87: =AVERAGEIF(fact_orders_1000[carrier_name],"Lone Star Transport",fact_orders_1000[maintenance_cost_total]) -> 55.972079 | D87: =AVERAGEIF(fact_orders_1000[carrier_name],"Lone Star Transport",fact_orders_1000[driver_pay_total]) -> 210.27376 | E87: =AVERAGEIF(fact_orders_1000[carrier_name],"Lone Star Transport",fact_orders_1000[cost_per_mile]) -> 2.2043564 | F87: =COUNTIF(fact_orders_1000[carrier_name],"Lone Star Transport") -> 101
A88: Midwest Express Trucking | B88: =AVERAGEIF(fact_orders_1000[carrier_name],"Midwest Express Trucking",fact_orders_1000[fuel_cost_total]) -> 249.76217 | C88: =AVERAGEIF(fact_orders_1000[carrier_name],"Midwest Express Trucking",fact_orders_1000[maintenance_cost_total]) -> 53.365978 | D88: =AVERAGEIF(fact_orders_1000[carrier_name],"Midwest Express Trucking",fact_orders_1000[driver_pay_total]) -> 191.85293 | E88: =AVERAGEIF(fact_orders_1000[carrier_name],"Midwest Express Trucking",fact_orders_1000[cost_per_mile]) -> 2.2975 | F88: =COUNTIF(fact_orders_1000[carrier_name],"Midwest Express Trucking") -> 92
A89: Pacific Linehaul | B89: =AVERAGEIF(fact_orders_1000[carrier_name],"Pacific Linehaul",fact_orders_1000[fuel_cost_total]) -> 253.18291 | C89: =AVERAGEIF(fact_orders_1000[carrier_name],"Pacific Linehaul",fact_orders_1000[maintenance_cost_total]) -> 66.199417 | D89: =AVERAGEIF(fact_orders_1000[carrier_name],"Pacific Linehaul",fact_orders_1000[driver_pay_total]) -> 195.27903 | E89: =AVERAGEIF(fact_orders_1000[carrier_name],"Pacific Linehaul",fact_orders_1000[cost_per_mile]) -> 2.2545631 | F89: =COUNTIF(fact_orders_1000[carrier_name],"Pacific Linehaul") -> 103
A90: Sunbelt Haulage | B90: =AVERAGEIF(fact_orders_1000[carrier_name],"Sunbelt Haulage",fact_orders_1000[fuel_cost_total]) -> 259.58527 | C90: =AVERAGEIF(fact_orders_1000[carrier_name],"Sunbelt Haulage",fact_orders_1000[maintenance_cost_total]) -> 52.579643 | D90: =AVERAGEIF(fact_orders_1000[carrier_name],"Sunbelt Haulage",fact_orders_1000[driver_pay_total]) -> 198.89393 | E90: =AVERAGEIF(fact_orders_1000[carrier_name],"Sunbelt Haulage",fact_orders_1000[cost_per_mile]) -> 2.2059821 | F90: =COUNTIF(fact_orders_1000[carrier_name],"Sunbelt Haulage") -> 112
A93: PART 6: METHODOLOGY - HOW TO ANALYZE OPERATIONAL COSTS
A95: Step | B95: Method | C95: Excel Formula | D95: Purpose
A96: 1. Calculate Totals: =SUM(range) - Total cost exposure
A97: 2. Calculate Averages: =AVERAGE(range) - Per-unit benchmarks
A98: 3. Find Correlations: =CORREL(X,Y) - Identify cost drivers
A99: 4. Assess Strength: =RSQ(Y,X) - >70% means strong link
A100: 5. Build Regression: =INTERCEPT() + =SLOPE() - Predict costs
A101: 6. Segment Analysis: =AVERAGEIF() - Compare groups
A103: INTERPRETATION GUIDE:
A104: |r| > 0.7 = 🔴 STRONG - X strongly predicts Y - Primary cost driver
A105: |r| 0.3-0.7 = 🟡 MODERATE - Some predictive power
A106: |r| < 0.3 = 🟢 WEAK - No meaningful relationship
A108: KEY STRONG CORRELATIONS FOUND (>0.7):
A109: ✅ Fuel Cost ↔ Total Miles: r=0.979 (96% variance explained)
... A114: Cost Reduction​ Performance Improvement​ Risk Mitigation​ Operational Efficiency. based on the regression and other analysis, how can cost be reduced?

Sheet CostStrategy
A1: COST REDUCTION STRATEGIES - BASED ON REGRESSION & CORRELATION ANALYSIS
A3: EXECUTIVE SUMMARY: KEY COST DRIVERS IDENTIFIED
A5: Cost Driver | B5: Correlation | C5: R² Impact | D5: Potential Savings | E5: Priority | F5: Strategy
A6: Variable Cost Per Mile | B6: r = 0.73 | C6: 0.533 | D6: 15-20% of CPM | E6: 🔴 HIGH | F6: Optimize fuel & labor efficiency
A7: Fuel Cost → Miles | B7: r = 0.98 | C7: 0.958 | D7: $0.78/mile | E7: 🔴 HIGH | F7: Route optimization
A8: Driver Pay → Miles | B8: r = 0.98 | C8: 0.957 | D8: $0.61/mile | E8: 🔴 HIGH | F8: Efficient routing
A9: Maintenance → Mechanical | B9: r = 0.81 | C9: 0.659 | D9: $165/incident | E9: 🟠 MEDIUM | F9: Preventive maintenance
A10: Deadhead Miles | B10: 0.0576 | C10: N/A | D10: ~$15K potential | E10: 🟠 MEDIUM | F10: Better load matching
A11: Detention → Delays | B11: r = 0.54 | C11: 0.286 | D11: Indirect savings | E11: 🟡 LOW | F11: Scheduling optimization
A13: STRATEGY 1: REDUCE VARIABLE COST PER MILE (r = 0.73)
A15: Metric | B15: Current Value | C15: Target (10% Cut) | D15: CPM Impact
A16: Avg Variable CPM | B16: =AVERAGE(fact_orders_1000[variable_cost_per_mile]) -> 1.5552077 | C16: =B16*0.9 -> 1.3996869
A17: Avg Total CPM | B17: =AVERAGE(fact_orders_1000[cost_per_mile]) -> 2.25372 | C17: =1.073+0.759*C16 -> 2.1353624 | D17: =B17-C17 -> 0.11835762
A18: Regression Equation | B18: CPM = 1.073 + 0.759 × VCPM
A20: ACTION: Negotiate fuel contracts, implement fuel-efficient driving, optimize routes
A22: STRATEGY 2: FUEL COST OPTIMIZATION (r = 0.98)
A24: Metric | B24: Current | C24: 5% Reduction | D24: Savings
A25: Total Fuel Cost | B25: =SUM(fact_orders_1000[fuel_cost_total]) -> 258543.21 | C25: =B25*0.95 -> 245616.05 | D25: =B25-C25 -> 12927.16
A26: Total Miles | B26: =SUM(fact_orders_1000[total_miles]) -> 333652 | C26: =B26*0.95 -> 316969.4 | D26: =B26-C26 -> 16682.6
A27: Fuel Cost Per Mile | B27: =B25/B26 -> 0.77488884
A28: Regression Equation | B28: Fuel = -$3.15 + $0.784 × Miles
A30: ACTION: Each mile saved = $0.78 fuel savings. Focus on route optimization.
A32: STRATEGY 3: TRUCK TYPE CPM OPTIMIZATION
A34: Truck Type | B34: Avg CPM | C34: Count | D34: vs Average | E34: Recommendation
A35: Overall Average | B35: =AVERAGE(fact_orders_1000[cost_per_mile]) -> 2.25372 | C35: =COUNTA(fact_orders_1000[cost_per_mile]) -> 1000 | D35: Baseline | E35: -
A36: Intermodal | B36: =AVERAGEIF(fact_orders_1000[truck_types],"Intermodal",fact_orders_1000[cost_per_mile]) -> 2.0889 | C36: =COUNTIF(fact_orders_1000[truck_types],"Intermodal") -> 100 | D36: =B36-$B$35 -> -0.16482 | E36: ✅ LOWEST - Expand use
A37: Dry Van | B37: =AVERAGEIF(fact_orders_1000[truck_types],"Dry Van",fact_orders_1000[cost_per_mile]) -> 2.1807172 | C37: =COUNTIF(fact_orders_1000[truck_types],"Dry Van") -> 488 | D37: =B37-$B$35 -> -0.073002787 | E37: ✅ Below avg
A38: Flatbed | B38: =AVERAGEIF(fact_orders_1000[truck_types],"Flatbed",fact_orders_1000[cost_per_mile]) -> 2.3125197 | C38: =COUNTIF(fact_orders_1000[truck_types],"Flatbed") -> 127 | D38: =B38-$B$35 -> 0.058799685 | E38: ⚠️ Above avg - Review
A39: Reefer | B39: =AVERAGEIF(fact_orders_1000[truck_types],"Reefer",fact_orders_1000[cost_per_mile]) -> 2.3758723 | C39: =COUNTIF(fact_orders_1000[truck_types],"Reefer") -> 235 | D39: =B39-$B$35 -> 0.12215234 | E39: ⚠️ Higher - Optimize
A40: Tanker | B40: =AVERAGEIF(fact_orders_1000[truck_types],"Tanker",fact_orders_1000[cost_per_mile]) -> 2.5724 | C40: =COUNTIF(fact_orders_1000[truck_types],"Tanker") -> 50 | D40: =B40-$B$35 -> 0.31868 | E40: 🔴 HIGHEST - Review pricing
A42: STRATEGY 4: MAINTENANCE COST REDUCTION (r = 0.81)
A44: Metric | B44: Value
A45: Total Maintenance Cost | B45: =SUM(fact_orders_1000[maintenance_cost_total]) -> 57716.2
A46: Avg Maint (No Mechanical) | B46: =AVERAGEIF(fact_orders_1000[mechanical_flag],0,fact_orders_1000[maintenance_cost_total]) -> 53.616814
A47: Avg Maint (WITH Mechanical) | B47: =AVERAGEIF(fact_orders_1000[mechanical_flag],1,fact_orders_1000[maintenance_cost_total]) -> 873.494
A48: Cost Increase per Issue | B48: =B47-B46 -> 819.87719
A49: Mechanical Issue Count | B49: =COUNTIF(fact_orders_1000[mechanical_flag],1) -> 5
A50: Total Excess Mechanical Cost | B50: =B48*B49 -> 4099.3859
A52: ACTION: Preventive maintenance has 3:1 ROI vs reactive repairs.
A54: STRATEGY 5: DEADHEAD MILE REDUCTION (5.76%)
A56: Metric | B56: Current | C56: 50% Reduction | D56: Savings
A57: Total Deadhead Miles | B57: =SUM(fact_orders_1000[deadhead_miles]) -> 19208.6 | C57: =B57*0.5 -> 9604.3 | D57: =B57-C57 -> 9604.3
A58: Deadhead Cost (@$0.78/mi) | B58: =B57*0.78 -> 14982.708 | C58: =C57*0.78 -> 7491.354 | D58: =B58-C58 -> 7491.354
A59: Deadhead % of Total | B59: =SUM(fact_orders_1000[deadhead_miles])/SUM(fact_orders_1000[total_miles]) -> 0.057570762
A61: ACTION: Improve load matching, negotiate backhaul agreements.
A63: TOTAL POTENTIAL SAVINGS CALCULATOR
A65: Strategy | B65: Conservative (5%) | C65: Moderate (10%) | D65: Aggressive (15%)
A66: 1. Fuel Optimization | B66: =SUM(fact_orders_1000[fuel_cost_total])*0.05 -> 12927.16 | C66: =SUM(fact_orders_1000[fuel_cost_total])*0.1 -> 25854.321 | D66: =SUM(fact_orders_1000[fuel_cost_total])*0.15 -> 38781.481
A67: 2. Route Optimization | B67: =SUM(fact_orders_1000[total_miles])*0.05*0.78 -> 13012.428 | C67: =SUM(fact_orders_1000[total_miles])*0.1*0.78 -> 26024.856 | D67: =SUM(fact_orders_1000[total_miles])*0.15*0.78 -> 39037.284
A68: 3. Preventive Maintenance | B68: =B50*0.25 -> 1024.8465 | C68: =B50*0.5 -> 2049.693 | D68: =B50*0.75 -> 3074.5394
A69: 4. Deadhead Reduction | B69: =B58*0.25 -> 3745.677 | C69: =B58*0.5 -> 7491.354 | D69: =B58*0.75 -> 11237.031
A71: TOTAL POTENTIAL SAVINGS | B71: =SUM(B66:B69) -> 30710.112 | C71: =SUM(C66:C69) -> 61420.224 | D71: =SUM(D66:D69) -> 92130.336
A72: Total Operating Cost (Base) | B72: =SUM(fact_orders_1000[fuel_cost_total])+SUM(fact_orders_1000[maintenance_cost_total])+SUM(fact_orders_1000[driver_pay_total]) -> 517454.46
A73: % Savings of Operating Cost | B73: =B71/B72 -> 0.059348434 | C73: =C71/B72 -> 0.11869687 | D73: =D71/B72 -> 0.1780453
A74: Running Total | B74: =SUM($B$66:B73) -> 578874.74 | C74: =SUM($B$66:C73) -> 701715.31 | D74: =SUM($B$66:D73) -> 885976.16

Sheet Capstone_Methodology
A1: CAPSTONE PROJECT METHODOLOGY DOCUMENTATION
A2: Logistics & Fleet Operations Cost Optimization Analysis
A4: 1. PROJECT IDEA & BUSINESS PROBLEM
A6: 1.1 How the Idea Originated:
A7: • Business Challenge: Fleet operations face significant cost pressures from fuel, maintenance, and inefficiencies
A8: • Key Question: What operational factors most strongly predict and drive costs (CPM)?
A9: • Opportunity: Use regression analysis to identify actionable cost reduction levers
A10: • Goal: Quantify relationships between operational variables to enable data-driven decisions
A12: 1.2 Research Questions:
A13: Q1: Which variables have strong correlation (>0.7) with Cost Per Mile?
A14: Q2: What causes severe delays (>300 min) and how do they impact costs?
A15: Q3: How can regression equations predict and reduce operational costs?
... A18: 2. DATA SOURCES & COLLECTION
A20: Data Source | B20: Description | C20: Records | D20: Key Fields
A21: fact_orders_1000 | B21: Transactional shipment data | C21: 1,000 orders | D21: 53 variables
A22: dim_fleet_260 | B22: Fleet/truck master data | C22: 260 trucks | D22: 21 variables
A24: 2.1 Key Data Fields Used:
A25: Category | B25: Variables | C25: Data Type | D25: Purpose
A26: Cost Metrics | B26: cost_per_mile, variable_cost_per_mile, fuel_cost_total, maintenance_cost_total | C26: Numeric (USD) | D26: Dependent/Independent vars
A27: Distance Metrics | B27: distance_miles, total_miles, loaded_miles, deadhead_miles | C27: Numeric (miles) | D27: Operational efficiency
A28: Performance | B28: delay_minutes, detention_minutes, on_time_flag, late_flag | C28: Numeric/Boolean | D28: Service quality
A29: Risk Factors | B29: weather_severity_index, traffic_index, mechanical_flag | C29: Numeric/Boolean | D29: External/internal factors
A30: Dimensions | B30: carrier_name, truck_types, region, lanes_usa | C30: Categorical | D30: Segmentation
A32: 3. DATA CLEANING & TRANSFORMATION
A34: 3.1 Data Quality Checks Performed:
A35: Step | B35: Method/Formula | C35: Issue Found | D35: Resolution
A36: Missing Values | B36: COUNTBLANK formula | C36: Minimal missing data | D36: Used IFERROR
A37: Outlier Detection | B37: IF statement >300 | C37: 12 severe delays found | D37: Analyzed separately
A38: Data Type Validation | B38: ISNUMBER formula | C38: All numeric validated | D38: No conversion needed
A39: Duplicate Check | B39: COUNTIF formula | C39: No duplicates found | D39: Data integrity OK
A41: 3.2 Calculated Fields Created:
A42: Field Name | B42: Formula/Logic | C42: Purpose | D42: Sheet Location
A43: On-Time Flag | B43: IF delay<=0 then 1 else 0 | C43: Binary classification | D43: fact_orders_1000!AS
A44: Late Flag | B44: IF delay>0 then 1 else 0 | C44: Binary classification | D44: fact_orders_1000!AT
A45: Severe Delay Flag | B45: IF delay>300 then 1 else 0 | C45: Identify extreme delays | D45: SevereDelayAnalysis
A46: Deadhead Percentage | B46: deadhead_miles/total_miles | C46: Efficiency metric | D46: OpCostAnalysis
A47: Total Operating Cost | B47: fuel + maint + driver_pay | C47: Aggregate cost | D47: OpCostAnalysis
A49: 4. ANALYTICAL METHODOLOGY
A51: 4.1 Statistical Techniques Applied:
A52: Technique | B52: Excel Formula | C52: Purpose | D52: Key Finding
A53: Pearson Correlation | B53: CORREL(array1,array2) | C53: Measure linear relationships | D53: Var CPM vs CPM: r=0.73
A54: Linear Regression | B54: SLOPE, INTERCEPT, RSQ | C54: Predict dependent variable | D54: CPM = 1.07 + 0.76*VCPM
A55: Descriptive Stats | B55: AVERAGE, MEDIAN, STDEV | C55: Summarize distributions | D55: Avg CPM = $2.25
A56: COUNTIFS Analysis | B56: COUNTIFS(crit1,crit2) | C56: Conditional counting | D56: 12 severe delays found
A57: AVERAGEIF Analysis | B57: AVERAGEIF(range,crit,avg) | C57: Conditional averaging | D57: Severe avg = 456 min
A59: 4.2 Correlation Classification:
A60: Correlation Range | B60: Classification | C60: Interpretation | D60: Business Action
A61: |r| > 0.7 | B61: Strong | C61: Variable is a key driver | D61: Prioritize for optimization
A62: |r| = 0.3-0.7 | B62: Moderate | C62: Variable has influence | D62: Monitor and manage
A63: |r| < 0.3 | B63: Weak | C63: Minimal relationship | D63: Low priority
A65: 4.3 Regression Analysis Framework:
A66: Component | B66: Formula | C66: Interpretation | D66: Example
A67: Slope (b) | B67: SLOPE(known_ys,known_xs) | C67: Unit change impact | D67: b=0.76: +$1 VCPM adds $0.76
A68: Intercept (a) | B68: INTERCEPT(ys,xs) | C68: Base value when X=0 | D68: a=1.07: Base CPM
A69: R-Squared | B69: RSQ(known_ys,known_xs) | C69: % variance explained | D69: 53% = Strong model
A70: Prediction | B70: {=a + b * X} -> #NAME? | C70: Forecast Y from X | D70: 1.07+0.76*1.56=$2.25
A72: 5. KEY INSIGHTS & FINDINGS
A74: 5.1 Strong Correlations Discovered (>0.7):
A75: Relationship | B75: Correlation | C75: R-Squared | D75: Business Implication
A76: Variable CPM to Cost Per Mile | B76: r = 0.73 | C76: 0.533 | D76: Primary cost driver
A77: Total Miles to Fuel Cost | B77: r = 0.98 | C77: 0.958 | D77: Route optimization key
A78: Total Miles to Driver Pay | B78: r = 0.98 | C78: 0.957 | D78: Efficient routing saves
A79: Mechanical Flag to Maint Cost | B79: r = 0.81 | C79: 0.659 | D79: Preventive maint ROI
A81: 5.2 Delay Analysis Insights:
A82: Metric | B82: Value | C82: % of Total | D82: Insight
A83: Total Shipments | B83: 1000 | C83: 1 | D83: Analysis population
A84: On-Time Deliveries | B84: 703 | C84: 0.703 | D84: Baseline performance
A85: Late Deliveries | B85: 297 | C85: 0.297 | D85: Improvement opportunity
A86: Severe Delays (>300 min) | B86: 12 | C86: 0.012 | D86: High-impact outliers
A87: Avg Severe Delay | B87: 456 min | C87: N/A | D87: ~7.6 hours average
A89: 5.3 Cost Optimization Opportunities:
A90: Strategy | B90: Potential Savings | C90: Implementation | D90: ROI Timeline
A91: Fuel Optimization | B91: $12,927-$38,781 | C91: Route optimization | D91: 3-6 months
A92: Deadhead Reduction | B92: $7,491-$11,237 | C92: Load matching | D92: 6-12 months
A93: Preventive Maintenance | B93: $1,025-$3,075 | C93: Scheduled programs | D93: Immediate
A94: TOTAL SAVINGS | B94: $30,710-$92,130 | C94: 5.9%-17.8% of OpCost | D94: Annual
A96: 6. METHODOLOGY APPLICABILITY TO OTHER BUSINESSES
A98: 6.1 Universal Framework:
A99: This methodology can be applied to ANY industry with the following adaptations:
A101: Step | B101: Logistics Example | C101: Retail Example | D101: Healthcare Example
A102: 1. Identify KPI | B102: Cost Per Mile (CPM) | C102: Cost Per Transaction | D102: Cost Per Patient Visit
A103: 2. Collect Variables | B103: Fuel, maint, labor, miles | C103: Labor, inventory, marketing | D103: Staff, supplies, equipment
A104: 3. Calculate Correlations | B104: CORREL(CPM, variable) | C104: CORREL(CPT, variable) | D104: CORREL(CPV, variable)
A105: 4. Find Strong (>0.7) | B105: Variable CPM (r=0.73) | C105: Inventory turns (r=?) | D105: Staff ratio (r=?)
A106: 5. Build Regression | B106: CPM = a + b*VCPM | C106: CPT = a + b*InvTurns | D106: CPV = a + b*StaffRatio
A107: 6. Quantify Savings | B107: $30K-$92K annual | C107: $X annual | D107: $Y annual
A109: 6.2 Key Excel Formulas (Copy & Adapt):
A110: Purpose | B110: Formula Template | C110: How to Adapt
A111: Correlation | B111: CORREL(A:A, B:B) | C111: Replace A,B with your KPI and variable
A112: R-Squared | B112: RSQ(A:A, B:B) | C112: Measures percent variance explained
A113: Regression Slope | B113: SLOPE(KPI_col, Var_col) | C113: Shows unit impact on KPI
A114: Regression Intercept | B114: INTERCEPT(KPI_col, Var_col) | C114: Base value when variable equals 0
A115: Prediction | B115: Intercept + Slope * X_value | C115: Forecast KPI from variable value
A116: Conditional Average | B116: AVERAGEIF(Cat,Val,KPI) | C116: Segment analysis
A117: Conditional Count | B117: COUNTIFS(Col1,criteria) | C117: Flag outliers and segments
A119: 6.3 Replication Checklist:
A120: Step 1: Define your primary KPI (cost metric)
A121: Step 2: Identify 10-15 potential driver variables
A122: Step 3: Clean data - remove blanks, fix outliers
A123: Step 4: Calculate correlation for each variable vs KPI
...

Sheet RawDataSample
A1: BEFORE & AFTER DATA CLEANING DEMONSTRATION - For ScribeHow Recording
A3: SECTION 1: SIMULATED 'DIRTY' DATA (Before Cleaning)
A5: Row # | B5: carrier_name (DIRTY) | C5: origin_city (DIRTY) | D5: origin_state (DIRTY) | E5: delay_minutes (DIRTY) | F5: truck_type (DIRTY) | G5: Issues Present
A6: 1 | B6: blue ridge logistics | C6: TOLEDO | D6: oh | F6: DRY VAN | G6: Extra spaces, inconsistent case, missing value
A7: 2 | B7: SUNBELT HAULAGE | C7: Miami | D7: FL | E7: 27 | F7: reefer | G7: All caps, extra spaces, lowercase type
A8: 3 | B8: pacific linehaul | C8: Denver | D8: co | E8: -15 | F8: FLATBED | G8: Lowercase name, lowercase state
A9: 4 | B9: Cascade Cargo | C9: CHICAGO | D9: IL | E9: abc | F9: Intermodal | G9: Leading space, non-numeric delay
A10: 5 | B10: KEYSTONE FREIGHT | C10: boston | D10: ma | E10: 42 | F10: Tanker | G10: Trailing space, inconsistent case
A11: 6 | B11: great lakes carriers | C11: PHOENIX | D11: az | F11: dry van | G11: Lowercase, missing delay
A12: 7 | B12: MIDWEST EXPRESS TRUCKING | C12: seattle | D12: WA | E12: -8 | F12: REEFER | G12: Extra spaces both sides
A13: 8 | B13: Desert Road Haulers | C13: LOS ANGELES | D13: ca | E13: 15 | F13: flatbed | G13: City has spaces, lowercase
A14: 9 | B14: LONE STAR TRANSPORT | C14: houston | D14: TX | E14: N/A | F14: Dry Van | G14: N/A instead of number
A15: 10 | B15: atlantic freightways | C15: New York | D15: ny | E15: 0 | F15: intermodal | G15: All lowercase, extra spaces
A18: SECTION 2: CLEANING FORMULAS (How to Clean)
A20: Issue Type | B20: Dirty Example | C20: Cleaning Formula | D20: Clean Result | E20: Excel Formula to Use | F20: LIVE Demo (Actual Result)
A21: Extra Spaces | B21: blue ridge logistics | C21: =TRIM(B21) -> blue ridge logistics | D21: =TRIM(B21) -> blue ridge logistics | E21: =TRIM(B6) | F21: =TRIM(B6) -> blue ridge logistics
A22: Proper Case | B22: TOLEDO | C22: =PROPER(B22) -> Toledo | D22: =PROPER(B22) -> Toledo | E22: =PROPER(C6) | F22: =PROPER(C6) -> Toledo
A23: Uppercase State | B23: oh | C23: =UPPER(B23) -> OH | D23: =UPPER(B23) -> OH | E23: =UPPER(D6) | F23: =UPPER(D6) -> OH
A24: Combined Clean | B24: BLUE RIDGE LOGISTICS | C24: =PROPER(TRIM(B24)) -> Blue Ridge Logistics | D24: =PROPER(TRIM(B24)) -> Blue Ridge Logistics | E24: =PROPER(TRIM(B6)) | F24: =PROPER(TRIM(B6)) -> Blue Ridge Logistics
A25: Missing Number | C25: =IFERROR(VALUE(B25),0) -> 0 | D25: =IFERROR(VALUE(B25),0) -> 0 | E25: =IF(E6="",0,E6) | F25: =IF(E6="",0,E6) -> 0
A26: Non-Numeric | B26: abc | C26: =IFERROR(VALUE(B26),0) -> 0 | D26: =IFERROR(VALUE(B26),0) -> 0 | E26: =IFERROR(VALUE(E9),0) | F26: =IFERROR(VALUE(E9),0) -> 0
A27: N/A Value | B27: N/A | C27: =IF(B27="N/A",0,B27) -> 0 | D27: =IF(B27="N/A",0,B27) -> 0 | E27: =IF(E14="N/A",0,E14) | F27: =IF(E14="N/A",0,E14) -> 0
A28: Clean Text+Trim | B28: Cascade Cargo | C28: =CLEAN(TRIM(B28)) -> Cascade Cargo | D28: =CLEAN(TRIM(B28)) -> Cascade Cargo | E28: =TRIM(CLEAN(B9)) | F28: =TRIM(CLEAN(B9)) -> Cascade Cargo
A29: Remove Duplicates | B29: (Use Data Tab) | C29: Data > Remove Duplicates | D29: N/A | E29: Menu: Data > Remove Duplicates
A30: Find Blanks | B30: (Use Find & Select) | C30: Home > Find > Go To Special > Blanks | D30: N/A | E30: Ctrl+G > Special > Blanks
A31: ADDITIONAL USEFUL CLEANING FORMULAS:
A32: Function | B32: Purpose | C32: Example Input | D32: Formula Syntax | E32: Output | F32: Use Case
A33: SUBSTITUTE() | B33: Replace specific text | C33: New York City | D33: =SUBSTITUTE(C33," ","") | E33: =SUBSTITUTE(C33," ","") -> NewYorkCity | F33: Remove all spaces
A34: 📋 KEY FORMULAS FOR SCRIBEHOW DEMO:
A35: Row # | B35: carrier_name (CLEAN) | C35: origin_city (CLEAN) | D35: origin_state (CLEAN) | E35: delay_minutes (CLEAN) | F35: truck_type (CLEAN) | G35: Cleaning Applied
A36: 1 | B36: =PROPER(TRIM(B6)) -> Blue Ridge Logistics | C36: =PROPER(TRIM(C6)) -> Toledo | D36: =UPPER(TRIM(D6)) -> OH | E36: =IFERROR(VALUE(E6),0) -> 0 | F36: =PROPER(TRIM(F6)) -> Dry Van | G36: PROPER(TRIM()), IFERROR() for blank
A37: 2 | B37: =PROPER(TRIM(B7)) -> Sunbelt Haulage | C37: =PROPER(TRIM(C7)) -> Miami | D37: =UPPER(TRIM(D7)) -> FL | E37: =IFERROR(VALUE(E7),E7) -> 27 | F37: =PROPER(TRIM(F7)) -> Reefer | G37: PROPER(TRIM())
A38: 3 | B38: =PROPER(TRIM(B8)) -> Pacific Linehaul | C38: =PROPER(TRIM(C8)) -> Denver | D38: =UPPER(TRIM(D8)) -> CO | E38: =IFERROR(VALUE(E8),E8) -> -15 | F38: =PROPER(TRIM(F8)) -> Flatbed | G38: PROPER(), UPPER()
A39: 4 | B39: =PROPER(TRIM(B9)) -> Cascade Cargo | C39: =PROPER(TRIM(C9)) -> Chicago | D39: =UPPER(TRIM(D9)) -> IL | E39: =IFERROR(VALUE(E9),0) -> 0 | F39: =PROPER(TRIM(F9)) -> Intermodal | G39: TRIM(), IFERROR() for non-numeric
A40: 5 | B40: =PROPER(TRIM(B10)) -> Keystone Freight | C40: =PROPER(TRIM(C10)) -> Boston | D40: =UPPER(TRIM(D10)) -> MA | E40: =IFERROR(VALUE(E10),E10) -> 42 | F40: =PROPER(TRIM(F10)) -> Tanker | G40: PROPER(TRIM())
A41: 6 | B41: =PROPER(TRIM(B11)) -> Great Lakes Carriers | C41: =PROPER(TRIM(C11)) -> Phoenix | D41: =UPPER(TRIM(D11)) -> AZ | E41: =IFERROR(VALUE(E11),0) -> 0 | F41: =PROPER(TRIM(F11)) -> Dry Van | G41: PROPER(TRIM()), IFERROR() for blank
A42: 7 | B42: =PROPER(TRIM(B12)) -> Midwest Express Trucking | C42: =PROPER(TRIM(C12)) -> Seattle | D42: =UPPER(TRIM(D12)) -> WA | E42: =IFERROR(VALUE(E12),E12) -> -8 | F42: =PROPER(TRIM(F12)) -> Reefer | G42: PROPER(TRIM())
A43: 8 | B43: =PROPER(TRIM(B13)) -> Desert Road Haulers | C43: =PROPER(TRIM(C13)) -> Los Angeles | D43: =UPPER(TRIM(D13)) -> CA | E43: =IFERROR(VALUE(E13),E13) -> 15 | F43: =PROPER(TRIM(F13)) -> Flatbed | G43: PROPER(TRIM()), UPPER()
A44: 9 | B44: =PROPER(TRIM(B14)) -> Lone Star Transport | C44: =PROPER(TRIM(C14)) -> Houston | D44: =UPPER(TRIM(D14)) -> TX | E44: =IF(E14="N/A",0,IFERROR(VALUE(E14),0)) -> 0 | F44: =PROPER(TRIM(F14)) -> Dry Van | G44: IF() for N/A replacement
A45: 10 | B45: =PROPER(TRIM(B15)) -> Atlantic Freightways | C45: =PROPER(TRIM(C15)) -> New York | D45: =UPPER(TRIM(D15)) -> NY | E45: =IFERROR(VALUE(E15),E15) -> 0 | F45: =PROPER(TRIM(F15)) -> Intermodal | G45: PROPER(TRIM()), UPPER()
A48: SECTION 4: COMPREHENSIVE FORMULA EXAMPLES (Copy & Modify)
A50: Category | B50: Function | C50: Example Formula | D50: Description | E50: Input Example | F50: Output | G50: When to Use
A51: Text Cleaning | B51: TRIM | C51: =TRIM(A1) | D51: Removes extra spaces | E51: hello world | F51: hello world | G51: Leading/trailing spaces
A52: Text Cleaning | B52: CLEAN | C52: =CLEAN(A1) | D52: Removes non-printable | E52: data here | F52: datahere | G52: Imported data
A53: Text Cleaning | B53: PROPER | C53: =PROPER(A1) | D53: Title Case | E53: JOHN SMITH | F53: John Smith | G53: Names, cities
A54: Text Cleaning | B54: UPPER | C54: =UPPER(A1) | D54: UPPERCASE | E54: hello | F54: HELLO | G54: State codes
A55: Text Cleaning | B55: LOWER | C55: =LOWER(A1) | D55: lowercase | E55: HELLO | F55: hello | G55: Email addresses
A56: Text Cleaning | B56: SUBSTITUTE | C56: =SUBSTITUTE(A1," ","") | D56: Replace text | E56: New York | F56: NewYork | G56: Remove specific chars
A57: Missing Data | B57: IF (blank) | C57: =IF(A1="",0,A1) | D57: Replace blanks with 0 | E57: (blank) | F57: 0 | G57: Numeric fields
A58: Missing Data | B58: IFERROR | C58: =IFERROR(VALUE(A1),0) | D58: Handle errors | E58: abc | F58: 0 | G58: Non-numeric values
A59: Missing Data | B59: IF (N/A) | C59: =IF(A1="N/A","",A1) | D59: Replace N/A | E59: N/A | F59: (blank) | G59: Survey data
A60: Missing Data | B60: COALESCE | C60: =IF(ISBLANK(A1),B1,A1) | D60: Use fallback value | E60: (blank) | F60: Fallback | G60: Multiple sources
A61: Combined | B61: TRIM+PROPER | C61: =PROPER(TRIM(A1)) | D61: Clean + format | E61: JOHN DOE | F61: John Doe | G61: Names
A62: Combined | B62: TRIM+UPPER | C62: =UPPER(TRIM(A1)) | D62: Clean + uppercase | E62: ca | F62: CA | G62: State codes
A63: Combined | B63: CLEAN+TRIM | C63: =TRIM(CLEAN(A1)) | D63: Remove all junk | E63: bad data | F63: bad data | G63: Imported text
A64: Validation | B64: ISNUMBER | C64: =ISNUMBER(A1) | D64: Check if numeric | E64: 123 | F64: TRUE | G64: Data validation
A65: Validation | B65: ISTEXT | C65: =ISTEXT(A1) | D65: Check if text | E65: hello | F65: TRUE | G65: Type checking
A66: Validation | B66: ISBLANK | C66: =ISBLANK(A1) | D66: Check if empty | E66: (blank) | F66: TRUE | G66: Find missing
A67: Validation | B67: LEN | C67: =LEN(TRIM(A1)) | D67: Count characters | E67: hello | F67: 5 | G67: Field length
A68: Analysis | B68: COUNTBLANK | C68: =COUNTBLANK(A1:A100) | D68: Count empty cells | E68: (range) | F68: 5 | G68: Missing data count
A69: Analysis | B69: COUNTIF | C69: =COUNTIF(A1:A100,">300") | D69: Count with criteria | E69: (range) | F69: 12 | G69: Threshold counting
A70: Analysis | B70: SUMIF | C70: =SUMIF(A:A,"X",B:B) | D70: Sum with criteria | E70: (range) | F70: 1000 | G70: Category totals
A71: Analysis | B71: AVERAGEIF | C71: =AVERAGEIF(A:A,">0",B:B) | D71: Avg with criteria | E71: (range) | F71: 45.5 | G71: Segment averages
A76: Severe Delays (>300) | B76: =COUNTIF(fact_orders_1000[delay_minutes],">300") -> 12 | D76: {=COUNTIF(range,">300")} -> #NAME?
A77: On-Time Shipments | B77: =COUNTIF(fact_orders_1000[on_time_flag],1) -> 829 | D77: {=COUNTIF(on_time_flag,1)} -> #NAME?
A78: Late Shipments | B78: =COUNTIF(fact_orders_1000[late_flag],1) -> 171 | D78: {=COUNTIF(late_flag,1)} -> #NAME?
A79: Avg Delay Minutes | B79: =AVERAGE(fact_orders_1000[delay_minutes]) -> 6.461 | D79: =AVERAGE(delay_minutes) -> #NAME?
A82: SECTION 6: KEY TRANSFORMATION FORMULAS USED IN THIS PROJECT
A84: Formula Type | B84: Purpose | C84: Example Formula | D84: Sheet Used In | E84: Result
A85: CORREL | B85: Find correlations | C85: =CORREL(fact_orders_1000[cost_per_mile],fact_orders_1000[variable_cost_per_mile]) -> 0.72995772 | D85: RegressionAnalysis | E85: 0.73
A86: SLOPE | B86: Regression coefficient | C86: =SLOPE(fact_orders_1000[cost_per_mile],fact_orders_1000[variable_cost_per_mile]) -> 0.7591332 | D86: RegressionAnalysis | E86: 0.759
A87: INTERCEPT | B87: Regression constant | C87: =INTERCEPT(fact_orders_1000[cost_per_mile],fact_orders_1000[variable_cost_per_mile]) -> 1.0727742 | D87: RegressionAnalysis | E87: 1.073
A88: RSQ | B88: R-squared value | C88: =RSQ(fact_orders_1000[cost_per_mile],fact_orders_1000[variable_cost_per_mile]) -> 0.53283827 | D88: RegressionAnalysis | E88: 0.533
A89: COUNTIFS | B89: Count with criteria | C89: =COUNTIFS(fact_orders_1000[delay_minutes],">300") -> 12 | D89: SevereDelayAnalysis | E89: 12
A90: SUMIFS | B90: Sum with criteria | C90: =SUMIFS(fact_orders_1000[fuel_cost_total],fact_orders_1000[truck_types],"Reefer") -> 64949.94 | D90: OpCostAnalysis | E90: 64950
A91: AVERAGEIFS | B91: Average with criteria | C91: =AVERAGEIFS(fact_orders_1000[cost_per_mile],fact_orders_1000[truck_types],"Reefer") -> 2.3758723 | D91: OpCostAnalysis | E91: 2.38
A92: IF | B92: Conditional logic | C92: =IF(1<=0,1,0) -> 0 | D92: fact_orders_1000 | E92: 0 (FALSE)
A93: IFERROR | B93: Handle errors | C93: {=IFERROR(formula,0)} -> 0 | D93: Multiple sheets | E93: 0 if error
A94: XLOOKUP | B94: Lookup values | C94: =_xlfn.XLOOKUP(770487,dim_fleet_260[truck_id],dim_fleet_260[carrier_name]) -> Desert Road Haulers | D94: Data joins | E94: Desert Road Haulers
A95: MEDIAN | B95: Middle value | C95: =MEDIAN(fact_orders_1000[delay_minutes]) -> -14 | D95: Insights | E95: -14 min
A98: SECTION 7: PROJECT SHEETS NAVIGATION (For ScribeHow Demo)
A100: Sheet Name | B100: Purpose | C100: Key Content | D100: Demo Focus | E100: Business Question
A101: fact_orders_1000 | B101: Raw transactional data | C101: 1,000 shipment orders | D101: Show source data | E101: What does data look like?
A102: dim_fleet_260 | B102: Fleet master data | C102: 260 truck records | D102: Show dimension table | E102: What trucks do we have?
A103: RawDataSample | B103: Cleaning demonstration | C103: Before/After examples | D103: RECORD THIS FIRST | E103: How was data cleaned?
A104: Insights | B104: Key metrics summary | C104: On-time %, averages | D104: Show summary stats | E104: Overall performance?
A105: SevereDelayAnalysis | B105: Outlier deep dive | C105: Severe delays by carrier | D105: Show drill-down | E105: What causes severe delays?
A106: RegressionAnalysis | B106: Correlation analysis | C106: Correlation matrix | D106: Show regression | E106: What predicts delays?
A107: RPM_Correlation | B107: Cost per mile drivers | C107: Strong correlations >0.7 | D107: Show key finding | E107: What drives CPM?
A108: OpCostAnalysis | B108: Operational costs | C108: Fuel, maint, driver pay | D108: Show cost breakdown | E108: Where does money go?
A109: CostStrategy | B109: Recommendations | C109: Savings calculator | D109: Show business value | E109: How to reduce costs?
A110: Capstone_Methodology | B110: Documentation | C110: Full methodology | D110: Reference for write-up | E110: How was analysis done?

Sheet DataCleaningLog
A1: DATA CLEANING & TRANSFORMATION DOCUMENTATION
A2: For ScribeHow Recording - Capstone Project
A4: PHASE 1: DATA CLEANING
A6: 1.1 ORIGINAL DATA ASSESSMENT
A7: Metric | B7: fact_orders_1000 | C7: dim_fleet_260 | D7: Formula | E7: ScribeHow Action
A8: Total Records | B8: =COUNTA(fact_orders_1000!A:A)-1 -> 1000 | C8: =COUNTA(dim_fleet_260!A:A)-1 -> 260 | D8: COUNTA()-1 | E8: Count rows before cleaning
A9: Total Columns | B9: 53 | C9: 21 | D9: Manual | E9: Document column count
A10: Blank Cells Check | B10: =COUNTBLANK(fact_orders_1000!A2:BA1002) -> 935 | C10: =COUNTBLANK(dim_fleet_260!A2:U261) -> 0 | D10: COUNTBLANK() | E10: Identify missing data
A12: 1.2 DATA QUALITY CHECKS
A13: Check Type | B13: Formula Example | C13: Applied To | D13: Result | E13: ScribeHow Steps
A14: Missing Values | B14: {=COUNTBLANK(range)} -> #NAME? | C14: All columns | D14: See above | E14: Find & Select > Blanks
A15: Duplicate Check | B15: {=SUMPRODUCT((COUNTIF(A:A,A2:A1002)>1)*1)} -> 16 | C15: order_id | D15: 0 duplicates | E15: Data > Remove Duplicates
A16: Numeric Validation | B16: {=SUMPRODUCT(ISNUMBER(range)*1)} -> 0 | C16: Cost columns | D16: All valid | E16: Conditional Formatting
A18: 1.3 TEXT CLEANING FUNCTIONS
A19: Function | B19: Purpose | C19: Example | D19: Applied To | E19: Demo
A20: TRIM() | B20: Remove extra spaces | C20: =TRIM(A2) -> For ScribeHow Recording - Capstone Project | D20: Text fields | E20: Show before/after
A21: PROPER() | B21: Capitalize properly | C21: =PROPER(A2) -> For Scribehow Recording - Capstone Project | D21: City names | E21: Transform demo
A22: UPPER() | B22: Uppercase | C22: =UPPER(A2) -> FOR SCRIBEHOW RECORDING - CAPSTONE PROJECT | D22: State codes | E22: Consistency check
A23: CLEAN() | B23: Remove non-printable | C23: =CLEAN(A2) -> For ScribeHow Recording - Capstone Project | D23: All text | E23: Combine with TRIM
A25: 1.4 HANDLING MISSING DATA
A26: Field | B26: Missing Count | C26: Resolution | D26: Formula | E26: Action
A27: delay_minutes | B27: =COUNTBLANK(fact_orders_1000!AE2:AE1002) -> 1 | C27: Fill with 0 | D27: =IFERROR(AE2,0) -> 0 | E27: Show wrapper
A28: Delay Reason | B28: =COUNTBLANK(fact_orders_1000!AD2:AD1002) -> 872 | C28: Intentional blank | D28: N/A | E28: Business logic
A30: PHASE 2: DATA TRANSFORMATION
A32: 2.1 CALCULATED FIELDS CREATED
A33: New Field | B33: Column | C33: Formula | D33: Purpose | E33: ScribeHow Demo
A34: on_time_flag | B34: AS | C34: {=IF(delay_minutes<=0,1,0)} -> #NAME? | D34: Binary: 1=On-time | E34: Show IF logic
A35: late_flag | B35: AT | C35: {=IF(delay_minutes>0,1,0)} -> #NAME? | D35: Binary: 1=Late | E35: Complement field
A36: on_time_count | B36: AQ | C36: {=on_time_flag} -> #NAME? | D36: For aggregation | E36: Pivot ready
A37: Late_count | B37: AR | C37: {=late_flag} -> #NAME? | D37: For aggregation | E37: Pivot ready
A38: total_shipments | B38: AN | C38: =1 -> 1 | D38: Count each row | E38: Always 1
A40: 2.2 COMPLEX FORMULAS DEMONSTRATED
A41: Formula Type | B41: Example | C41: Purpose | D41: Location | E41: ScribeHow
A42: XLOOKUP
A43: SUMIFS | B43: Conditional sum by criteria | C43: Insights sheet | D43: Multi-criteria aggregation
A44: COUNTIFS | B44: Count with conditions | C44: SevereDelayAnalysis | D44: Threshold counting
A45: AVERAGEIFS | B45: Segment averages | C45: OpCostAnalysis | D45: By category
A47: PHASE 3: VISUALIZATION
A49: 3.1 CHARTS CREATED
A50: Chart Type | B50: Data Source | C50: Purpose | D50: Sheet | E50: ScribeHow Demo
A51: Pie Chart | B51: Deadhead % by Region | C51: Distribution view | D51: Sheet8 | E51: Insert > Chart > Pie
A52: Bar Chart | B52: Delay % by Reason | C52: Compare categories | D52: %delay_by_reason | E52: Clustered bars
A53: Stacked Column | B53: Cost Savings Scenarios | C53: Multi-series | D53: CostStrategy | E53: Show potential
A55: 3.2 CONDITIONAL FORMATTING
A56: Format Type | B56: Rule | C56: Applied To | D56: Purpose | E56: ScribeHow Steps
A57: Color Scale | B57: Red-Yellow-Green | C57: delay_minutes | D57: Visual highlight | E57: Home > Cond Format
A58: Data Bars | B58: Bar = value | C58: Cost columns | D58: Quick compare | E58: Gradient Fill
A59: Highlight Cells | B59: >300 = Red | C59: Severe delays | D59: Flag outliers | E59: Greater Than rule
A61: PHASE 4: INSIGHTS & ANALYSIS
A63: 4.1 REGRESSION ANALYSIS FORMULAS
A64: Analysis | B64: Formula | C64: Result | D64: Interpretation | E64: ScribeHow Demo
A65: Correlation | B65: =CORREL(CPM,VCPM) -> #NAME? | C65: 0.73 | D65: Strong relationship | E65: RegressionAnalysis
A66: Slope | B66: =SLOPE(CPM,VCPM) -> #NAME? | C66: 0.759 | D66: +$1 VCPM = +$0.76 CPM | E66: Coefficient meaning
A67: Intercept | B67: =INTERCEPT(CPM,VCPM) -> #NAME? | C67: 1.073 | D67: Base CPM when VCPM=0 | E67: Y-intercept
A68: R-Squared | B68: =RSQ(CPM,VCPM) -> #NAME? | C68: 0.533 | D68: Model explains 53% | E68: Predictive power
A70: 4.2 KEY BUSINESS INSIGHTS
A71: Insight # | B71: Finding | C71: Supporting Data | D71: Business Impact | E71: Navigation
A72: 1 | B72: 70.3% on-time delivery | C72: =AVERAGE(on_time_flag) -> #NAME? | D72: Good baseline | E72: Insights sheet
A73: 2 | B73: Variable CPM drives total CPM | C73: r=0.73 correlation | D73: Focus on variable costs | E73: RPM_Correlation
A74: 3 | B74: Mechanical = +$820 maint cost | C74: AVERAGEIF comparison | D74: Preventive maint ROI | E74: OpCostAnalysis
A75: 4 | B75: Intermodal lowest CPM $2.09 | C75: AVERAGEIF by truck | D75: Equipment optimization | E75: CostStrategy
A76: 5 | B76: Savings potential $30K-$92K | C76: Regression projections | D76: Clear targets | E76: CostStrategy totals
A78: SCRIBEHOW RECORDING CHECKLIST
A80: Phase | B80: What to Record | C80: Key Action | D80: Duration | E80: Done?
A81: Cleaning | B81: TRIM/PROPER on text | C81: Formula bar demo | D81: 2-3 min | E81: [ ]
A82: Cleaning | B82: Remove Duplicates dialog | C82: Data tab workflow | D82: 1 min | E82: [ ]
A83: Cleaning | B83: COUNTBLANK for missing | C83: Type and show result | D83: 1 min | E83: [ ]
A84: Transform | B84: Create IF columns | C84: Add new column | D84: 2 min | E84: [ ]
A85: Transform | B85: Build Pivot Table | C85: Insert > PivotTable | D85: 3-4 min | E85: [ ]
A86: Transform | B86: XLOOKUP or IFS formula | C86: Complex formula | D86: 2 min | E86: [ ]
A87: Visualize | B87: Create Pivot Chart | C87: From PivotTable | D87: 2 min | E87: [ ]
A88: Visualize | B88: Conditional Formatting | C88: Home tab workflow | D88: 2 min | E88: [ ]
A89: Visualize | B89: Dashboard navigation | C89: Switch sheets | D89: 3 min | E89: [ ]
A90: Insights | B90: What drives cost? | C90: Show regression | D90: 2 min | E90: [ ]
A91: Insights | B91: Where to reduce cost? | C91: CostStrategy sheet | D91: 2 min | E91: [ ]
A93: SAMPLE BEFORE/AFTER COMPARISON
A95: Field | B95: BEFORE (Raw) | C95: AFTER (Cleaned) | D95: Function Applied | E95: Notes
A96: carrier_name | B96: blue ridge logistics | C96: Blue Ridge Logistics | D96: =PROPER(TRIM(A2)) -> For Scribehow Recording - Capstone Project | E96: Spaces + case
A97: origin_city | B97: TOLEDO | C97: Toledo | D97: =PROPER(A2) -> For Scribehow Recording - Capstone Project | E97: Title case
A98: origin_state | B98: oh | C98: OH | D98: =UPPER(A2) -> FOR SCRIBEHOW RECORDING - CAPSTONE PROJECT | E98: Uppercase
A99: delay_minutes | B99: (blank) | C99: 0 | D99: =IFERROR(A2,0) -> For ScribeHow Recording - Capstone Project | E99: Fill blanks
A100: cost_per_mile | B100: 2.03 | C100: 2.03 | D100: Format as Currency | E100: Display only
A101: shipping_dat | B101: 44927 | C101: 44927 | D101: Format as Date | E101: Excel serial
A103: ANALYSIS ARTIFACTS CREATED
A105: Sheet Name | B105: Purpose | C105: Key Content | D105: Formulas Used | E105: Business Question
A106: fact_orders_1000 | B106: Source data | C106: 1000 shipments, 53 columns | D106: Calculated fields | E106: Raw transactional data
A107: dim_fleet_260 | B107: Fleet master data | C107: 260 trucks, 21 attributes | D107: Reference lookups | E107: Equipment details
A108: Insights | B108: KPI Summary | C108: On-time %, delays by reason | D108: AVERAGE, COUNTIF | E108: How are we performing?
A109: SevereDelayAnalysis | B109: Outlier deep dive | C109: 12 severe delays analyzed | D109: COUNTIFS, AVERAGEIF | E109: What causes worst delays?
A110: RegressionAnalysis | B110: Delay predictors | C110: Correlation matrix | D110: CORREL, SLOPE, RSQ | E110: What predicts delays?
A111: RPM_Correlation | B111: CPM drivers | C111: Strong correlations >0.7 | D111: CORREL matrix | E111: What drives costs?
A112: OpCostAnalysis | B112: Cost metrics | C112: Fuel, maint, driver pay | D112: Regression equations | E112: Where is money going?
A113: CostStrategy | B113: Recommendations | C113: Savings calculator | D113: Projection formulas | E113: How to reduce costs?
A114: Capstone_Methodology | B114: Documentation | C114: Full methodology | D114: Process narrative | E114: How was this done?
A115: DataCleaningLog | B115: This sheet | C115: Cleaning steps | D115: All techniques | E115: ScribeHow reference

Sheet Trucking Capstone Dashboard
B2: 🚛 LOGISTICS & FLEET OPERATIONS - KEY INSIGHTS DASHBOARD
B3: Comprehensive Performance Analysis | Data: 1,000 Shipments | Fleet: 260 Trucks
C5: 📦 TOTAL SHIPMENTS | F5: ✅ ON-TIME RATE | I5: ⏱️ AVG DELAY (MIN) | L5: 🔴 SEVERE DELAYS (>300)
C6: =COUNTA(fact_orders_1000[order_id]) -> 1000 | F6: =TEXT(SUM(fact_orders_1000[on_time_count])/SUM(fact_orders_1000[total_shipments]),"0.0%") -> 82.9% | I6: =ROUND(AVERAGE(fact_orders_1000[delay_minutes]),1) -> 6.5 | L6: =COUNTIF(fact_orders_1000[delay_minutes],">300")&" ("&TEXT(COUNTIF(fact_orders_1000[delay_minutes],">300")/COUNTA(fact_orders_1000[order_id]),"0.0%")&")" -> 12 (1.2%)
B8: 📋 KEY INSIGHTS SUMMARY
B9: ="✓ Overall on-time delivery rate: "&TEXT(SUM(fact_orders_1000[on_time_count])/SUM(fact_orders_1000[total_shipments]),"0.0%")&" ("&SUM(fact_orders_1000[on_time_count])&" of "&COUNTA(fact_orders_1000[order_id])&" shipments)" -> ✓ Overall on-time delivery rate: 82.9% (829 of 1000 shipments)
B10: ="✓ Average delay is "&ROUND(AVERAGE(fact_orders_1000[delay_minutes]),0)&" min, indicating most deliveries arrive early" -> ✓ Average delay is 6 min, indicating most deliveries arrive early
B11: ="✓ Detention is the #1 cause of delays ("&TEXT(COUNTIF(fact_orders_1000[Delay Reason],"detention")/COUNTA(fact_orders_1000[order_id]),"0.0%")&" of documented delay reasons)" -> ✓ Detention is the #1 cause of delays (6.3% of documented delay reasons)
B12: ="✓ Severe delays (>300 min) represent only "&TEXT(COUNTIF(fact_orders_1000[delay_minutes],">300")/COUNTA(fact_orders_1000[order_id]),"0.0%")&" of shipments" -> ✓ Severe delays (>300 min) represent only 1.2% of shipments
B13: ✓ Compare carrier and regional performance to identify improvement areas
B14: 📈 VISUAL ANALYTICS - PERFORMANCE CHARTS
K15: 🥧 ON-TIME VS LATE
R16: Carrier | S16: On-Time % | T16: Performance | U16: Count
R17: Atlantic Freightways | S17: 0.861 | T17: On-Time | U17: =SUM(fact_orders_1000[on_time_count]) -> 829
R18: Pacific Linehaul | S18: 0.845 | T18: Late | U18: =SUM(fact_orders_1000[Late_count]) -> 171
R19: Great Lakes Carriers | S19: 0.838
R20: Desert Road Haulers | S20: 0.837
R21: Blue Ridge Logistics | S21: 0.835
R22: Keystone Freight | S22: 0.831
R23: Midwest Express Trucking | S23: 0.815
R24: Sunbelt Haulage | S24: 0.813
R25: Lone Star Transport | S25: 0.812
R26: Cascade Cargo | S26: 0.805
B38: 📋 DETAILED PERFORMANCE TABLES
B40: 📊 CARRIER PERFORMANCE | H40: 🗺️ REGIONAL PERFORMANCE | M40: 🏆 TOP & BOTTOM PERFORMERS
B41: Carrier | C41: Shipments | D41: On-Time % | E41: Avg Delay | F41: Status | H41: Region | I41: Shipments | J41: On-Time % | K41: Avg Delay | L41: Status | M41: 🏆 Best Carrier: | O41: Atlantic Freightways (86.1%)
B42: Sunbelt Haulage | C42: =SUMIFS(fact_orders_1000[total_shipments],fact_orders_1000[carrier_name],B42) -> 112 | D42: =SUMIFS(fact_orders_1000[on_time_count],fact_orders_1000[carrier_name],B42)/C42 -> 0.8125 | E42: =AVERAGEIF(fact_orders_1000[carrier_name],B42,fact_orders_1000[delay_minutes]) -> 12.1875 | F42: =IF(E42<0,"✅ Early","⚠️ OK") -> ⚠️ OK | H42: Northeast | I42: =SUMIFS(fact_orders_1000[total_shipments],fact_orders_1000[region],H42) -> 201 | J42: =SUMIFS(fact_orders_1000[on_time_count],fact_orders_1000[region],H42)/I42 -> 0.7960199 | K42: =AVERAGEIF(fact_orders_1000[region],H42,fact_orders_1000[delay_minutes]) -> 14.522388 | L42: =IF(K42<0,"✅ Early","⚠️ OK") -> ⚠️ OK | M42: 🏆 Best Region: | O42: Midwest (85.8%)
B43: Atlantic Freightways | C43: =SUMIFS(fact_orders_1000[total_shipments],fact_orders_1000[carrier_name],B43) -> 72 | D43: =SUMIFS(fact_orders_1000[on_time_count],fact_orders_1000[carrier_name],B43)/C43 -> 0.86111111 | E43: =AVERAGEIF(fact_orders_1000[carrier_name],B43,fact_orders_1000[delay_minutes]) -> 11.430556 | F43: =IF(E43<0,"✅ Early","⚠️ OK") -> ⚠️ OK | H43: West | I43: =SUMIFS(fact_orders_1000[total_shipments],fact_orders_1000[region],H43) -> 243 | J43: =SUMIFS(fact_orders_1000[on_time_count],fact_orders_1000[region],H43)/I43 -> 0.83127572 | K43: =AVERAGEIF(fact_orders_1000[region],H43,fact_orders_1000[delay_minutes]) -> 8.6213992 | L43: =IF(K43<0,"✅ Early","⚠️ OK") -> ⚠️ OK | M43: 🏆 Best Truck: | O43: Flatbed (86.6%)
B44: Pacific Linehaul | C44: =SUMIFS(fact_orders_1000[total_shipments],fact_orders_1000[carrier_name],B44) -> 103 | D44: =SUMIFS(fact_orders_1000[on_time_count],fact_orders_1000[carrier_name],B44)/C44 -> 0.84466019 | E44: =AVERAGEIF(fact_orders_1000[carrier_name],B44,fact_orders_1000[delay_minutes]) -> 10.650485 | F44: =IF(E44<0,"✅ Early","⚠️ OK") -> ⚠️ OK | H44: South | I44: =SUMIFS(fact_orders_1000[total_shipments],fact_orders_1000[region],H44) -> 309 | J44: =SUMIFS(fact_orders_1000[on_time_count],fact_orders_1000[region],H44)/I44 -> 0.82524272 | K44: =AVERAGEIF(fact_orders_1000[region],H44,fact_orders_1000[delay_minutes]) -> 6.0194175 | L44: =IF(K44<0,"✅ Early","⚠️ OK") -> ⚠️ OK | M44: ⚠️ Review Carrier: | O44: Cascade Cargo (80.5%)
B45: Blue Ridge Logistics | C45: =SUMIFS(fact_orders_1000[total_shipments],fact_orders_1000[carrier_name],B45) -> 243 | D45: =SUMIFS(fact_orders_1000[on_time_count],fact_orders_1000[carrier_name],B45)/C45 -> 0.83539095 | E45: =AVERAGEIF(fact_orders_1000[carrier_name],B45,fact_orders_1000[delay_minutes]) -> 10.242798 | F45: =IF(E45<0,"✅ Early","⚠️ OK") -> ⚠️ OK | H45: Midwest | I45: =SUMIFS(fact_orders_1000[total_shipments],fact_orders_1000[region],H45) -> 247 | J45: =SUMIFS(fact_orders_1000[on_time_count],fact_orders_1000[region],H45)/I45 -> 0.8582996 | K45: =AVERAGEIF(fact_orders_1000[region],H45,fact_orders_1000[delay_minutes]) -> -1.6720648 | L45: =IF(K45<0,"✅ Early","⚠️ OK") -> ✅ Early | M45: ⚠️ Review Region: | O45: Northeast (79.6%)
B46: Cascade Cargo | C46: =SUMIFS(fact_orders_1000[total_shipments],fact_orders_1000[carrier_name],B46) -> 77 | D46: =SUMIFS(fact_orders_1000[on_time_count],fact_orders_1000[carrier_name],B46)/C46 -> 0.80519481 | E46: =AVERAGEIF(fact_orders_1000[carrier_name],B46,fact_orders_1000[delay_minutes]) -> 5.8311688 | F46: =IF(E46<0,"✅ Early","⚠️ OK") -> ⚠️ OK
B47: Lone Star Transport | C47: =SUMIFS(fact_orders_1000[total_shipments],fact_orders_1000[carrier_name],B47) -> 101 | D47: =SUMIFS(fact_orders_1000[on_time_count],fact_orders_1000[carrier_name],B47)/C47 -> 0.81188119 | E47: =AVERAGEIF(fact_orders_1000[carrier_name],B47,fact_orders_1000[delay_minutes]) -> 4.2079208 | F47: =IF(E47<0,"✅ Early","⚠️ OK") -> ⚠️ OK | H47: ⚠️ DELAY REASONS
B48: Midwest Express Trucking | C48: =SUMIFS(fact_orders_1000[total_shipments],fact_orders_1000[carrier_name],B48) -> 92 | D48: =SUMIFS(fact_orders_1000[on_time_count],fact_orders_1000[carrier_name],B48)/C48 -> 0.81521739 | E48: =AVERAGEIF(fact_orders_1000[carrier_name],B48,fact_orders_1000[delay_minutes]) -> 4.2173913 | F48: =IF(E48<0,"✅ Early","⚠️ OK") -> ⚠️ OK | H48: Reason | I48: Count | J48: % of Total | K48: Bar
B49: Desert Road Haulers | C49: =SUMIFS(fact_orders_1000[total_shipments],fact_orders_1000[carrier_name],B49) -> 49 | D49: =SUMIFS(fact_orders_1000[on_time_count],fact_orders_1000[carrier_name],B49)/C49 -> 0.83673469 | E49: =AVERAGEIF(fact_orders_1000[carrier_name],B49,fact_orders_1000[delay_minutes]) -> -2.0816327 | F49: =IF(E49<0,"✅ Early","⚠️ OK") -> ✅ Early | H49: Detention | I49: =COUNTIF(fact_orders_1000[Delay Reason],"detention") -> 63 | J49: =I49/COUNTA(fact_orders_1000[order_id]) -> 0.063 | K49: ████
B50: Great Lakes Carriers | C50: =SUMIFS(fact_orders_1000[total_shipments],fact_orders_1000[carrier_name],B50) -> 80 | D50: =SUMIFS(fact_orders_1000[on_time_count],fact_orders_1000[carrier_name],B50)/C50 -> 0.8375 | E50: =AVERAGEIF(fact_orders_1000[carrier_name],B50,fact_orders_1000[delay_minutes]) -> -2.5625 | F50: =IF(E50<0,"✅ Early","⚠️ OK") -> ✅ Early | H50: Traffic | I50: =COUNTIF(fact_orders_1000[Delay Reason],"traffic") -> 41 | J50: =I50/COUNTA(fact_orders_1000[order_id]) -> 0.041 | K50: ███
B51: Keystone Freight | C51: =SUMIFS(fact_orders_1000[total_shipments],fact_orders_1000[carrier_name],B51) -> 71 | D51: =SUMIFS(fact_orders_1000[on_time_count],fact_orders_1000[carrier_name],B51)/C51 -> 0.83098592 | E51: =AVERAGEIF(fact_orders_1000[carrier_name],B51,fact_orders_1000[delay_minutes]) -> -3.7746479 | F51: =IF(E51<0,"✅ Early","⚠️ OK") -> ✅ Early | H51: Weather | I51: =COUNTIF(fact_orders_1000[Delay Reason],"weather") -> 20 | J51: =I51/COUNTA(fact_orders_1000[order_id]) -> 0.02 | K51: ██
H52: Mechanical | I52: =COUNTIF(fact_orders_1000[Delay Reason],"mechanical") -> 5 | J52: =I52/COUNTA(fact_orders_1000[order_id]) -> 0.005 | K52: █
B53: 🚚 TRUCK TYPE PERFORMANCE
B54: Truck Type | C54: Shipments | D54: On-Time % | E54: Avg CPM | F54: Avg Delay | H54: 💰 COST SUMMARY
B55: Dry Van | C55: =SUMIFS(fact_orders_1000[total_shipments],fact_orders_1000[truck_types],B55) -> 488 | D55: =SUMIFS(fact_orders_1000[on_time_count],fact_orders_1000[truck_types],B55)/C55 -> 0.80327869 | E55: =AVERAGEIF(fact_orders_1000[truck_types],B55,fact_orders_1000[cost_per_mile]) -> 2.1807172 | F55: =AVERAGEIF(fact_orders_1000[truck_types],B55,fact_orders_1000[delay_minutes]) -> 11.159836 | H55: Metric | I55: Value
B56: Intermodal | C56: =SUMIFS(fact_orders_1000[total_shipments],fact_orders_1000[truck_types],B56) -> 100 | D56: =SUMIFS(fact_orders_1000[on_time_count],fact_orders_1000[truck_types],B56)/C56 -> 0.86 | E56: =AVERAGEIF(fact_orders_1000[truck_types],B56,fact_orders_1000[cost_per_mile]) -> 2.0889 | F56: =AVERAGEIF(fact_orders_1000[truck_types],B56,fact_orders_1000[delay_minutes]) -> 6.4 | H56: Total Fuel Cost | I56: =SUM(fact_orders_1000[fuel_cost_total]) -> 258543.21
B57: Flatbed | C57: =SUMIFS(fact_orders_1000[total_shipments],fact_orders_1000[truck_types],B57) -> 127 | D57: =SUMIFS(fact_orders_1000[on_time_count],fact_orders_1000[truck_types],B57)/C57 -> 0.86614173 | E57: =AVERAGEIF(fact_orders_1000[truck_types],B57,fact_orders_1000[cost_per_mile]) -> 2.3125197 | F57: =AVERAGEIF(fact_orders_1000[truck_types],B57,fact_orders_1000[delay_minutes]) -> 2.6850394 | H57: Total Maintenance | I57: =SUM(fact_orders_1000[maintenance_cost_total]) -> 57716.2
B58: Reefer | C58: =SUMIFS(fact_orders_1000[total_shipments],fact_orders_1000[truck_types],B58) -> 235 | D58: =SUMIFS(fact_orders_1000[on_time_count],fact_orders_1000[truck_types],B58)/C58 -> 0.84255319 | E58: =AVERAGEIF(fact_orders_1000[truck_types],B58,fact_orders_1000[cost_per_mile]) -> 2.3758723 | F58: =AVERAGEIF(fact_orders_1000[truck_types],B58,fact_orders_1000[delay_minutes]) -> 0.17446809 | H58: Total Driver Pay | I58: =SUM(fact_orders_1000[driver_pay_total]) -> 201195.05
B59: Tanker | C59: =SUMIFS(fact_orders_1000[total_shipments],fact_orders_1000[truck_types],B59) -> 50 | D59: =SUMIFS(fact_orders_1000[on_time_count],fact_orders_1000[truck_types],B59)/C59 -> 0.86 | E59: =AVERAGEIF(fact_orders_1000[truck_types],B59,fact_orders_1000[cost_per_mile]) -> 2.5724 | F59: =AVERAGEIF(fact_orders_1000[truck_types],B59,fact_orders_1000[delay_minutes]) -> -0.14 | H59: Average CPM | I59: =AVERAGE(fact_orders_1000[cost_per_mile]) -> 2.25372
B61: 📝 EXECUTIVE SUMMARY
B62: Fleet performance is strong with 82.9% on-time delivery across 1,000 shipments and 260 trucks.
B63: Key focus areas: Detention causes 48.8% of documented delays. Northeast region needs improvement (79.6% on-time).
B64: Dry Van truck type has highest delays (11.2 min avg). Implementing dock scheduling improvements could yield 15% reduction in delay incidents.
B66: 🎯 ACTION ITEMS & RECOMMENDATIONS
B67: Priority | C67: Action Item | D67: Owner | E67: Target | F67: Impact | H67: Report Date: | I67: =TEXT(TODAY(),"MMM DD, YYYY") -> Apr 12, 2026
B68: 🔴 HIGH | C68: Reduce detention delays - dock scheduling | D68: Operations | E68: Q2 2026 | F68: -15% delays | H68: Data Period: | I68: Jan 2025 - Dec 2025
B69: 🔴 HIGH | C69: Address Northeast region delays | D69: Regional Mgr | E69: Q2 2026 | F69: +5% on-time | H69: Total Records: | I69: 1,000 shipments | 260 trucks
B70: 🟠 MEDIUM | C70: Review Dry Van performance | D70: Fleet Mgr | E70: Q3 2026 | F70: +3% on-time | H70: Version: | I70: v1.0 Final
B71: Report Date: | C71: 46124 | E71: Data Period: | F71: Jan 2025 - Dec 2025 | H71: Total Records: | I71: 1,000 shipments | 260 trucks | L71: Version: | M71: v1.0 | O71: Status: | P71: Final

Sheet Key Insights DASHBOARD
B2: 🚛 LOGISTICS & FLEET OPERATIONS - KEY INSIGHTS DASHBOARD
B3: Comprehensive Performance Analysis | Data: 1,000 Shipments | Fleet: 260 Trucks
B5: 📦 TOTAL SHIPMENTS | E5: ✅ ON-TIME DELIVERY RATE | H5: ⏱️ AVERAGE DELAY (MIN) | K5: 🔴 SEVERE DELAYS (>300 min)
B6: =COUNTA(fact_orders_1000[order_id]) -> 1000 | E6: =TEXT(SUM(fact_orders_1000[on_time_count])/COUNTA(fact_orders_1000[order_id]),"0.0%") -> 82.9% | H6: =ROUND(AVERAGE(fact_orders_1000[delay_minutes]),1) -> 6.5 | K6: =COUNTIF(fact_orders_1000[delay_minutes],">300")&" ("&TEXT(COUNTIF(fact_orders_1000[delay_minutes],">300")/COUNTA(fact_orders_1000[order_id]),"0.0%")&")" -> 12 (1.2%)
B8: 📋 KEY INSIGHTS SUMMARY
B9: ="✓ Overall on-time delivery rate: "&TEXT(SUM(fact_orders_1000[on_time_count])/COUNTA(fact_orders_1000[order_id]),"0.0%")&" ("&SUM(fact_orders_1000[on_time_count])&" of "&COUNTA(fact_orders_1000[order_id])&" shipments)" -> ✓ Overall on-time delivery rate: 82.9% (829 of 1000 shipments)
B10: ="✓ Average delay is "&ROUND(AVERAGE(fact_orders_1000[delay_minutes]),0)&" min, indicating most deliveries arrive early" -> ✓ Average delay is 6 min, indicating most deliveries arrive early
B11: ="✓ Detention is the #1 cause of delays ("&TEXT(COUNTIF(fact_orders_1000[Delay Reason],"detention")/COUNTIF(fact_orders_1000[Delay Reason],"<>"),"0.0%")&" of documented delay reasons)" -> ✓ Detention is the #1 cause of delays (6.3% of documented delay reasons)
B12: ="✓ Severe delays (>300 min) represent only "&TEXT(COUNTIF(fact_orders_1000[delay_minutes],">300")/COUNTA(fact_orders_1000[order_id]),"0.0%")&" of shipments" -> ✓ Severe delays (>300 min) represent only 1.2% of shipments
B13: ✓ Compare carrier and regional performance to identify improvement areas
B15: 📊 CARRIER PERFORMANCE | H15: 🗺️ REGIONAL PERFORMANCE | N15: Performance | O15: Count
B16: Carrier | C16: Shipments | D16: On-Time % | E16: Avg Delay | F16: Status | H16: Region | I16: Shipments | J16: On-Time % | K16: Avg Delay | L16: Status | N16: On-Time | O16: =SUM(fact_orders_1000[on_time_count]) -> 829
B17: Sunbelt Haulage | C17: =COUNTIF(fact_orders_1000[carrier_name],"Sunbelt Haulage") -> 112 | D17: =TEXT(SUMIF(fact_orders_1000[carrier_name],"Sunbelt Haulage",fact_orders_1000[on_time_count])/COUNTIF(fact_orders_1000[carrier_name],"Sunbelt Haulage"),"0.0%") -> 81.3% | E17: =ROUND(AVERAGEIF(fact_orders_1000[carrier_name],"Sunbelt Haulage",fact_orders_1000[delay_minutes]),1) -> 12.2 | F17: =IF(AVERAGEIF(fact_orders_1000[carrier_name],"Sunbelt Haulage",fact_orders_1000[delay_minutes])<0,"✅ Early",IF(AVERAGEIF(fact_orders_1000[carrier_name],"Sunbelt Haulage",fact_orders_1000[delay_minutes])<15,"⚠️ OK","🔴 Late")) -> ⚠️ OK | H17: Northeast | I17: =COUNTIF(fact_orders_1000[region],"Northeast") -> 201 | J17: =TEXT(SUMIF(fact_orders_1000[region],"Northeast",fact_orders_1000[on_time_count])/COUNTIF(fact_orders_1000[region],"Northeast"),"0.0%") -> 79.6% | K17: =ROUND(AVERAGEIF(fact_orders_1000[region],"Northeast",fact_orders_1000[delay_minutes]),1) -> 14.5 | L17: =IF(AVERAGEIF(fact_orders_1000[region],"Northeast",fact_orders_1000[delay_minutes])<0,"✅ Early",IF(AVERAGEIF(fact_orders_1000[region],"Northeast",fact_orders_1000[delay_minutes])<15,"⚠️ OK","🔴 Late")) -> ⚠️ OK | N17: Late | O17: =SUM(fact_orders_1000[Late_count]) -> 171
B18: Atlantic Freightways | C18: =COUNTIF(fact_orders_1000[carrier_name],"Atlantic Freightways") -> 72 | D18: =TEXT(SUMIF(fact_orders_1000[carrier_name],"Atlantic Freightways",fact_orders_1000[on_time_count])/COUNTIF(fact_orders_1000[carrier_name],"Atlantic Freightways"),"0.0%") -> 86.1% | E18: =ROUND(AVERAGEIF(fact_orders_1000[carrier_name],"Atlantic Freightways",fact_orders_1000[delay_minutes]),1) -> 11.4 | F18: =IF(AVERAGEIF(fact_orders_1000[carrier_name],"Atlantic Freightways",fact_orders_1000[delay_minutes])<0,"✅ Early",IF(AVERAGEIF(fact_orders_1000[carrier_name],"Atlantic Freightways",fact_orders_1000[delay_minutes])<15,"⚠️ OK","🔴 Late")) -> ⚠️ OK | H18: West | I18: =COUNTIF(fact_orders_1000[region],"West") -> 243 | J18: =TEXT(SUMIF(fact_orders_1000[region],"West",fact_orders_1000[on_time_count])/COUNTIF(fact_orders_1000[region],"West"),"0.0%") -> 83.1% | K18: =ROUND(AVERAGEIF(fact_orders_1000[region],"West",fact_orders_1000[delay_minutes]),1) -> 8.6 | L18: =IF(AVERAGEIF(fact_orders_1000[region],"West",fact_orders_1000[delay_minutes])<0,"✅ Early",IF(AVERAGEIF(fact_orders_1000[region],"West",fact_orders_1000[delay_minutes])<15,"⚠️ OK","🔴 Late")) -> ⚠️ OK
B19: Pacific Linehaul | C19: =COUNTIF(fact_orders_1000[carrier_name],"Pacific Linehaul") -> 103 | D19: =TEXT(SUMIF(fact_orders_1000[carrier_name],"Pacific Linehaul",fact_orders_1000[on_time_count])/COUNTIF(fact_orders_1000[carrier_name],"Pacific Linehaul"),"0.0%") -> 84.5% | E19: =ROUND(AVERAGEIF(fact_orders_1000[carrier_name],"Pacific Linehaul",fact_orders_1000[delay_minutes]),1) -> 10.7 | F19: =IF(AVERAGEIF(fact_orders_1000[carrier_name],"Pacific Linehaul",fact_orders_1000[delay_minutes])<0,"✅ Early",IF(AVERAGEIF(fact_orders_1000[carrier_name],"Pacific Linehaul",fact_orders_1000[delay_minutes])<15,"⚠️ OK","🔴 Late")) -> ⚠️ OK | H19: South | I19: =COUNTIF(fact_orders_1000[region],"South") -> 309 | J19: =TEXT(SUMIF(fact_orders_1000[region],"South",fact_orders_1000[on_time_count])/COUNTIF(fact_orders_1000[region],"South"),"0.0%") -> 82.5% | K19: =ROUND(AVERAGEIF(fact_orders_1000[region],"South",fact_orders_1000[delay_minutes]),1) -> 6 | L19: =IF(AVERAGEIF(fact_orders_1000[region],"South",fact_orders_1000[delay_minutes])<0,"✅ Early",IF(AVERAGEIF(fact_orders_1000[region],"South",fact_orders_1000[delay_minutes])<15,"⚠️ OK","🔴 Late")) -> ⚠️ OK
B20: Blue Ridge Logistics | C20: =COUNTIF(fact_orders_1000[carrier_name],"Blue Ridge Logistics") -> 243 | D20: =TEXT(SUMIF(fact_orders_1000[carrier_name],"Blue Ridge Logistics",fact_orders_1000[on_time_count])/COUNTIF(fact_orders_1000[carrier_name],"Blue Ridge Logistics"),"0.0%") -> 83.5% | E20: =ROUND(AVERAGEIF(fact_orders_1000[carrier_name],"Blue Ridge Logistics",fact_orders_1000[delay_minutes]),1) -> 10.2 | F20: =IF(AVERAGEIF(fact_orders_1000[carrier_name],"Blue Ridge Logistics",fact_orders_1000[delay_minutes])<0,"✅ Early",IF(AVERAGEIF(fact_orders_1000[carrier_name],"Blue Ridge Logistics",fact_orders_1000[delay_minutes])<15,"⚠️ OK","🔴 Late")) -> ⚠️ OK | H20: Midwest | I20: =COUNTIF(fact_orders_1000[region],"Midwest") -> 247 | J20: =TEXT(SUMIF(fact_orders_1000[region],"Midwest",fact_orders_1000[on_time_count])/COUNTIF(fact_orders_1000[region],"Midwest"),"0.0%") -> 85.8% | K20: =ROUND(AVERAGEIF(fact_orders_1000[region],"Midwest",fact_orders_1000[delay_minutes]),1) -> -1.7 | L20: =IF(AVERAGEIF(fact_orders_1000[region],"Midwest",fact_orders_1000[delay_minutes])<0,"✅ Early",IF(AVERAGEIF(fact_orders_1000[region],"Midwest",fact_orders_1000[delay_minutes])<15,"⚠️ OK","🔴 Late")) -> ✅ Early
B21: Cascade Cargo | C21: =COUNTIF(fact_orders_1000[carrier_name],"Cascade Cargo") -> 77 | D21: =TEXT(SUMIF(fact_orders_1000[carrier_name],"Cascade Cargo",fact_orders_1000[on_time_count])/COUNTIF(fact_orders_1000[carrier_name],"Cascade Cargo"),"0.0%") -> 80.5% | E21: =ROUND(AVERAGEIF(fact_orders_1000[carrier_name],"Cascade Cargo",fact_orders_1000[delay_minutes]),1) -> 5.8 | F21: =IF(AVERAGEIF(fact_orders_1000[carrier_name],"Cascade Cargo",fact_orders_1000[delay_minutes])<0,"✅ Early",IF(AVERAGEIF(fact_orders_1000[carrier_name],"Cascade Cargo",fact_orders_1000[delay_minutes])<15,"⚠️ OK","🔴 Late")) -> ⚠️ OK
B22: Lone Star Transport | C22: =COUNTIF(fact_orders_1000[carrier_name],"Lone Star Transport") -> 101 | D22: =TEXT(SUMIF(fact_orders_1000[carrier_name],"Lone Star Transport",fact_orders_1000[on_time_count])/COUNTIF(fact_orders_1000[carrier_name],"Lone Star Transport"),"0.0%") -> 81.2% | E22: =ROUND(AVERAGEIF(fact_orders_1000[carrier_name],"Lone Star Transport",fact_orders_1000[delay_minutes]),1) -> 4.2 | F22: =IF(AVERAGEIF(fact_orders_1000[carrier_name],"Lone Star Transport",fact_orders_1000[delay_minutes])<0,"✅ Early",IF(AVERAGEIF(fact_orders_1000[carrier_name],"Lone Star Transport",fact_orders_1000[delay_minutes])<15,"⚠️ OK","🔴 Late")) -> ⚠️ OK | H22: ⚠️ DELAY REASONS BREAKDOWN
B23: Midwest Express Trucking | C23: =COUNTIF(fact_orders_1000[carrier_name],"Midwest Express Trucking") -> 92 | D23: =TEXT(SUMIF(fact_orders_1000[carrier_name],"Midwest Express Trucking",fact_orders_1000[on_time_count])/COUNTIF(fact_orders_1000[carrier_name],"Midwest Express Trucking"),"0.0%") -> 81.5% | E23: =ROUND(AVERAGEIF(fact_orders_1000[carrier_name],"Midwest Express Trucking",fact_orders_1000[delay_minutes]),1) -> 4.2 | F23: =IF(AVERAGEIF(fact_orders_1000[carrier_name],"Midwest Express Trucking",fact_orders_1000[delay_minutes])<0,"✅ Early",IF(AVERAGEIF(fact_orders_1000[carrier_name],"Midwest Express Trucking",fact_orders_1000[delay_minutes])<15,"⚠️ OK","🔴 Late")) -> ⚠️ OK | H23: Delay Reason | I23: Count | J23: % of Delays | K23: Bar
B24: Desert Road Haulers | C24: =COUNTIF(fact_orders_1000[carrier_name],"Desert Road Haulers") -> 49 | D24: =TEXT(SUMIF(fact_orders_1000[carrier_name],"Desert Road Haulers",fact_orders_1000[on_time_count])/COUNTIF(fact_orders_1000[carrier_name],"Desert Road Haulers"),"0.0%") -> 83.7% | E24: =ROUND(AVERAGEIF(fact_orders_1000[carrier_name],"Desert Road Haulers",fact_orders_1000[delay_minutes]),1) -> -2.1 | F24: =IF(AVERAGEIF(fact_orders_1000[carrier_name],"Desert Road Haulers",fact_orders_1000[delay_minutes])<0,"✅ Early",IF(AVERAGEIF(fact_orders_1000[carrier_name],"Desert Road Haulers",fact_orders_1000[delay_minutes])<15,"⚠️ OK","🔴 Late")) -> ✅ Early | H24: Detention | I24: =COUNTIF(fact_orders_1000[Delay Reason],"detention") -> 63 | J24: =TEXT(COUNTIF(fact_orders_1000[Delay Reason],"detention")/COUNTIF(fact_orders_1000[Delay Reason],"<>"),"0.0%") -> 6.3% | K24: =REPT("█",ROUND(COUNTIF(fact_orders_1000[Delay Reason],"detention")/COUNTIF(fact_orders_1000[Delay Reason],"<>")*20,0)) -> █
B25: Great Lakes Carriers | C25: =COUNTIF(fact_orders_1000[carrier_name],"Great Lakes Carriers") -> 80 | D25: =TEXT(SUMIF(fact_orders_1000[carrier_name],"Great Lakes Carriers",fact_orders_1000[on_time_count])/COUNTIF(fact_orders_1000[carrier_name],"Great Lakes Carriers"),"0.0%") -> 83.8% | E25: =ROUND(AVERAGEIF(fact_orders_1000[carrier_name],"Great Lakes Carriers",fact_orders_1000[delay_minutes]),1) -> -2.6 | F25: =IF(AVERAGEIF(fact_orders_1000[carrier_name],"Great Lakes Carriers",fact_orders_1000[delay_minutes])<0,"✅ Early",IF(AVERAGEIF(fact_orders_1000[carrier_name],"Great Lakes Carriers",fact_orders_1000[delay_minutes])<15,"⚠️ OK","🔴 Late")) -> ✅ Early | H25: Traffic | I25: =COUNTIF(fact_orders_1000[Delay Reason],"traffic") -> 41 | J25: =TEXT(COUNTIF(fact_orders_1000[Delay Reason],"traffic")/COUNTIF(fact_orders_1000[Delay Reason],"<>"),"0.0%") -> 4.1% | K25: =REPT("█",ROUND(COUNTIF(fact_orders_1000[Delay Reason],"traffic")/COUNTIF(fact_orders_1000[Delay Reason],"<>")*20,0)) -> █
B26: Keystone Freight | C26: =COUNTIF(fact_orders_1000[carrier_name],"Keystone Freight") -> 71 | D26: =TEXT(SUMIF(fact_orders_1000[carrier_name],"Keystone Freight",fact_orders_1000[on_time_count])/COUNTIF(fact_orders_1000[carrier_name],"Keystone Freight"),"0.0%") -> 83.1% | E26: =ROUND(AVERAGEIF(fact_orders_1000[carrier_name],"Keystone Freight",fact_orders_1000[delay_minutes]),1) -> -3.8 | F26: =IF(AVERAGEIF(fact_orders_1000[carrier_name],"Keystone Freight",fact_orders_1000[delay_minutes])<0,"✅ Early",IF(AVERAGEIF(fact_orders_1000[carrier_name],"Keystone Freight",fact_orders_1000[delay_minutes])<15,"⚠️ OK","🔴 Late")) -> ✅ Early | H26: Weather | I26: =COUNTIF(fact_orders_1000[Delay Reason],"weather") -> 20 | J26: =TEXT(COUNTIF(fact_orders_1000[Delay Reason],"weather")/COUNTIF(fact_orders_1000[Delay Reason],"<>"),"0.0%") -> 2.0% | K26: =REPT("█",ROUND(COUNTIF(fact_orders_1000[Delay Reason],"weather")/COUNTIF(fact_orders_1000[Delay Reason],"<>")*20,0))
H27: Mechanical | I27: =COUNTIF(fact_orders_1000[Delay Reason],"mechanical") -> 5 | J27: =TEXT(COUNTIF(fact_orders_1000[Delay Reason],"mechanical")/COUNTIF(fact_orders_1000[Delay Reason],"<>"),"0.0%") -> 0.5% | K27: =REPT("█",ROUND(COUNTIF(fact_orders_1000[Delay Reason],"mechanical")/COUNTIF(fact_orders_1000[Delay Reason],"<>")*20,0))
B28: 🚚 TRUCK TYPE PERFORMANCE
B29: Truck Type | C29: Shipments | D29: On-Time % | E29: Avg CPM | F29: Avg Delay | H29: 💰 COST SUMMARY
B30: Dry Van | C30: 488 | D30: 0.803 | E30: 2.18 | F30: 11.2 | H30: Total Fuel Cost | J30: =TEXT(SUM(fact_orders_1000[fuel_cost_total]),"$#,##0") -> $258,543
B31: Intermodal | C31: 100 | D31: 0.86 | E31: 2.09 | F31: 6.4 | H31: Total Maintenance | J31: =TEXT(SUM(fact_orders_1000[maintenance_cost_total]),"$#,##0") -> $57,716
B32: Flatbed | C32: 127 | D32: 0.866 | E32: 2.31 | F32: 2.7 | H32: Total Driver Pay | J32: =TEXT(SUM(fact_orders_1000[driver_pay_total]),"$#,##0") -> $201,195
B33: Reefer | C33: 235 | D33: 0.843 | E33: 2.38 | F33: 0.2 | H33: Avg Cost Per Mile | J33: =TEXT(AVERAGE(fact_orders_1000[cost_per_mile]),"$0.00") -> $2.25
B34: Tanker | C34: 50 | D34: 0.86 | E34: 2.57 | F34: -0.1
B35: 📈 VISUAL ANALYTICS - CARRIER PERFORMANCE
N38: Carrier | O38: On-Time %
N39: Atlantic Freightways | O39: =SUMIFS(fact_orders_1000[on_time_count],fact_orders_1000[carrier_name],"Atlantic Freightways")/SUMIFS(fact_orders_1000[total_shipments],fact_orders_1000[carrier_name],"Atlantic Freightways") -> 0.86111111
N40: Blue Ridge Logistics | O40: =SUMIFS(fact_orders_1000[on_time_count],fact_orders_1000[carrier_name],"Blue Ridge Logistics")/SUMIFS(fact_orders_1000[total_shipments],fact_orders_1000[carrier_name],"Blue Ridge Logistics") -> 0.83539095
N41: Cascade Cargo | O41: =SUMIFS(fact_orders_1000[on_time_count],fact_orders_1000[carrier_name],"Cascade Cargo")/SUMIFS(fact_orders_1000[total_shipments],fact_orders_1000[carrier_name],"Cascade Cargo") -> 0.80519481
N42: Desert Road Haulers | O42: =SUMIFS(fact_orders_1000[on_time_count],fact_orders_1000[carrier_name],"Desert Road Haulers")/SUMIFS(fact_orders_1000[total_shipments],fact_orders_1000[carrier_name],"Desert Road Haulers") -> 0.83673469
N43: Great Lakes Carriers | O43: =SUMIFS(fact_orders_1000[on_time_count],fact_orders_1000[carrier_name],"Great Lakes Carriers")/SUMIFS(fact_orders_1000[total_shipments],fact_orders_1000[carrier_name],"Great Lakes Carriers") -> 0.8375
N44: Keystone Freight | O44: =SUMIFS(fact_orders_1000[on_time_count],fact_orders_1000[carrier_name],"Keystone Freight")/SUMIFS(fact_orders_1000[total_shipments],fact_orders_1000[carrier_name],"Keystone Freight") -> 0.83098592
N45: Lone Star Transport | O45: =SUMIFS(fact_orders_1000[on_time_count],fact_orders_1000[carrier_name],"Lone Star Transport")/SUMIFS(fact_orders_1000[total_shipments],fact_orders_1000[carrier_name],"Lone Star Transport") -> 0.81188119
N46: Midwest Express Trucking | O46: =SUMIFS(fact_orders_1000[on_time_count],fact_orders_1000[carrier_name],"Midwest Express Trucking")/SUMIFS(fact_orders_1000[total_shipments],fact_orders_1000[carrier_name],"Midwest Express Trucking") -> 0.81521739
N47: Pacific Linehaul | O47: =SUMIFS(fact_orders_1000[on_time_count],fact_orders_1000[carrier_name],"Pacific Linehaul")/SUMIFS(fact_orders_1000[total_shipments],fact_orders_1000[carrier_name],"Pacific Linehaul") -> 0.84466019
N48: Sunbelt Haulage | O48: =SUMIFS(fact_orders_1000[on_time_count],fact_orders_1000[carrier_name],"Sunbelt Haulage")/SUMIFS(fact_orders_1000[total_shipments],fact_orders_1000[carrier_name],"Sunbelt Haulage") -> 0.8125
B52: 📅 Data Source: fact_orders_1000 (1,000 shipments) | dim_fleet_260 (260 trucks) | Dashboard auto-updates with source data
B54: 🎨 Perfrmance Guide: 🟢 >84% = Top Performer | 🔵 81-84% = Average | 🟠 <81% = Needs
